Workbook
Name A1.: 'ABISINIA INSS'!$A$2213
Name A1.: 'ACOPIO ABISINIA'!$A$2204
Name A1.: 'ACOPIO EL CONSUELO'!$A$2205
Name A1.: 'ACOPIO ESCAMBRAY'!$A$2204
Name A1.: 'ACOPIO LAS MORENAS 2'!$A$2204
Name A1.: 'ACOPIO MONTECRISTO'!$A$2206
Name A1.: 'ACOPIO STA ISABEL'!$A$2204
Name A1.: 'ADMON COM. '!$A$2300
Name A1.: 'BODEG STA Isabel'!$A$2213
Name A1.: 'BODEGA-ACOPIO'!$A$2208
Name A1.: 'COMISARIATO INSS'!$A$2213
Name A1.: 'COMISARIATO SIN INSS'!$A$2209
Name A1.: 'FINANCIAMIENTO INSS'!$A$2211
Name A1.: FINCA!$A$2205
Name A1.: 'FINCA INSS '!$A$2225
Name A1.: 'FINCA SIN INSS'!$A$2216
Name A1.: 'PERS-ACOPIO STA ISABEL'!$A$2218
Name A1.: TECNICOS!$A$2208

Sheet DETALLE ADMON.
A1: AGRICOLA SANTA ISABEL
A2: QUINCENA DEL 16 AL 30 DE ABRIL 2026
A4: PLANILLA | B4: TOTAL | C4: FEMENINO | D4: MASCULINO | E4: CON INSS | F4: SIN INSS | G4: TOTAL NOMINA | H4: FINCA | I4: TOTAL A PAGAR | J4: COMISARIATO | K4: NETO A PAGAR
A5: ADMINISTRACION FINCA | E5: =+ADMON!X21 -> 36121.381 | G5: =+E5+F5 -> 36121.381 | H5: =+ADMON!Z21 -> 1500 | I5: =+G5-H5 -> 34621.381 | J5: =+ADMON!AB21 -> 808 | K5: =G5-H5-J5 -> 33813.381
A6: ADMINISTRACION COMERCIAL | B6: =+C6+D6 -> 7 | C6: =COUNTIF('ADMON COM. '!E18:E29,"F")+H!I16 -> 2 | D6: =COUNTIF('ADMON COM. '!E18:E29,"M")+H!J16 -> 5 | E6: =+'ADMON COM. '!T30 -> 57799.001 | F6: =+H!BP15 -> 0 | G6: =+E6+F6 -> 57799.001 | H6: =+'ADMON COM. '!V30 -> 500 | I6: =+G6-H6 -> 57299.001 | J6: 0 | K6: =G6-H6-J6 -> 57299.001
A7: FINCA SIN INSS | B7: =+C7+D7 -> 1 | C7: 0 | D7: 1 | E7: 0 | F7: =+'FINCA SIN INSS'!X15 -> 36647.945 | G7: =+E7+F7 -> 36647.945 | H7: ='FINCA SIN INSS'!Y15 -> 2500 | I7: ='FINCA SIN INSS'!Z15 -> 34147.945 | J7: =+'FINCA SIN INSS'!AA15 -> 2000 | K7: =G7-H7-J7 -> 32147.945
A8: FINCA CON INSS | E8: =+'FINCA INSS '!W17 -> 0 | F8: 0 | G8: =+E8+F8 -> 0 | H8: =+'FINCA INSS '!Z17 -> 0 | I8: =+G8-H8 -> 0 | J8: =+'FINCA INSS '!AC17 -> 195 | K8: =+I8-J8 -> -195
A9: BENEFICIO SECO SIN INSS | B9: =+C9+D9 -> 3 | C9: 2 | D9: 1 | E9: 0 | F9: =+'BENEFICIO SECO'!X13 -> 0 | G9: =+E9+F9 -> 0 | H9: =+'BENEFICIO SECO'!Y13 -> 0 | I9: =+G9-H9 -> 0 | J9: 0 | K9: =+I9-J9 -> 0
A10: COMPLEMENTO DE SALARIO | B10: =+C10+D10 -> 2 | C10: 1 | D10: 1 | E10: 0 | F10: =+'COMPLEMENTO DE SALARIO'!C12 -> 5009.2 | G10: =+E10+F10 -> 5009.2 | H10: ='COMPLEMENTO DE SALARIO'!D12 -> 0 | I10: =+G10-H10 -> 5009.2 | J10: =+'COMPLEMENTO DE SALARIO'!F12 -> 0 | K10: =G10-H10-J10 -> 5009.2
A11: EVENTUAL | E11: 0 | F11: =+EVENTUAL!C14 -> 36966.984 | G11: =E11+F11 -> 36966.984 | H11: =+EVENTUAL!D14 -> 0 | I11: =+G11-H11 -> 36966.984 | J11: 0 | K11: =G11-H11-J11 -> 36966.984
A12: ABISINIA-INSS | E12: =+'ABISINIA INSS'!Z12 -> 3664.53 | F12: 0 | G12: =E12+F12 -> 3664.53 | H12: 0 | I12: =+G12-H12 -> 3664.53 | J12: 0 | K12: =G12-H12-J12 -> 3664.53
A13: BODEGA DE ACOPIO | E13: ='BODEG STA Isabel'!W12 -> 4275 | F13: 0 | G13: =+E13+F13 -> 4275 | H13: ='BODEG STA Isabel'!Y12 -> 2000 | I13: =+G13-H13 -> 2275 | J13: =+#REF! -> #REF! | K13: =+I13-J13 -> #REF!
A14: ACOPIO MONTECRISTO | E14: 0 | F14: =+'ACOP MONTECRISTO'!X12 -> 0 | G14: =+E14+F14 -> 0 | H14: =+'ACOP MONTECRISTO'!Y12 -> 0 | I14: =+G14-H14 -> 0 | J14: =+'ACOP MONTECRISTO'!AB12 -> 0 | K14: =+I14-J14 -> 0
A15: ACOPIO LAS MORENAS | E15: 0 | F15: =+'ACOP LAS MORENAS'!X13 -> 0 | G15: =+E15+F15 -> 0 | H15: =+'ACOP LAS MORENAS'!Y13 -> 0 | I15: =+G15-H15 -> 0 | J15: 0 | K15: =+G15-H15-J15 -> 0
A16: ACOPIO ABISINIA SIN INSS | E16: 0 | F16: =+'ACOP ABISINIA SIN INSS'!X14 -> 0 | G16: =+E16+F16 -> 0 | H16: =+'ACOP ABISINIA SIN INSS'!Z14 -> 0 | I16: =+G16-H16 -> 0 | J16: 0 | K16: =+G16-H16-J16 -> 0
A17: ACOPIO EL CONSUELO | E17: 0 | F17: =+'ACOP EL CONSUELO'!X12 -> 0 | G17: =+E17+F17 -> 0 | H17: =+'ACOP EL CONSUELO'!Y12 -> 0 | I17: =+G17-H17 -> 0 | J17: 0 | K17: =+G17-H17-J17 -> 0
A18: VIATICOS PERSONAL DE ACOPIO | E18: 0 | F18: =+'VIATICOS ACOPIO'!F18 -> 0 | G18: =+E18+F18 -> 0 | H18: =+'ACOP LA UNION'!Y9 -> 0 | I18: =+G18-H18 -> 0 | J18: 0 | K18: =+G18-H18-J18 -> 0
E19: 0 | F19: 0 | G19: =+E19+F19 -> 0 | H19: 0 | I19: =+G19-H19 -> 0 | J19: 0 | K19: =+G19-H19-J19 -> 0
A20: COMPLEMENTO DE SALARIO EN RECIBO | E20: 0 | F20: 0 | G20: =+E20+F20 -> 0 | H20: 0 | I20: 0 | J20: 0 | K20: =+G20-H20-J20 -> 0
A21: PAGO DE VIAJE DE CAMIONERO | E21: 0 | F21: 0 | G21: =+E21+F21 -> 0 | H21: 0 | I21: 0 | J21: 0 | K21: =+G21-H21-J21 -> 0
A22: TOTAL | E22: =SUM(E5:E21) -> 101859.91 | F22: =SUM(F5:F21) -> 78624.129 | G22: =SUM(G5:G21) -> 180484.04 | H22: =SUM(H5:H21) -> 6500 | I22: =SUM(I5:I21) -> 173984.04 | J22: =SUM(J5:J21) -> #REF! | K22: =SUM(K5:K21) -> #REF!
N26: =G22-H22-J22 -> #REF!
A27: _______________________________ | E27: ______________________________________ | H27: ________________________________________________
A28: REVISADO | E28: AUTORIZADO | H28: IVAN OROZCO OSEJO
A29: Ivan Orozco Osejo | E29: Lic. Osman Gregorio Gutierrez Moreno | I29: Auxiliar Contable

Sheet Cambio del dia
F7: Dias | G7: Dólar
F8: 1
F9: 2
F10: 3
F11: 4
F12: 5
F13: 6
F14: 7
F15: 8
F16: 9
F17: 10
F18: 11
F19: 12
F20: 13
F21: 14 | G21: 0
F22: 15 | G22: 36.6243
F23: 16 | G23: 36.6243
F24: 17 | G24: 36.6243
F25: 18 | G25: 36.6243
F26: 19 | G26: 36.6243
F27: 20 | G27: 36.6243
F28: 21 | G28: 36.6243
F29: 22 | G29: 36.6243
F30: 23 | G30: 36.6243
F31: 24 | G31: 36.6243
F32: 25 | G32: 36.6243
... F38: 31 | G38: 36.6243
A44: No | B44: INSS | C44: NUMERO DE CEDULA | D44: NOMBRES Y APELLIDOS | E44: GENERO | F44: CARGO | G44: salario en dolares | H44: cambio del dia | I44: SALARIO MENSUAL | J44: I N G R E S O S | M44: RETENCIONES | Q44: TOTAL DEVENGADO | R44: ALIMENTACION | S44: FINCA | T44: COMISARIATO | U44: TOTAL A PAGAR | V44: FIRMAS | W44: VACACIONES | X44: 13vo mes | Y44: TOTAL GASTOS NOMINAS
J45: SALARIO QUINCENAL | K45: DIAS LABORADOS | L45: TOTAL INGRESOS | M45: INSS LABORAL | N45: IR | O45: ABONO RESTAMOS | P45: TOTAL RETENCION
A47: 1 | B47: 7288164 | C47: 241-250163-0005Q | D47: PASTOR DE JESUS CHAVARRIA HERRERA | E47: M | F47: CONTADOR GENERAL | G47: 1000 | H47: =+G38 -> 36.6243 | I47: =+G47*H47 -> 36624.3 | J47: =+I47/30*K47 -> 18312.15 | K47: 15 | L47: =+J47 -> 18312.15 | M47: 0 | N47: 0 | O47: 1090.524 | P47: 1090.524 | Q47: =+L47-O47 -> 17221.626 | S47: 0 | T47: 0 | U47: =+Q47 -> 17221.626 | V47: 1 | W47: 776.93777 | X47: 776.93777 | Y47: =+U47+W47+X47 -> 18775.502
A48: 2 | B48: 17814360 | C48: 288-210859-0001M | D48: PEDRO JOAQUIN HUETE | E48: M | F48: MANDADOR FINCA | G48: 510 | H48: =+G36 -> 36.6243 | I48: 18678.4 | J48: =+I48/30*K48 -> 9339.2 | K48: 15 | L48: =+J48 -> 9339.2 | M48: 0 | N48: 0 | O48: 0 | P48: 0 | Q48: =+L48 -> 9339.2 | R48: 0 | S48: 0 | T48: 0 | U48: =+Q48-S48 -> 9339.2 | V48: 3 | W48: 908.77 | X48: 908.77 | Y48: =+U48+W48+X48 -> 11156.74
A49: 3 | D49: YEMIN DAVID GUTIERREZ MORENO | E49: M | F49: DILLERO | G49: 182.08 | H49: 36.6243 | I49: =+G49*H49 -> 6668.5525 | J49: =+I49/30*K49 -> 3334.2763 | K49: 15 | L49: =+J49 -> 3334.2763 | O49: 0 | P49: 0 | Q49: =+L49 -> 3334.2763 | R49: 0 | U49: =+Q49-S49 -> 3334.2763 | W49: 908.77 | X49: 908.77 | Y49: =+U49+W49+X49 -> 5151.8163
A50: 4 | B50: 6983178 | C50: 601-120863-0000N | D50: JOAQUIN ENRRIQUE CASTILLO CARCACHE | E50: M | F50: TECNICO | G50: 350 | H50: =+G35 -> 36.6243 | I50: =+G50*H50 -> 12818.505 | J50: =+I50/30*K50 -> 6409.2525 | K50: 15 | L50: =+J50 -> 6409.2525 | M50: 0 | N50: 0 | O50: 0 | P50: 0 | Q50: =+L50 -> 6409.2525 | R50: 0 | S50: 0 | T50: 0 | U50: =+Q50-S50 -> 6409.2525 | V50: 3 | W50: 908.77 | X50: 908.77 | Y50: =+U50+W50+X50 -> 8226.7925
A51: 4 | B51: 6983178 | C51: 601-120863-0000N | D51: LUIS FERNANDO PALACIOS RIOS | E51: M | F51: TECNICO | G51: 350 | H51: =+G35 -> 36.6243 | I51: =+G51*H51 -> 12818.505 | J51: =+I51/30*K51 -> 6409.2525 | K51: 15 | L51: =+J51 -> 6409.2525 | M51: 0 | N51: 0 | O51: 0 | P51: 0 | Q51: =+L51 -> 6409.2525 | R51: 0 | S51: 0 | T51: 0 | U51: =+Q51-S51 -> 6409.2525 | V51: 3 | W51: 908.77 | X51: 908.77 | Y51: =+U51+W51+X51 -> 8226.7925
A52: 4 | B52: 6983178 | C52: 601-120863-0000N | D52: MARTIN CONRRADO RIZO | E52: M | F52: PLANILLAS | G52: 327.6515 | H52: =+G35 -> 36.6243 | I52: =+G52*H52 -> 12000.007 | J52: =+I52/30*K52 -> 6000.0034 | K52: 15 | L52: =+J52 -> 6000.0034 | M52: 0 | N52: 0 | O52: 0 | P52: 0 | Q52: =+L52 -> 6000.0034 | R52: 0 | S52: 0 | T52: 0 | U52: =+Q52-S52 -> 6000.0034 | V52: 3 | W52: 908.77 | X52: 908.77 | Y52: =+U52+W52+X52 -> 7817.5434
A53: 4 | B53: 6983178 | C53: 601-120863-0000N | D53: =+'ADMON COM. '!D20 -> NELLY DEL CARMEN SOBALVARRO THOMAS | E53: F | F53: TECNICO | G53: =+'ADMON COM. '!G20 -> 298.9818 | H53: =+G36 -> 36.6243 | I53: =+G53*H53 -> 10949.999 | J53: =+I53/30*K53 -> 5474.9996 | K53: 15 | L53: =+J53 -> 5474.9996 | M53: 0 | N53: 0 | O53: 0 | P53: 0 | Q53: =+L53 -> 5474.9996 | R53: 0 | S53: 0 | T53: 0 | U53: =+Q53-S53 -> 5474.9996 | V53: 3 | W53: 908.77 | X53: 908.77 | Y53: =+U53+W53+X53 -> 7292.5396
L54: 18

Sheet FINCA
A1: AGRÍCOLA SANTA ISABEL
A2: PLANILLA DE SALARIO QUINCENAL DE TÉCNICOS DE ACOPIO
A3: =+'ADMON COM. '!A5:AC5 -> QUINCENA DEL 16 AL 30 DE ABRIL - 2026
A4: =+'ADMON COM. '!A6 -> 15
A5: No | B5: INSS | C5: NUMERO DE CEDULA | D5: NOMBRES Y APELLIDOS | E5: GENERO | F5: CARGO | G5: salario en dolares | H5: cambio del dia | I5: SALARIO DIARIO | J5: SALARIO MENSUAL | K5: I N G R E S O S | Q5: RETENCIONES | U5: TOTAL | V5: ALIMENTACION | W5: FINCA | X5: COMISARIATO | Y5: SALARIO DEVENGADO | Z5: FIRMAS | AA5: VACASIONES | AB5: 13VO MES | AC5: INSS PATRONAL | AD5: INATEC 2% | AE5: TOTAL GASTOS NOMINAS
K6: SALARIO QUINCENAL | L6: DIAS LABORADOS | M6: total subcidio | N6: subcidio por dia | O6: DIAS SUBSIDIO | P6: TOTAL INGRESOS | Q6: INSS LABORAL | R6: IR | S6: ABONO POR PRESTAMOS | T6: TOTAL RETENCION
A8: 1 | B8: 5357574 | C8: 0 | D8: =+'ADMON COM. '!#REF! -> #REF! | E8: M | F8: ADMINISTRADOR | G8: 500 | H8: =LOOKUP(A4,'Cambio del dia'!F7:G38) -> 36.6243 | I8: =+K8/L8 -> #REF! | J8: =+H8*G8 -> 18312.15 | K8: =+(J8/30)*L8-'ADMON COM. '!#REF! -> #REF! | L8: 16 | M8: =+N8*O8 -> #REF! | N8: =I8*60% -> #REF! | O8: 0 | P8: =+K8-M8 -> #REF! | Q8: 0 | R8: 0 | T8: =+Q8+R8+S8 -> 0 | U8: =-T8+P8 -> #REF! | V8: 0 | Y8: =+P8 -> #REF! | AA8: =+J8/30*1.25 -> 763.00625 | AB8: =+J8/30*1.25 -> 763.00625 | AC8: =IF(B8="",0,P8*21.5%) -> #REF! | AD8: =IF(Q8>0,P8*2%,0) -> 0 | AE8: =SUM(P8,AC8,AB8,AA8,AD8) -> #REF!
A9: TOTALES | G9: =SUM(G8:G8) -> 500 | I9: =SUM(I8:I8) -> #REF! | J9: =SUM(J8:J8) -> 18312.15 | K9: =SUM(K8:K8) -> #REF! | L9: =SUM(L8:L8) -> 16 | M9: =+N9*O9 -> #REF! | N9: =I9*60% -> #REF! | O9: =SUM(O8:O8) -> 0 | P9: =SUM(P8:P8) -> #REF! | Q9: =SUM(Q8:Q8) -> 0 | R9: =SUM(R8:R8) -> 0 | S9: =SUM(S8:S8) -> 0 | T9: =SUM(T8:T8) -> 0 | U9: =SUM(U8:U8) -> #REF! | V9: =SUM(V8:V8) -> 0 | ... Y9: =SUM(Y8:Y8) -> #REF! | Z9: "EL SEÑOR ES MI PASTOR, NADA ME FALTARA" | AA9: =SUM(AA8:AA8) -> 763.00625 | AB9: =SUM(AB8:AB8) -> 763.00625 | AC9: =SUM(AC8:AC8) -> #REF! | AD9: =SUM(AD8:AD8) -> 0 | AE9: =SUM(AE8:AE8) -> #REF!
C20: ELABORADO POR: | L20: REVISADO POR: | Y20: AUTORIZADO POR:
C21: =+'ADMON COM. '!C50:F50 -> Jose Martin Conrrado | L21: Lic. Pastor de Jesús Chavarría Herrera | Y21: Lic. Osman Gregorio Gutiérrez Moreno

Sheet H
A3: JINOTEGA, NICARAGUA
A4: ACOPIO OSMAN GUTIERREZ
A5: PLANILLA DE SALARIO QUINCENAL PERSONAL ADMINISTRATIVO
A6: =+'COMISARIATO CON INSS'!A4 -> QUINCENA DEL 16 AL 30 DE ABRIL - 2026
A11: =+'ADMON COM. '!A6 -> 15
A12: No. | B12: SALARIO | C12: dolares | D12: cambio | E12: mensual | F12: 14cenal | G12: NOMBRES Y APELLIDOS | H12: SALARIO DIARIO | I12: GENERO | J12: Actividad | K12: =+'COMISARIATO CON INSS'!H7 -> 16 | L12: =+'COMISARIATO CON INSS'!I7 -> 17 | M12: =+'COMISARIATO CON INSS'!J7 -> 18 | N12: =+'COMISARIATO CON INSS'!K7 -> 19 | O12: =+'COMISARIATO CON INSS'!L7 -> 20 | P12: =+'COMISARIATO CON INSS'!M7 -> 21 | Q12: =+'COMISARIATO CON INSS'!N7 -> 22 | R12: 1 semana | S12: SEPTIMO DIA | T12: =+'COMISARIATO CON INSS'!Q7 -> 23 | U12: =+'COMISARIATO CON INSS'!R7 -> 24 | V12: =+'COMISARIATO CON INSS'!S7 -> 25 | W12: =+'COMISARIATO CON INSS'!T7 -> 26 | X12: =+'COMISARIATO CON INSS'!U7 -> 27 | Y12: =+'COMISARIATO CON INSS'!V7 -> 28 | Z12: =+'COMISARIATO CON INSS'!W7 -> 29 | AA12: =+'COMISARIATO CON INSS'!X7 -> 30 | AB12: 16 | AC12: 2 semana | AD12: SEPTIMO DIA | AE12: SUMA SETIMOS | AF12: SUMA DIAS | AG12: DIAS TRABAJADOS | AH12: FERIADOS/ LIBRES | AI12: HRS EXT | AJ12: DOM LAB | AK12: SALARIO BASICO | AN12: SEPTIMO DIA | AO12: COSTE DIA | AP12: COSTE HORA | AQ12: DOMINGOS TRABAJADOS | AR12: HORAS EXTRAS | AS12: DIAS FERIADOS | AT12: Extras y/o Dom. Trab | AU12: DIAS | AV12: SALARIO | AW12: DODIGO | AX12: CONSTANTE | AY12: SALARIO 14CENAL | AZ12: FORMUAL | BA12: FORMULA | BB12: FORMULA | BC12: TOTAOL | BD12: adicional | BE12: INGRESO BASICO | BG12: INSS | BH12: VACASIONES | BI12: 13VO MES | BJ12: TOTAL INGRESOS | BN12: SALARIO NETO | BO12: ALIMENTACION | BP12: NETO A PAGAR | BQ12: RECIBIDO CONFORME
K14: =+'COMISARIATO CON INSS'!H9 -> S | L14: =+'COMISARIATO CON INSS'!I9 -> D | M14: =+'COMISARIATO CON INSS'!J9 -> L | N14: =+'COMISARIATO CON INSS'!K9 -> M | O14: =+'COMISARIATO CON INSS'!L9 -> M | P14: =+'COMISARIATO CON INSS'!M9 -> J | Q14: =+'COMISARIATO CON INSS'!N9 -> V | T14: =+'COMISARIATO CON INSS'!Q9 -> S | U14: =+'COMISARIATO CON INSS'!R9 -> D | V14: =+'COMISARIATO CON INSS'!S9 -> L | W14: =+'COMISARIATO CON INSS'!T9 -> M | X14: =+'COMISARIATO CON INSS'!U9 -> M | Y14: =+'COMISARIATO CON INSS'!V9 -> J | Z14: =+'COMISARIATO CON INSS'!W9 -> V | AA14: =+'COMISARIATO CON INSS'!X9 -> S | AB14: =+'COMISARIATO CON INSS'!Y9 -> D
A15: 1 | B15: =+F15 -> 313.19881 | C15: 256.55 | D15: =VLOOKUP(A11,'Cambio del dia'!F7:G38,2,1) -> 36.6243 | E15: =+D15*C15 -> 9395.9642 | F15: =+E15/30 -> 313.19881 | G15: HENRY RIZO HERNANDEZ | H15: 147.16 | I15: M | J15: PLANILLA Y BODEGAS | K15: 0 | L15: 0 | M15: 0 | N15: 0 | O15: 0 | P15: 0 | Q15: 0 | R15: =COUNTIF(K15:Q15,147.16) -> 0 | S15: =COUNTIF(R15,6) -> 0 | T15: 0 | U15: 0 | V15: 0 | W15: 0 | X15: 0 | Y15: 0 | Z15: 0 | AA15: 0 | AB15: 0 | AC15: =COUNTIF(T15:Z15,147.16) -> 0 | AD15: =COUNTIF(AC15,6) -> 0 | AE15: =+AD15+S15 -> 0 | AF15: =COUNTIF(K15:AD15,147.16) -> 0 | AG15: =+AF15+AE15+AJ15+AH15 -> 0 | AH15: 0 | AI15: 0 | AJ15: =+W15+N15 -> 0 | AK15: =+AB15+Y15+X15+V15+U15+T15+Q15+P15+O15+M15+L15+K15+AA15+Z15 -> 0 | AL15: 147.16 | AM15: =H15*AD15 -> 0 | AN15: =+AL15*S15+AM15*AD15 -> 0 | AO15: =+H15 -> 147.16 | AP15: =+H15/8 -> 18.395 | AQ15: =+AO15*AJ15 -> 0 | AR15: =+AP15*AI15 -> 0 | AS15: =+AH15*H15 -> 0 | AT15: =+AL15*N15+AM15*W15 -> 0 | AU15: =+AG15 -> 0 | AV15: =+B15 -> 313.19881 | AW15: 124 | AX15: 0.857142 | AY15: =AU15*AV15 -> 0 | AZ15: =+AY15-BI15 -> 0 | BA15: =AU15*AW15*AX15 -> 0 | BB15: 0.8333 | BC15: =+AN15+AK15 -> 0 | BD15: =+BJ15-BC15 -> 0 | BE15: =+AY15 -> 0 | BF15: 0 | BG15: =BK15*5% -> 0 | BH15: =+BE15/12 -> 0 | BI15: =+BH15 -> 0 | BJ15: =BE15 -> 0 | BK15: =+BJ15-BI15 -> 0 | BL15: 5 | BM15: 0 | BN15: =+BJ15-BM15 -> 0 | BO15: 0 | BP15: =+BN15+BO15+AR15-BG15 -> 0 | BQ15: =+A15 -> 1
I16: =COUNTIF(I15,"F") -> 0
BB18: 3570.2
T26: _______________________________________________ | AT26: ____________________________________
G27: ELABORADO | U27: REVISADO | AT27: AUTORIZADO
G28: Henry Rizo H | U28: LIC. PASTOR CHAVARRIA HERRERA | AT28: LIC. OSMAN GUTIERREZ

Sheet ADMON
A2: AGRICOLA SANTA ISABEL
A3: JINOTEGA NICARAGUA
A4: PLANILLA DE SALARIO QUINCENAL PERSONAL ADMINISTRATIVO
A5: QUINCENA DEL 16 AL 30 DE ABRIL - 2026
A6: 15
A7: No | B7: INSS | C7: NUMERO CEDULA | D7: NOMBRES Y APELLIDOS | E7: GENERO | F7: CARGO | G7: salario en dolares | H7: cambio del dia | I7: SALARIO BASICO | J7: SALARIO MENSUAL | K7: I N G R E S O S | T7: RETENCIONES | X7: TOTAL DEVENGADO | Y7: ALIMENTACION | Z7: FINCA | AA7: NETO A PAGAR | AB7: COMISARIATO | AC7: TOTAL A PAGAR | AD7: FIRMAS | AE7: INSS PATRONAL | AF7: INATEC 2% | AG7: VACACIONES | AH7: 13vo mes | AI7: TOTAL GASTOS NOMINAS
K8: SALARIO QUINCENAL | L8: DIAS LABORADOS | M8: TOTAL SUBCIDIO | N8: SUBCIDIO POR DIA | O8: DIAS SUBCICIO | P8: TOTAL BASICO | Q8: VACACIONES | R8: AGUINALDO | S8: TOTAL INGRESO | T8: INSS LABORAL | U8: IR | W8: TOTAL RETENCION
D10: ADMINISTRACION FINCA
A11: 1 | B11: 26875888 | C11: 241-051289-0002Y | D11: DEXIS MILENA PICADO GARCIA | E11: F | F11: SECRETARIA | G11: 227.47 | H11: 36.6243 | I11: =+K11/15 -> 277.69765 | J11: =+G11*H11 -> 8330.9295 | K11: =(J11/30)*L11 -> 4165.4648 | L11: 15 | M11: =+O11*N11 -> 0 | N11: =+I11*60% -> 166.61859 | O11: 0 | P11: =+K11-M11 -> 4165.4648 | S11: =+P11 -> 4165.4648 | T11: =IF(B11="",0,(P11*7%)) -> 291.58253 | W11: =+T11+U11+V11 -> 291.58253 | X11: =+P11-W11 -> 3873.8822 | Z11: 500 | AA11: =+X11-Z11 -> 3373.8822 | AB11: 500 | AC11: =+X11-Z11-AB11 -> 2873.8822 | AD11: =+A11 -> 1 | AE11: =+P11*21.5% -> 895.57492 | AF11: =IF(T11>0,P11*2%,0) -> 83.309295 | AG11: =+K11/12 -> 347.12206 | AH11: =+AG11 -> 347.12206 | AI11: =SUM(P11,AE11:AF11)+AG11+AH11 -> 5838.5931
A12: 2 | B12: 40238649 | C12: 241-050476-0008Y | D12: GISELLE WALESKA ESPINAL SALGUERA | E12: F | F12: CERTIFICACION | G12: 350 | H12: 36.6243 | I12: =+K12/15 -> 427.2835 | J12: =+G12*H12 -> 12818.505 | K12: =(J12/30)*L12 -> 6409.2525 | L12: 15 | M12: =+O12*N12 -> 0 | N12: =+I12*60% -> 256.3701 | O12: 0 | P12: =+K12-M12 -> 6409.2525 | S12: =+P12 -> 6409.2525 | T12: =IF(B12="",0,(P12*7%)) -> 448.64767 | U12: =+((((P12-T12)*24)-100000)*15%/24) -> 269.09072 | V12: 0 | W12: =+T12+U12+V12 -> 717.7384 | X12: =+P12-W12 -> 5691.5141 | Z12: 1000 | AA12: =+X12-Z12 -> 4691.5141 | AC12: =X12-Z12 -> 4691.5141 | AD12: =+A12 -> 2 | AE12: =+P12*21.5% -> 1377.9893 | AF12: =IF(T12>0,P12*2%,0) -> 128.18505 | AG12: =+K12/12 -> 534.10438 | AH12: =+AG12 -> 534.10438 | AI12: =SUM(P12,AE12:AF12)+AG12+AH12 -> 8983.6356
A13: 3 | B13: 17814405 | C13: 001-080763-0045M | D13: MANUEL DE JESUS HUETES | E13: M | F13: JEFE DE TRANSPORTE | G13: 245.73 | H13: 36.6243 | I13: =+K13/15 -> 339.98826 | J13: =+H13*G13 -> 8999.6892 | K13: =(J13/30)*L13 -> 5099.8239 | L13: 17 | M13: =+O13*N13 -> 0 | N13: =+I13*60% -> 203.99296 | O13: 0 | P13: =+K13 -> 5099.8239 | S13: =+P13 -> 5099.8239 | T13: =IF(B13="",0,(P13*7%)) -> 356.98767 | W13: =+T13+U13+V13 -> 356.98767 | X13: =+P13-W13 -> 4742.8362 | AA13: =+X13-Z13 -> 4742.8362 | AC13: =X13-Z13 -> 4742.8362 | AD13: =+A13 -> 3 | AE13: =+P13*21.5% -> 1096.4621 | AF13: =IF(T13>0,P13*2%,0) -> 101.99648 | AG13: =+K13/12 -> 424.98533 | AH13: =+AG13 -> 424.98533 | AI13: =SUM(P13,AE13:AF13)+AG13+AH13 -> 7148.2532
A14: 4 | B14: 38675494 | C14: 241-060492-0003J | D14: SANDRO OSMANY GUITIERREZ | E14: M | F14: ADMINISTRADOR | G14: 167 | H14: 36.6243 | I14: =+K14/15 -> 203.87533 | J14: 6116.26 | K14: =(J14/30)*L14 -> 3058.13 | L14: 15 | M14: =+O14*N14 -> 0 | N14: =+I14*60% -> 122.3252 | O14: 0 | P14: =+K14-Q14-R14 -> 2548.4417 | Q14: =+K14/12 -> 254.84417 | R14: =+K14/12 -> 254.84417 | S14: =P14+Q14+R14 -> 3058.13 | T14: =+(P14+Q14)*7% -> 196.23001 | W14: =+T14+U14+V14 -> 196.23001 | X14: =S14-T14 -> 2861.9 | Z14: 0 | AA14: =+X14-Z14 -> 2861.9 | AC14: =X14-Z14 -> 2861.9 | AD14: =+A14 -> 4 | AE14: =+P14*21.5% -> 547.91496 | AF14: =IF(T14>0,P14*2%,0) -> 50.968833 | AG14: =+K14/12 -> 254.84417 | AH14: =+AG14 -> 254.84417 | AI14: =SUM(P14,AE14:AF14)+AG14+AH14 -> 3657.0138
A15: 5 | B15: 12762134 | C15: 241-090775-0014S | D15: IVAN OROZCO OSEJO | E15: M | F15: AUXILIAR CONTABLE | G15: 167 | H15: 36.6243 | I15: =+K15/15 -> 350 | J15: 10500 | K15: =(J15/30)*L15 -> 5250 | L15: 15 | M15: =+O15*N15 -> 0 | N15: =+I15*60% -> 210 | O15: 0 | P15: =+K15-Q15-R15 -> 5250 | Q15: 0 | R15: 0 | S15: =P15+Q15+R15 -> 5250 | T15: =+(P15+Q15)*7% -> 367.5 | V15: 0 | W15: =+T15+U15+V15 -> 367.5 | X15: =+S15-W15 -> 4882.5 | Z15: 0 | AA15: =+X15-Z15 -> 4882.5 | AB15: 308 | AC15: =+AA15-AB15 -> 4574.5 | AD15: =+A15 -> 5 | AE15: =+P15*21.5% -> 1128.75 | AF15: =IF(T15>0,P15*2%,0) -> 105 | AG15: =+K15/12 -> 437.5 | AH15: =+AG15 -> 437.5 | AI15: =SUM(P15,AE15:AF15)+AG15+AH15 -> 7358.75
A16: 5 | D16: JUBER ELUIDTH | E16: M | F16: RESP DE FINCA | G16: 167 | H16: 36.6243 | I16: =+K16/15 -> 833.33333 | J16: 25000 | K16: =(J16/30)*L16 -> 12500 | L16: 15 | M16: =+O16*N16 -> 0 | N16: =+I16*60% -> 500 | O16: 0 | P16: =+K16-Q16-R16 -> 12500 | Q16: 0 | R16: 0 | S16: =P16+Q16+R16 -> 12500 | T16: =+(P16+Q16)*7% -> 875 | U16: =+((((P16-T16)*24)-100000)*15%/24) -> 1118.75 | V16: 0 | W16: =+T16+U16+V16 -> 1993.75 | X16: =+S16-W16 -> 10506.25 | Z16: 0 | AA16: =+X16-Z16 -> 10506.25 | AB16: 0 | AC16: =+AA16-AB16 -> 10506.25 | AD16: =+A16 -> 5 | AE16: =+P16*21.5% -> 2687.5 | AF16: =IF(T16>0,P16*2%,0) -> 250 | AG16: =+K16/12 -> 1041.6667 | AH16: =+AG16 -> 1041.6667 | AI16: =SUM(P16,AE16:AF16)+AG16+AH16 -> 17520.833
A17: SUB TOTAL | G17: =SUM(G11:G16) -> 1324.2 | H17: =SUM(H11:H16) -> 219.7458 | J17: =SUM(J11:J16) -> 71765.384 | K17: =SUM(K11:K16) -> 36482.671 | L17: =SUM(L11:L16) -> 92 | P17: =SUM(P11:P16) -> 35972.983 | Q17: =SUM(Q11:Q16) -> 254.84417 | R17: =SUM(R11:R16) -> 254.84417 | S17: =SUM(S11:S16) -> 36482.671 | T17: =SUM(T11:T16) -> 2535.9479 | U17: =SUM(U11:U16) -> 1387.8407 | V17: =SUM(V11:V16) -> 0 | W17: =SUM(W11:W16) -> 3923.7886 | ... Z17: =SUM(Z11:Z16) -> 1500 | AA17: =+X17-Z17 -> 31058.883 | AB17: =SUM(AB11:AB16) -> 808 | AC17: =SUM(AC11:AC16) -> 30250.883 | AE17: =SUM(AE11:AE16) -> 7734.1913 | AF17: =SUM(AF11:AF16) -> 719.45966 | AG17: =SUM(AG11:AG16) -> 3040.2226 | AH17: =SUM(AH11:AH16) -> 3040.2226 | AI17: =SUM(AI11:AI16) -> 50507.079
D18: AREA TECNICA
A19: 6 | B19: 35126559 | C19: 241-241192-0000Q | D19: KEYLING JOHANA PEREZ MARTINEZ | E19: F | F19: ATENCION AL CLIENTE Y CAJA | G19: 204.782 | H19: 36.6243 | J19: =+H19*G19 -> 7499.9974 | K19: =(J19/30)*L19 -> 3749.9987 | L19: 15 | P19: =+K19-Q19-R19 -> 3749.9987 | Q19: 0 | R19: 0 | S19: =P19+Q19+R19 -> 3749.9987 | T19: =+(P19+Q19)*5% -> 187.49994 | W19: =+T19+U19+V19 -> 187.49994 | X19: =S19-T19 -> 3562.4988 | Z19: 0 | AA19: =+X19-Z19 -> 3562.4988 | AB19: 0 | AC19: =+X19-Z19-AB19 -> 3562.4988 | AD19: =+A19 -> 6 | AE19: =+P19*21.5% -> 806.24972 | AF19: =IF(T19>0,P19*2%,0) -> 74.999974 | AG19: =+K19/12 -> 312.49989 | AH19: =+AG19 -> 312.49989 | AI19: =SUM(P19,AE19:AF19)+AG19+AH19 -> 5256.2482
A20: SU TOTAL | J20: =SUM(J19) -> 7499.9974 | K20: =SUM(K19) -> 3749.9987 | L20: =SUM(L19) -> 15 | P20: =SUM(P19) -> 3749.9987 | Q20: =SUM(Q19) -> 0 | R20: =SUM(R19) -> 0 | S20: =SUM(S19) -> 3749.9987 | T20: =SUM(T19) -> 187.49994 | U20: =SUM(U19) -> 0 | V20: =SUM(V19) -> 0 | W20: =SUM(W19) -> 187.49994 | ... Z20: =SUM(Z19) -> 0 | AA20: =+X20-Z20 -> 3562.4988 | AB20: =+AB19 -> 0 | AC20: =SUM(AC19) -> 3562.4988 | AE20: =SUM(AE19) -> 806.24972 | AF20: =SUM(AF19) -> 74.999974 | AG20: =SUM(AG19) -> 312.49989 | AH20: =SUM(AH19) -> 312.49989 | AI20: =SUM(AI19) -> 5256.2482
A21: TOTALES | J21: =+J17+J20 -> 79265.381 | K21: =+K17+K20 -> 40232.67 | L21: =+L17+L20 -> 107 | P21: =+P17+P20 -> 39722.982 | Q21: =+Q17+Q20 -> 254.84417 | R21: =+R17+R20 -> 254.84417 | S21: =+S17+S20 -> 40232.67 | T21: =+T17+T20 -> 2723.4478 | U21: =+U17+U20 -> 1387.8407 | V21: =+V17+V20 -> 0 | W21: =+W17+W20 -> 4111.2885 | ... Z21: =+Z17+Z20 -> 1500 | AA21: =+X21-Z21 -> 34621.381 | AB21: =+AB17+AB20 -> 808 | AC21: =+X21-Z21-AB21 -> 33813.381 | AD21: =+TECNICOS!Z15 -> "EL SEÑOR ES MI PASTOR, NADA ME FALTARA" | AE21: =+AE17+AE20 -> 8540.441 | AF21: =+AF17+AF20 -> 794.45963 | AG21: =+AG17+AG20 -> 3352.7225 | AH21: =+AH17+AH20 -> 3352.7225 | AI21: =+AI17+AI20 -> 55763.327
H23: =500*35.6348 -> 17817.4
C29: ELABORADO POR: | K29: REVISADO POR: | AC29: AUTORIZADO POR:
C30: Jose Martin Conrrado | K30: IVAN OROZCO OSEJO | AC30: LIC: OSMAN G GUTIERREZ MORENO

Sheet Hoja2

Sheet ADMON COM. 
A2: AGRICOLA SANTA ISABEL
A3: JINOTEGA NICARAGUA
A4: PLANILLA DE SALARIO QUINCENAL PERSONAL ADMINISTRATIVO COMERCIAL
A5: =+ADMON!A5 -> QUINCENA DEL 16 AL 30 DE ABRIL - 2026
A6: 15
A7: No | B7: INSS | C7: NUMERO CEDULA | D7: NOMBRES Y APELLIDOS | E7: GENERO | F7: CARGO | G7: salario en dolares | H7: cambio del dia | I7: SALARIO MENSUAL | J7: I N G R E S O S | P7: RETENCIONES | T7: TOTAL DEVENGADO | U7: ALIMENTACION | V7: FINCA | W7: TOTAL A PAGAR | X7: FIRMAS | Y7: INSS PATRONAL | Z7: INATEC 2% | AA7: VACACIONES | AB7: 13vo mes | AC7: TOTAL GASTOS NOMINAS
J8: SALARIO QUINCENAL | K8: DIAS LABORADOS | L8: TOTAL BASICO | M8: VACACIONES | N8: AGUINALDO | O8: TOTAL INGRESO | P8: INSS LABORAL | Q8: IR | R8: ABONO RESTAMOS | S8: TOTAL RETENCION
A10: AREA TECNICA
A11: 1 | B11: 8069333 | C11: 001-040170-0013R | D11: JOSE MANUEL MORAGA FLORES | E11: M | F11: JEFE COMERCIAL | G11: 700 | H11: =LOOKUP(A6,'Cambio del dia'!F1:G38) -> 36.6243 | I11: =+H11*G11 -> 25637.01 | J11: =(I11/30)*K11 -> 12818.505 | K11: 15 | L11: =+J11 -> 12818.505 | O11: =+L11 -> 12818.505 | P11: =IF(B11="",0,(L11*7%)) -> 897.29535 | Q11: =+((((L11-P11)*24)-100000)*15%/24) -> 1163.1814 | R11: 0 | S11: =+P11+Q11+R11 -> 2060.4768 | T11: =L11-P11-Q11 -> 10758.028 | V11: 0 | W11: =+U11+T11-V11 -> 10758.028 | X11: =+A11 -> 1 | Y11: =+L11*21.5% -> 2755.9786 | Z11: =IF(P11>0,L11*2%,0) -> 256.3701 | AA11: =+J11/12 -> 1068.2088 | AB11: =+AA11 -> 1068.2088 | AC11: =SUM(L11,Y11:Z11)+AA11+AB11 -> 17967.271
A12: 2 | B12: 25093885 | C12: 241-091087-0001E | D12: YANT CARLO FERRUFINO PINEDA | E12: M | F12: ASESOR TECNICO Y FINANCIERO | G12: 350 | H12: 36.6243 | I12: =+H12*G12 -> 12818.505 | J12: =(I12/30)*K12 -> 6409.2525 | K12: 15 | L12: =+J12 -> 6409.2525 | O12: =+L12 -> 6409.2525 | P12: =IF(B12="",0,(L12*7%)) -> 448.64767 | Q12: =+((((L12-P12)*24)-100000)*15%/24) -> 269.09072 | R12: 0 | S12: =+P12+Q12+R12 -> 717.7384 | T12: =+L12-S12 -> 5691.5141 | V12: 0 | W12: =+U12+T12-V12 -> 5691.5141 | X12: =+A12 -> 2 | Y12: =+L12*21.5% -> 1377.9893 | Z12: =IF(P12>0,L12*2%,0) -> 128.18505 | AA12: =+J12/12 -> 534.10438 | AB12: =+AA12 -> 534.10438 | AC12: =SUM(L12,Y12:Z12)+AA12+AB12 -> 8983.6356
A13: 3 | B13: 5357574 | C13: 241-300565-0007T | D13: LUIS FERNANDO PALACIOS RIOS | E13: M | F13: ASESOR TECNICO Y FINANCIERO | G13: 350 | H13: 36.6243 | I13: =+H13*G13 -> 12818.505 | J13: =(I13/30)*K13 -> 0 | K13: 0 | L13: =+J13 -> 0 | O13: =+L13 -> 0 | P13: =IF(B13="",0,(L13*7%)) -> 0 | Q13: =+((((L13-P13)*24)-100000)*15%/24) -> -625 | R13: 0 | S13: =+P13+Q13+R13 -> -625 | T13: 0 | V13: 0 | W13: =+U13+T13-V13 -> 0 | X13: =+A13 -> 3 | Y13: =+L13*21.5% -> 0 | Z13: =IF(P13>0,L13*2%,0) -> 0 | AA13: =+J13/12 -> 0 | AB13: =+AA13 -> 0 | AC13: =SUM(L13,Y13:Z13)+AA13+AB13 -> 0
A14: 4 | B14: 21371240 | C14: 001-210878-0075X | D14: JACKS HERRY TORRES PEREZ | E14: M | F14: ASESOR TECNICO Y FINANCIERO | G14: 350 | H14: 36.6243 | I14: =+H14*G14 -> 12818.505 | J14: =(I14/30)*K14 -> 6409.2525 | K14: 15 | L14: =+J14 -> 6409.2525 | O14: =+L14 -> 6409.2525 | P14: =IF(B14="",0,(L14*7%)) -> 448.64767 | Q14: =+((((L14-P14)*24)-100000)*15%/24) -> 269.09072 | R14: 0 | S14: =+P14+Q14+R14 -> 717.7384 | T14: =+L14-S14 -> 5691.5141 | V14: 0 | W14: =+U14+T14-V14 -> 5691.5141 | X14: =+A14 -> 4 | Y14: =+L14*21.5% -> 1377.9893 | Z14: =IF(P14>0,L14*2%,0) -> 128.18505 | AA14: =+J14/12 -> 534.10438 | AB14: =+AA14 -> 534.10438 | AC14: =SUM(L14,Y14:Z14)+AA14+AB14 -> 8983.6356
A15: 5 | B15: 19144283 | C15: 241-210680-0011D | D15: CESAR AUGUSTO ZEAS | E15: M | F15: ASESOR TECNICO Y FINANCIERO | G15: 350 | H15: 36.6243 | I15: =+H15*G15 -> 12818.505 | J15: =(I15/30)*K15 -> 6409.2525 | K15: 15 | L15: =+J15 -> 6409.2525 | O15: =+L15 -> 6409.2525 | P15: =IF(B15="",0,(L15*7%)) -> 448.64767 | Q15: =+((((L15-P15)*24)-100000)*15%/24) -> 269.09072 | R15: 0 | S15: =+P15+Q15+R15 -> 717.7384 | T15: =+L15-S15 -> 5691.5141 | V15: 0 | W15: =+U15+T15-V15 -> 5691.5141 | X15: =+A15 -> 5 | Y15: =+L15*21.5% -> 1377.9893 | Z15: =IF(P15>0,L15*2%,0) -> 128.18505 | AA15: =+J15/12 -> 534.10438 | AB15: =+AA15 -> 534.10438 | AC15: =SUM(L15,Y15:Z15)+AA15+AB15 -> 8983.6356
A16: SUB TOTAL | I16: =SUM(I11:I15) -> 76911.03 | J16: =SUM(J11:J15) -> 32046.262 | K16: =SUM(K11:K15) -> 60 | L16: =SUM(L11:L15) -> 32046.262 | M16: =SUM(M11:M15) -> 0 | N16: =SUM(N11:N15) -> 0 | O16: =SUM(O11:O15) -> 32046.262 | P16: =SUM(P11:P15) -> 2243.2384 | ... W16: =SUM(W11:W15) -> 27832.571 | Y16: =SUM(Y11:Y15) -> 6889.9464 | Z16: =SUM(Z11:Z15) -> 640.92525 | AA16: =SUM(AA11:AA15) -> 2670.5219 | AB16: =SUM(AB11:AB15) -> 2670.5219 | AC16: =SUM(AC11:AC15) -> 44918.178
A17: ADMINISTRACION
A18: 6 | B18: 16167647 | C18: 241-301272-0001U | D18: ARMANDO JOSE IGLESIAS | E18: M | F18: JEFE INDUSTRIAL | G18: 500 | H18: =LOOKUP(A6,'Cambio del dia'!F2:G38) -> 36.6243 | I18: =+H18*G18 -> 18312.15 | J18: =(I18/30)*K18 -> 9156.075 | K18: 15 | L18: =+J18 -> 9156.075 | O18: =+L18 -> 9156.075 | P18: =IF(B18="",0,(L18*7%)) -> 640.92525 | Q18: =+((((L18-P18)*24)-100000)*15%/24) -> 652.27246 | R18: 0 | S18: =+P18+Q18+R18 -> 1293.1977 | T18: =L18-P18-Q18 -> 7862.8773 | V18: 0 | W18: =+U18+T18-V18 -> 7862.8773 | X18: =+A18 -> 6 | Y18: =+L18*21.5% -> 1968.5561 | Z18: =IF(P18>0,L18*2%,0) -> 183.1215 | AA18: =+J18/12 -> 763.00625 | AB18: =+AA18 -> 763.00625 | AC18: =SUM(L18,Y18:Z18)+AA18+AB18 -> 12833.765
A19: 7 | B19: 14049864 | C19: 241-050475-0001W | D19: VICENTE ALBERTO GADEA | E19: M | F19: JEFE DE PRODUCCION | G19: 500 | H19: 36.6243 | I19: =+H19*G19 -> 18312.15 | J19: =(I19/30)*K19 -> 9156.075 | K19: 15 | L19: =+J19 -> 9156.075 | O19: =+L19 -> 9156.075 | P19: =IF(B19="",0,(L19*7%)) -> 640.92525 | Q19: =+((((L19-P19)*24)-100000)*15%/24) -> 652.27246 | R19: 0 | S19: =+P19+Q19+R19 -> 1293.1977 | T19: =L19-P19-Q19 -> 7862.8773 | V19: 0 | W19: =+U19+T19-V19 -> 7862.8773 | X19: =+A19 -> 7 | Y19: =+L19*21.5% -> 1968.5561 | Z19: =IF(P19>0,L19*2%,0) -> 183.1215 | AA19: =+J19/12 -> 763.00625 | AB19: =+AA19 -> 763.00625 | AC19: =SUM(L19,Y19:Z19)+AA19+AB19 -> 12833.765
A20: 8 | B20: 9034666 | C20: 241-260465-0010G | D20: NELLY DEL CARMEN SOBALVARRO THOMAS | E20: F | F20: AUXILIAR CONTABLE | G20: 298.9818 | H20: 36.6243 | I20: =+H20*G20 -> 10949.999 | J20: =(I20/30)*K20 -> 0 | K20: 0 | L20: =+J20 -> 0 | O20: =+L20 -> 0 | P20: =IF(B20="",0,(L20*7%)) -> 0 | Q20: 0 | R20: 0 | S20: =+P20+Q20+R20 -> 0 | T20: =+L20-S20 -> 0 | V20: 0 | W20: =+U20+T20-V20 -> 0 | X20: =+A20 -> 8 | Y20: =+L20*21.5% -> 0 | Z20: =IF(P20>0,L20*2%,0) -> 0 | AA20: =+J20/12 -> 0 | AB20: =+AA20 -> 0 | AC20: =SUM(L20,Y20:Z20)+AA20+AB20 -> 0
A21: 9 | B21: 26875888 | C21: 003-020172-0001X | D21: ARMANDO GUIDO GONZALEZ | E21: M | F21: AUXILIAR CONTABLE ACOPIO | G21: 298.9818 | H21: 36.6243 | I21: =+H21*G21 -> 10949.999 | J21: =(I21/30)*K21 -> 5474.9996 | K21: 15 | L21: =+J21 -> 5474.9996 | O21: =+L21 -> 5474.9996 | P21: =IF(B21="",0,(L21*7%)) -> 383.24997 | Q21: =+((((L21-P21)*24)-100000)*15%/24) -> 138.76244 | R21: 0 | S21: =+P21+Q21+R21 -> 522.01241 | T21: =+L21-S21 -> 4952.9872 | V21: 500 | W21: =+U21+T21-V21 -> 4452.9872 | X21: =+A21 -> 9 | Y21: =+L21*21.5% -> 1177.1249 | Z21: =IF(P21>0,L21*2%,0) -> 109.49999 | AA21: =+J21/12 -> 456.24996 | AB21: =+AA21 -> 456.24996 | AC21: =SUM(L21,Y21:Z21)+AA21+AB21 -> 7674.1244
A22: SUB TOTAL | I22: =SUM(I18:I21) -> 58524.298 | J22: =SUM(J18:J21) -> 23787.15 | K22: =SUM(K18:K21) -> 45 | L22: =SUM(L18:L21) -> 23787.15 | M22: =SUM(M18:M21) -> 0 | N22: =SUM(N18:N21) -> 0 | O22: =SUM(O18:O21) -> 23787.15 | P22: =SUM(P18:P21) -> 1665.1005 | ... W22: =SUM(W18:W21) -> 20178.742 | Y22: =SUM(Y18:Y21) -> 5114.2372 | Z22: =SUM(Z18:Z21) -> 475.74299 | AA22: =SUM(AA18:AA21) -> 1982.2625 | AB22: =SUM(AB18:AB21) -> 1982.2625 | AC22: =SUM(AC18:AC21) -> 33341.655
A23: ACOPIO ABISINIA | D23: ACOPIO ABISINIA
A24: 10 | B24: 7305067 | C24: 241-140864-0000B | D24: MARIA HULDA GARCIA RIVAS | E24: F | F24: ATENCION AL CLIENTE | G24: 298.9818 | H24: 36.6243 | I24: =+H24*G24 -> 10949.999 | J24: =(I24/30)*K24 -> 5474.9996 | K24: 15 | L24: =+J24 -> 5474.9996 | O24: =+L24 -> 5474.9996 | P24: =IF(B24="",0,(L24*7%)) -> 383.24997 | Q24: =+((((L24-P24)*24)-100000)*15%/24) -> 138.76244 | R24: 0 | S24: =+P24+Q24+R24 -> 522.01241 | T24: =+L24-S24 -> 4952.9872 | V24: 0 | W24: =+U24+T24-V24 -> 4952.9872 | X24: =+A24 -> 10 | Y24: =+L24*21.5% -> 1177.1249 | Z24: =IF(P24>0,L24*2%,0) -> 109.49999 | AA24: =+J24/12 -> 456.24996 | AB24: =+AA24 -> 456.24996 | AC24: =SUM(L24,Y24:Z24)+AA24+AB24 -> 7674.1244
A25: SUB TOTAL | I25: =SUM(I24) -> 10949.999 | J25: =SUM(J24) -> 5474.9996 | K25: =SUM(K24) -> 15 | L25: =SUM(L24) -> 5474.9996 | M25: =SUM(M24) -> 0 | N25: =SUM(N24) -> 0 | O25: =SUM(O24) -> 5474.9996 | P25: =SUM(P24) -> 383.24997 | ... W25: =SUM(W24) -> 4952.9872 | Y25: =SUM(Y24) -> 1177.1249 | Z25: =SUM(Z24) -> 109.49999 | AA25: =SUM(AA24) -> 456.24996 | AB25: =SUM(AB24) -> 456.24996 | AC25: =SUM(AC24) -> 7674.1244
A26: BENEFICIO HUMEDO
A27: 11 | B27: 21389447 | C27: 442-120970-0000R | D27: CESAR AUGUSTO ALEMAN | E27: M | F27: RESPONSABLE BENEFICIO HUMEDO | G27: 298.9818 | H27: 36.6243 | I27: =+H27*G27 -> 10949.999 | J27: 5475 | K27: 15 | L27: 4692.855 | M27: =L27/12 -> 391.07125 | N27: =+L27/12 -> 391.07125 | O27: =+L27++M27+N27 -> 5474.9975 | P27: =IF(B27="",0,(L27*7%)) -> 328.49985 | Q27: =+((((L27-P27)*24)-100000)*15%/24) -> 29.653272 | R27: 0 | S27: =+P27+Q27+R27 -> 358.15312 | T27: =+L27-S27 -> 4334.7019 | V27: 0 | W27: =+U27+T27-V27 -> 4334.7019 | X27: =+A27 -> 11 | Y27: =+L27*21.5% -> 1008.9638 | Z27: =IF(P27>0,L27*2%,0) -> 93.8571 | AA27: =+J27/12 -> 456.25 | AB27: =+AA27 -> 456.25 | AC27: =SUM(L27,Y27:Z27)+AA27+AB27 -> 6708.1759
A28: SUB TOTAL | I28: =SUM(I27) -> 10949.999 | J28: =SUM(J27) -> 5475 | K28: =SUM(K27) -> 15 | L28: =SUM(L27) -> 4692.855 | M28: =SUM(M27) -> 391.07125 | N28: =SUM(N27) -> 391.07125 | O28: =SUM(O27) -> 5474.9975 | P28: =SUM(P27) -> 328.49985 | ... W28: =SUM(W27) -> 4334.7019 | Y28: =SUM(Y27) -> 1008.9638 | Z28: =SUM(Z27) -> 93.8571 | AA28: =SUM(AA27) -> 456.25 | AB28: =SUM(AB27) -> 456.25 | AC28: =SUM(AC27) -> 6708.1759
A29: 15 | B29: 38675494 | C29: 241-060492-0003J | D29: SANDRO OSMANY GUITIERREZ | E29: M | F29: ADMINISTRADOR | G29: 167 | H29: 36.6243 | I29: 6116.26 | J29: =(I29/30)*K29 -> 3058.13 | K29: 15 | L29: =+J29-M29-N29 -> 2548.4417 | M29: =+J29/12 -> 254.84417 | N29: =+J29/12 -> 254.84417 | O29: =L29+M29+N29 -> 3058.13 | P29: =+(L29+M29)*7% -> 196.23001 | S29: =+P29+Q29+R29 -> 196.23001 | T29: =O29-P29 -> 2861.9 | V29: 0 | W29: =O29-P29 -> 2861.9 | X29: =+A29 -> 15 | Y29: =+L29*21.5% -> 547.91496 | Z29: =IF(P29>0,L29*2%,0) -> 50.968833 | AA29: 0 | AB29: 0 | AC29: =SUM(L29,Y29:Z29)+AA29+AB29 -> 3147.3255
A30: TOTALES | I30: =+I16+I22+I25+I28 -> 157335.33 | J30: =+J16+J22+J25+J28 -> 66783.412 | K30: =+K16+K22+K25+K28 -> 135 | L30: =+L16+L22+L25+L28 -> 66001.267 | M30: =+M16+M22+M25+M28 -> 391.07125 | N30: =+N16+N22+N25+N28 -> 391.07125 | O30: =+O16+O22+O25+O28 -> 66783.409 | P30: =+P16+P22+P25+P28 -> 4620.0887 | ... W30: =+W16+W22+W25+W28 -> 57299.001 | X30: =+TECNICOS!Z15 -> "EL SEÑOR ES MI PASTOR, NADA ME FALTARA" | Y30: =+Y16+Y22+Y25+Y28 -> 14190.272 | Z30: =+Z16+Z22+Z25+Z28 -> 1320.0253 | AA30: =+AA16+AA22+AA25+AA28 -> 5565.2843 | AB30: =+AB16+AB22+AB25+AB28 -> 5565.2843 | AC30: =+AC16+AC22+AC25+AC28 -> 92642.133
H32: =500*35.6348 -> 17817.4
C49: ELABORADO POR: | J49: REVISADO POR: | W49: AUTORIZADO POR:
C50: Jose Martin Conrrado | J50: IVAN OROZCO OSEJO | W50: LIC:OSMAN G GUTIERREZ MORENO

Sheet TECNICOS
A2: AGRÍCOLA SANTA ISABEL
A3: PLANILLA DE SALARIO QUINCENAL DE TÉCNICOS DE ACOPIO
A4: =+'ADMON COM. '!A5:AC5 -> QUINCENA DEL 16 AL 30 DE ABRIL - 2026
A5: =+'ADMON COM. '!A6 -> 15
A6: No | B6: INSS | C6: NUMERO DE CEDULA | D6: NOMBRES Y APELLIDOS | E6: GENERO | F6: CARGO | G6: salario en dolares | H6: cambio del dia | I6: SALARIO DIARIO | J6: SALARIO MENSUAL | K6: I N G R E S O S | Q6: RETENCIONES | U6: TOTAL DEVENGADO | V6: COMISARIATO | W6: FINCA | X6: COMISARIATO | Y6: NETO A PAGAR DEVENGADO | Z6: FIRMAS | AA6: VACASIONES | AB6: 13VO MES | AC6: INSS PATRONAL | AD6: INATEC 2% | AE6: VACACIONES | AF6: 13VO MES | AG6: TOTAL GASTOS NOMINAS
K7: SALARIO QUINCENAL | L7: DIAS LABORADOS | M7: total subcidio | N7: subcidio por dia | O7: DIAS SUBSIDIO | P7: TOTAL INGRESOS | Q7: INSS LABORAL | R7: IR | S7: ABONO POR PRESTAMOS | T7: TOTAL RETENCION
A9: 1 | B9: 5357574 | C9: 241-300565-0007T | D9: LUIS FERNANDO PALACIOS RIOS | E9: M | F9: ASESOR TECNICO Y FINANCIERO | G9: 0 | H9: =LOOKUP(A5,'Cambio del dia'!F7:G38) -> 36.6243 | I9: =+K9/L9 -> 0 | J9: =+H9*G9 -> 0 | K9: =(J9/30)*L9 -> 0 | L9: 15 | M9: =+N9*O9 -> 0 | N9: =I9*60% -> 0 | O9: 0 | P9: =+K9-M9 -> 0 | Q9: =IF(B9="",0,(P9*7%)) -> 0 | R9: =IF(AND(P9*24>100000,P9*24<=200000),((((P9-Q9)*24)-100000)*15%)/24,IF(AND(P9*24>100000,P9*24<=200000),(((((P9-Q9)*24)-100000)*15%))/24,)) -> 0 | T9: =+Q9+R9+S9 -> 0 | U9: =-T9+P9 -> 0 | V9: 0 | W9: 0 | Y9: =+P9-T9+V9 -> 0 | AA9: =+J9/30*1.25 -> 0 | AB9: =+J9/30*1.25 -> 0 | AC9: =IF(B9="",0,P9*21.5%) -> 0 | AD9: =IF(Q9>0,P9*2%,0) -> 0 | AE9: =+K9/12 -> 0 | AF9: =+AE9 -> 0 | AG9: =SUM(P9,AC9,AB9,AA9,AD9) -> 0
A10: 2 | B10: 25093885 | C10: 241-091087-0001E | D10: YANT CARLO FERRUFINO PINEDA | E10: M | F10: ASESOR TECNICO Y FINANCIERO | G10: 0 | H10: =LOOKUP(A5,'Cambio del dia'!F7:G38) -> 36.6243 | I10: =+P10/L10 -> 0 | J10: =+H10*G10 -> 0 | K10: =(J10/30)*L10 -> 0 | L10: 15 | M10: =+N10*O10 -> 0 | N10: =I10*60% -> 0 | O10: 0 | P10: =+K10 -> 0 | Q10: =IF(B10="",0,(P10*7%)) -> 0 | R10: =IF(AND(P10*24>100000,P10*24<=200000),((((P10-Q10)*24)-100000)*15%)/24,IF(AND(P10*24>100000,P10*24<=200000),(((((P10-Q10)*24)-100000)*15%))/24,)) -> 0 | T10: =+Q10+R10+S10 -> 0 | U10: =-T10+P10 -> 0 | V10: 0 | W10: 0 | Y10: =+P10-T10+V10-W10 -> 0 | AA10: =+J10/30*1.25 -> 0 | AB10: =+J10/30*1.25 -> 0 | AC10: =IF(B10="",0,P10*21.5%) -> 0 | AD10: =IF(Q10>0,P10*2%,0) -> 0 | AE10: =+K10/12 -> 0 | AF10: =+AE10 -> 0 | AG10: =SUM(P10,AC10,AB10,AA10,AD10) -> 0
A11: 3 | B11: 21371240 | C11: 001-210878-0075X | D11: JACKS HERRY TORRES PEREZ | E11: M | F11: ASESOR TECNICO Y FINANCIERO | G11: 0 | H11: =LOOKUP(A5,'Cambio del dia'!F8:G38) -> 36.6243 | I11: =+P11/L11 -> 0 | J11: =+H11*G11 -> 0 | K11: =(J11/30)*L11 -> 0 | L11: 15 | M11: =+N11*O11 -> 0 | N11: =I11*60% -> 0 | O11: 0 | P11: =+K11 -> 0 | Q11: =IF(B11="",0,(P11*7%)) -> 0 | R11: =IF(AND(P11*24>100000,P11*24<=200000),((((P11-Q11)*24)-100000)*15%)/24,IF(AND(P11*24>100000,P11*24<=200000),(((((P11-Q11)*24)-100000)*15%))/24,)) -> 0 | T11: =+Q11+R11+S11 -> 0 | U11: =-T11+P11 -> 0 | V11: 0 | W11: 0 | Y11: =+P11-T11+V11 -> 0 | AA11: =+J11/30*1.25 -> 0 | AB11: =+J11/30*1.25 -> 0 | AC11: =IF(B11="",0,P11*21.5%) -> 0 | AD11: =IF(Q11>0,P11*2%,0) -> 0 | AE11: =+K11/12 -> 0 | AF11: =+AE11 -> 0 | AG11: =SUM(P11,AC11,AB11,AA11,AD11) -> 0
A12: 4 | B12: 19144283 | C12: 241-210680-0011D | D12: CESAR AUGUSTO ZEAS | E12: M | F12: ASESOR TECNICO Y FINANCIERO | G12: 0 | H12: =LOOKUP(A5,'Cambio del dia'!F7:G38) -> 36.6243 | I12: =+P12/L12 -> 0 | J12: =+H12*G12 -> 0 | K12: =(J12/30)*L12 -> 0 | L12: 15 | M12: =+N12*O12 -> 0 | N12: =I12*60% -> 0 | O12: 0 | P12: =+K12 -> 0 | Q12: =IF(B12="",0,(P12*7%)) -> 0 | R12: =IF(AND(P12*24>100000,P12*24<=200000),((((P12-Q12)*24)-100000)*15%)/24,IF(AND(P12*24>100000,P12*24<=200000),(((((P12-Q12)*24)-100000)*15%))/24,)) -> 0 | T12: =+Q12+R12+S12 -> 0 | U12: =-T12+P12 -> 0 | Y12: =+U12-V12-W12 -> 0 | AA12: =+J12/30*1.25 -> 0 | AB12: =+J12/30*1.25 -> 0 | AC12: =IF(B12="",0,P12*21.5%) -> 0 | AD12: =IF(Q12>0,P12*2%,0) -> 0 | AE12: =+K12/12 -> 0 | AF12: =+AE12 -> 0 | AG12: =SUM(P12,AC12,AB12,AA12,AD12) -> 0
A13: 5 | B13: 35126559 | C13: 241-241192-0000Q | D13: KEYLING JOHANA PEREZ MARTINEZ | E13: F | F13: ATENCION AL CLIENTE Y CAJA | G13: 0 | H13: 0 | I13: 0 | J13: 0 | K13: =(J13/30)*L13 -> 0 | L13: 15 | M13: =+N13*O13 -> 0 | N13: =I13*60% -> 0 | O13: 0 | P13: =+K13 -> 0 | Q13: =IF(B13="",0,(P13*5%)) -> 0 | R13: 0 | T13: =+Q13+R13+S13 -> 0 | U13: =-T13+P13 -> 0 | W13: 0 | Y13: =+P13-T13+V13-W13 -> 0 | AA13: =+J13/30*1.25 -> 0 | AB13: =+J13/30*1.25 -> 0 | AC13: =IF(B13="",0,P13*21.5%) -> 0 | AD13: =IF(Q13>0,P13*2%,0) -> 0 | AE13: =+K13/12 -> 0 | AF13: =+AE13 -> 0 | AG13: =SUM(P13,AC13,AB13,AA13,AD13) -> 0
A14: 6 | B14: 8069333 | C14: 001-040170-0013R | D14: JOSE MANUEL MORAGA | E14: M | F14: COORDINADOR DE ACOPIOS Y FINANZAS | G14: 0 | H14: =LOOKUP(A5,'Cambio del dia'!F7:G38) -> 36.6243 | I14: =+P14/L14 -> 0 | J14: =+H14*G14 -> 0 | K14: =(J14/30)*L14 -> 0 | L14: 15 | M14: =+N14*O14 -> 0 | N14: =I14*60% -> 0 | O14: 0 | P14: =+K14 -> 0 | Q14: =IF(B14="",0,(P14*7%)) -> 0 | R14: =IF(AND(P14*24>100000,P14*24<=200000),((((P14-Q14)*24)-100000)*15%)/24,IF(AND(P14*24>100000,P14*24<=200000),(((((P14-Q14)*24)-100000)*15%))/24,)) -> 0 | T14: =+Q14+R14+S14 -> 0 | U14: =-T14+P14 -> 0 | W14: 0 | Y14: =+P14-T14-V14-W14 -> 0 | AA14: =+J14/30*1.25 -> 0 | AB14: =+J14/30*1.25 -> 0 | AC14: =IF(B14="",0,P14*21.5%) -> 0 | AD14: =IF(Q14>0,P14*2%,0) -> 0 | AE14: =+K14/12 -> 0 | AF14: =+AE14 -> 0 | AG14: =SUM(P14,AC14,AB14,AA14,AD14) -> 0
A15: TOTALES | G15: =SUM(G9:G12) -> 0 | I15: =SUM(I9:I14) -> 0 | J15: =SUM(J9:J14) -> 0 | K15: =SUM(K9:K14) -> 0 | L15: =SUM(L9:L14) -> 90 | M15: =SUM(M9:M14) -> 0 | N15: =SUM(N9:N14) -> 0 | O15: =SUM(O9:O14) -> 0 | P15: =SUM(P9:P14) -> 0 | ... W15: =SUM(W9:W14) -> 0 | X15: =SUM(X9:X12) -> 0 | Y15: =SUM(Y9:Y14) -> 0 | Z15: "EL SEÑOR ES MI PASTOR, NADA ME FALTARA" | AA15: =SUM(AA9:AA10) -> 0 | AB15: =SUM(AB9:AB10) -> 0 | AC15: =SUM(AC9:AC14) -> 0 | AD15: =SUM(AD9:AD14) -> 0 | AE15: =SUM(AE9:AE14) -> 0 | AF15: =SUM(AF9:AF14) -> 0 | AG15: =SUM(AG9:AG14) -> 0
C23: ELABORADO POR: | L23: REVISADO POR: | Y23: AUTORIZADO POR:
C24: =+'ADMON COM. '!C50:F50 -> Jose Martin Conrrado | L24: Ivan Orozco Osejo | Y24: Lic. Osman Gregorio Gutiérrez Moreno

Sheet FINANCIAMIENTO INSS
A2: PLANILLA ACOPIO YEMIN DAVID GUTIERREZ
A3: PLANILLA DE SALARIO QUINCENAL
A4: =+TECNICOS!A4 -> QUINCENA DEL 16 AL 30 DE ABRIL - 2026
A8: No | B8: INSS | C8: NUMERO DE CEDULA | D8: NOMBRES Y APELLIDOS | E8: GENERO | F8: CARGO | G8: salario en dolares | H8: cambio del dia | I8: SALARIO DIARIO | J8: SALARIO MENSUAL | K8: I N G R E S O S | S8: RETENCIONES | Y8: TOTAL | Z8: FINCA | AA8: COMISARIATO | AB8: SALARIO DEVENGADO | AC8: FIRMAS | AF8: INSS PATRONAL | AG8: VACACIONES | AH8: 13VO MES | AI8: INATEC 2% | AJ8: TOTAL GASTOS NOMINAS
K9: SALARIO QUINCENAL | L9: DIAS LABORADOS | M9: total subcidio | N9: subcidio por dia | O9: DIAS SUBSIDIO | P9: TOTAL BASICO | Q9: VACACIONES | R9: 13VO MES | S9: TOTAL | U9: INSS | V9: IR | W9: ABONO POR PRESTAMOS | X9: TOTAL RETENCION
A11: 1 | B11: 17155823 | C11: 241-151294-0004V | D11: KEYLIN JOHANA PEREZ MARTINEZ | E11: F | F11: CAJERA | I11: 250 | J11: =I11*30 -> 7500 | K11: =(J11/30)*L11 -> 0 | L11: 0 | M11: =+N11*O11 -> 0 | N11: =I11*60% -> 150 | O11: 0 | P11: =+K11-Q11-R11 -> 0 | Q11: 0 | R11: 0 | S11: =+P11 -> 0 | T11: =P11+Q11 -> 0 | U11: =+T11*5% -> 0 | X11: =U11 -> 0 | Y11: =-X11+P11+Q11+R11 -> 0 | Z11: 0 | AA11: 0 | AB11: =Y11-Z11-AA11 -> 0 | AD11: 0.155 | AE11: =+S11-R11 -> 0 | AF11: =AD11*S11 -> 0 | AG11: =+K11/12 -> 0 | AH11: =+K11/12 -> 0 | AI11: =0.02*AB11 -> 0 | AJ11: =AB11+AF11+AI11+AG11+AH11 -> 0
A12: TOTALES | G12: =SUM(#REF!) -> #REF! | I12: =SUM(I11:I11) -> 250 | J12: =SUM(J11:J11) -> 7500 | K12: =SUM(K11:K11) -> 0 | L12: 15 | M12: =SUM(M11:M11) -> 0 | N12: =SUM(N11:N11) -> 150 | O12: =SUM(O11:O11) -> 0 | P12: =SUM(P11:P11) -> 0 | Q12: =SUM(Q11:Q11) -> 0 | R12: =SUM(R11:R11) -> 0 | S12: =SUM(S11:S11) -> 0 | T12: =SUM(T11:T11) -> 0 | ... AA12: =SUM(AA11:AA11) -> 0 | AB12: =Y12-Z12-AA12 -> 0 | AC12: "EL SEÑOR ES MI PASTOR, NADA ME FALTARA" | AD12: =SUM(#REF!) -> #REF! | AE12: =SUM(#REF!) -> #REF! | AF12: =SUM(AF11:AF11) -> 0 | AG12: =SUM(AG11:AG11) -> 0 | AH12: =SUM(AH11:AH11) -> 0 | AI12: =SUM(AI11:AI11) -> 0 | AJ12: =SUM(AJ11:AJ11) -> 0
I14: 10
I15: 350 | J15: 35.6948 | K15: =+I15*J15 -> 12493.18
K16: =+I15/J15 -> 9.8053498 | L16: =9.81*30 -> 294.3
C26: ELABORADO POR: | L26: REVISADO POR: | AB26: AUTORIZADO POR:
C27: =+'ADMON COM. '!C50:F50 -> Jose Martin Conrrado | L27: =+'FINCA SIN INSS'!K32:W32 -> 0 | AB27: Lic. Osman Gregorio Gutiérrez Moreno

Sheet Holman
A6: JINOTEGA, NICARAGUA
A7: PLANILLA DE SALARIO QUINCENAL
A8: =+TECNICOS!A4 -> QUINCENA DEL 16 AL 30 DE ABRIL - 2026
A14: No. | B14: SALARIO | C14: NOMBRES Y APELLIDOS | D14: SALARIO DIARIO | E14: Actividad | F14: 1 | G14: 2 | H14: 3 | I14: 4 | J14: 5 | K14: 6 | L14: 7 | M14: 1 semana | N14: SEPTIMO DIA | O14: 8 | P14: 9 | Q14: 10 | R14: 11 | S14: 12 | T14: 13 | U14: 14 | V14: 15 | W14: 31 | Y14: 2 semana | Z14: SEPTIMO DIA | AA14: SUMA SETIMOS | AB14: SUMA DIAS | AD14: DIAS TRABAJADOS | AE14: FERIADOS/ LIBRES | AF14: HRS EXT | AG14: DOM LAB | AH14: SALARIO BASICO | AK14: SEPTIMO DIA | AL14: COSTE DIA | AM14: COSTE HORA | AN14: DOMINGOS TRABAJADOS | AO14: HORAS EXTRAS | AP14: DIAS FERIADOS | AQ14: Extras y/o Dom. Trab | AR14: DIAS | AS14: SALARIO | AT14: DODIGO | AU14: CONSTANTE | AV14: SALARIO 14CENAL | AW14: FORMUAL | AX14: FORMULA | AY14: FORMULA | AZ14: TOTAL | BA14: Adicional | BB14: INGRESO BASICO | BC14: VACASIONES | BD14: 13VO MES | BE14: TOTAL INGRESOS | BI14: SALARIO NETO | BJ14: VIATICO | BK14: NETO A PAGAR | BL14: RECIBIDO CONFORME
F16: S | G16: D | H16: L | I16: M | J16: M | K16: J | L16: V | O16: S | P16: D | Q16: L | R16: M | S16: M | T16: J | U16: V | V16: S | W16: M
A17: 1 | B17: 200 | C17: HOLMAN HIDALGO | D17: 157.46 | E17: ACOPIO | F17: 157.46 | G17: 0 | H17: 157.46 | I17: 157.46 | J17: 157.46 | K17: 157.46 | L17: 157.46 | M17: 7 | N17: =COUNTIF(M17,7) -> 1 | O17: 157.46 | P17: 0 | Q17: 157.46 | R17: 157.46 | S17: 157.46 | T17: 157.46 | U17: 157.46 | V17: 157.46 | W17: 0 | X17: 7 | Y17: 7 | Z17: =COUNTIF(X17,7) -> 1 | AA17: =+Z17+N17 -> 2 | AB17: =+Y17+M17-1 -> 13 | AC17: =+AB17+AA17 -> 15 | AD17: 15 | AE17: =+H17+Q17 -> 314.92 | AF17: 0 | AG17: =+G17+U170 -> 0 | AH17: =+W17+T17+S17+Q17+P17+O17+L17+K17+J17+H17+G17+F17+U17+V17+I17+R17 -> 2046.98 | AI17: 147.16 | AJ17: =D17*Z17 -> 157.46 | AK17: =+AI17*N17+AJ17*Z17 -> 304.62 | AL17: =+D17 -> 157.46 | AM17: =+D17/8 -> 19.6825 | AN17: =+AL17*AG17 -> 0 | AO17: =+AM17*AF17 -> 0 | AP17: =+AE17*D17 -> 49587.303 | AQ17: =+AI17*I17+AJ17*R17 -> 47965.465 | AR17: =+AD17 -> 15 | AS17: =+B17 -> 200 | AT17: 84 | AU17: 0.857142 | AV17: =AR17*AS17 -> 3000 | AW17: =+AV17-BD17 -> 2785.7145 | AX17: =AR17*AT17*AU17 -> 1079.9989 | AY17: 0.857142 | AZ17: =+AK17+AH17 -> 2351.6 | BA17: =+BE17-AZ17 -> 648.397 | BB17: =+AV17*AY17 -> 2571.426 | BC17: =+BB17/12 -> 214.2855 | BD17: =+BC17 -> 214.2855 | BE17: =+BD17+BC17+BB17 -> 2999.997 | BF17: =+BE17-BD17 -> 2785.7115 | BG17: 5 | BH17: 0 | BI17: =+BE17-BH17 -> 2999.997 | BJ17: 0 | BK17: 0 | BL17: =+A17 -> 1
O26: _______________________________________________ | AQ26: ____________________________________
C27: ELABORADO | P27: REVISADO | AQ27: AUTORIZADO
C28: DEMIS CECILIA MONTIEL GONZALEZ. | P28: LIC. PASTOR CHAVARRIA HERRERA | AK28: LIC. OSMAN GUTIERREZ

Sheet FINCA SIN INSS
A2: AGRÍCOLA SANTA ISABEL
A3: PLANILLA DE SALARIO QUINCENAL
A4: =+ADMON!A5 -> QUINCENA DEL 16 AL 30 DE ABRIL - 2026
L6: 6
A7: No | B7: INSS | C7: NUMERO DE CEDULA | D7: NOMBRES Y APELLIDOS | E7: GENERO | F7: CARGO | G7: cambio del dia | H7: SALARIO DIARIO | I7: SALARIO MENSUAL | J7: I N G R E S O S | R7: RETENCIONES | X7: TOTAL | Y7: FINCA | Z7: DEVENGADO | AA7: COMISARIATO | AB7: SALARIO DEVENGADO | AC7: FIRMAS | AD7: =+P8 -> VACACIONES | AE7: =+Q8 -> 13VO MES
J8: SALARIO QUINCENAL | K8: DIAS LABORADOS | L8: total subcidio | M8: subcidio por dia | N8: DIAS SUBSIDIO | O8: TOTAL BASICO | P8: VACACIONES | Q8: 13VO MES | R8: TOTAL | T8: INSS | U8: IR | V8: ABONO POR PRESTAMOS | W8: TOTAL RETENCION
A10: 1 | B10: 0 | C10: 241-060492-0003J | D10: SANDRO OSMANY GUITIERREZ | E10: M | F10: ADMINISTRADOR | G10: =+'Cambio del dia'!G34 -> 36.6243 | H10: =+I10/30 -> 610.405 | I10: 18312.15 | J10: =(I10/30)*K10-'ADMON COM. '!J29 -> 6097.945 | K10: 15 | L10: =+M10*N10 -> 0 | M10: =H10*60% -> 366.243 | N10: 0 | O10: =+J10-P10-Q10 -> 5081.6208 | P10: =+J10/12 -> 508.16208 | Q10: =+P10 -> 508.16208 | R10: =+Q10+O10+P10 -> 6097.945 | S10: =O10+P10 -> 5589.7829 | W10: =T10 -> 0 | X10: =-W10+O10+P10+Q10 -> 6097.945 | Y10: 0 | Z10: =+X10 -> 6097.945 | AA10: 0 | AB10: =X10-Y10-AA10 -> 6097.945 | AD10: 0 | AE10: 0
A11: 2 | B11: 0 | D11: JONATHAN GUTIERREZ | E11: M | F11: BODEGUERO | G11: =+'Cambio del dia'!G35 -> 36.6243 | H11: 500 | I11: 15000 | J11: =(I11/30)*K11 -> 7500 | K11: 15 | L11: =+M11*N11 -> 0 | M11: =H11*60% -> 300 | N11: 0 | O11: =+J11-P11-Q11 -> 6250 | P11: =+J11/12 -> 625 | Q11: =+P11 -> 625 | R11: =+Q11+O11+P11 -> 7500 | S11: =O11+P11 -> 6875 | T11: 0 | W11: =T11 -> 0 | X11: =-W11+O11+P11+Q11 -> 7500 | Y11: 2500 | Z11: =X11-Y11 -> 5000 | AA11: 2000 | AB11: =+Z11-AA11 -> 3000 | AC11: 0 | AD11: =+AA11-AB11 -> -1000 | AE11: 0 | AF11: =X11-AB11-AE11 -> 4500 | AH11: 0.155 | AI11: =+R11-Q11 -> 6875 | AJ11: =AH11*R11 -> 1162.5 | AL11: 0 | AM11: =0.02*AF11 -> 90 | AN11: =AF11+AJ11+AM11 -> 5752.5
A12: 3 | B12: 0 | D12: JAIRO CANO | E12: M | F12: EBANISTA | G12: =+'Cambio del dia'!G36 -> 36.6243 | H12: 550 | I12: 16500 | J12: =(I12/30)*K12 -> 8250 | K12: 15 | L12: =+M12*N12 -> 0 | M12: =H12*60% -> 330 | N12: 0 | O12: =+J12-P12-Q12 -> 6875 | P12: =+J12/12 -> 687.5 | Q12: =+P12 -> 687.5 | R12: =+Q12+O12+P12 -> 8250 | S12: =O12+P12 -> 7562.5 | W12: =T12 -> 0 | X12: =-W12+O12+P12+Q12 -> 8250 | Y12: 0 | Z12: =X12 -> 8250 | AA12: 0 | AB12: =X12-Y12-AA12 -> 8250 | AD12: 0 | AE12: 0
A13: 1 | B13: 0 | C13: 604-011198-1001J | D13: BERMAN VICENTE MONTALVAN MARTINEZ | E13: M | F13: EBANISTA | G13: =+'Cambio del dia'!G36 -> 36.6243 | H13: 1000 | I13: 30000 | J13: =(I13/30)*K13 -> 13000 | K13: 13 | L13: =+M13*N13 -> 0 | M13: =H13*60% -> 600 | N13: 0 | O13: =+J13-P13-Q13 -> 10833.333 | P13: =+J13/12 -> 1083.3333 | Q13: =+P13 -> 1083.3333 | R13: =+Q13+O13+P13 -> 13000 | S13: =O13+P13 -> 11916.667 | W13: =T13 -> 0 | X13: =-W13+O13+P13+Q13 -> 13000 | Y13: 0 | Z13: =X13 -> 13000 | AA13: 0 | AB13: =X13-Y13-AA13 -> 13000 | AD13: 0 | AE13: 0
A14: 1 | B14: 0 | C14: 0 | D14: MARIO AZAEL REYES MARTINEZ | E14: M | F14: AYUD/EBANISTA | G14: =+'Cambio del dia'!G37 -> 36.6243 | H14: 300 | I14: 9000 | J14: =(I14/30)*K14 -> 1800 | K14: 6 | L14: =+M14*N14 -> 0 | M14: =H14*60% -> 180 | N14: 0 | O14: =+J14-P14-Q14 -> 1500 | P14: =+J14/12 -> 150 | Q14: =+P14 -> 150 | R14: =+Q14+O14+P14 -> 1800 | S14: =O14+P14 -> 1650 | W14: =T14 -> 0 | X14: =-W14+O14+P14+Q14 -> 1800 | Y14: 0 | Z14: =X14 -> 1800 | AA14: 0 | AB14: =X14-Y14-AA14 -> 1800 | AD14: 0 | AE14: 0
A15: TOTALES | F15: =SUM(F14) -> 0 | G15: =SUM(G14:G14) -> 36.6243 | H15: =SUM(H10:H12) -> 1660.405 | I15: =SUM(I10:I12) -> 49812.15 | J15: =SUM(J10:J12) -> 21847.945 | K15: =SUM(K10:K12) -> 45 | L15: =SUM(L10:L12) -> 0 | M15: =SUM(M10:M12) -> 996.243 | N15: =SUM(N10:N12) -> 0 | O15: =SUM(O10:O12) -> 18206.621 | ... R15: =SUM(R10:R12) -> 21847.945 | S15: =SUM(S12:S14) -> 21129.167 | T15: =SUM(T12:T14) -> 0 | U15: =SUM(U12:U14) -> 0 | V15: =SUM(V12:V14) -> 0 | W15: =SUM(W12:W14) -> 0 | X15: =SUM(X10:X14) -> 36647.945 | Y15: =SUM(Y10:Y14) -> 2500 | Z15: =X15-Y15 -> 34147.945 | AA15: =SUM(AA10:AA14) -> 2000 | AB15: =SUM(AB10:AB14) -> 32147.945 | AC15: "EL SEÑOR ES MI PASTOR, NADA ME FALTARA" | AD15: =SUM(AD14:AD14) -> 0 | AE15: =SUM(AE14:AE14) -> 0
H17: 10
H18: 350 | I18: 35.6948 | J18: =+H18*I18 -> 12493.18
J19: =+H18/I18 -> 9.8053498 | K19: =9.81*30 -> 294.3
C31: ELABORADO POR: | K31: REVISADO POR: | AB31: AUTORIZADO POR:
C32: Jose Martin Conrrado | K32: IVAN OROZCO OSEJO | AB32: LIC:OSMAN G GUTIERREZ MORENO

Sheet FINCA INSS 
A2: AGRÍCOLA SANTA ISABEL | AH2: B DIA
A3: PLANILLA DE SALARIO QUINCENAL
A4: =+ADMON!A5 -> QUINCENA DEL 16 AL 30 DE ABRIL - 2026
A8: No | B8: INSS | C8: NUMERO DE CEDULA | D8: NOMBRES Y APELLIDOS | E8: GENERO | F8: CARGO | G8: SALARIO DIARIO | H8: SALARIO MENSUAL | I8: I N G R E S O S | Q8: RETENCIONES | W8: TOTAL | Z8: FINCA | AB8: NETO A PAGAR | AC8: COMISARIATO | AD8: SALARIO DEVENGADO | AE8: FIRMAS | AH8: INSS PATRONAL | AI8: VACACIONES | AJ8: 13VO MES | AK8: INATEC 2% | AL8: TOTAL GASTOS NOMINAS
I9: SALARIO QUINCENAL | J9: DIAS LABORADOS | K9: total subcidio | L9: subcidio por dia | M9: DIAS SUBSIDIO | N9: TOTAL BASICO | O9: VACACIONES | P9: 13VO MES | Q9: TOTAL | S9: INSS | T9: IR | U9: ABONO POR PRESTAMOS | V9: TOTAL RETENCION | X9: ALIMENTACION | Y9: DEVENGADO | AA9: TOTAL
A11: 1 | B11: 23724864 | C11: 241-240972-0016G | D11: WILFREDO ARGEÑAL BLANDON | E11: M | F11: BODEGUERO | G11: 400 | H11: 12000 | I11: =(H11/30)*J11 -> 0 | J11: 0 | K11: =+L11*M11 -> 0 | L11: =G11*60% -> 240 | M11: 0 | N11: =+I11-O11-P11 -> 0 | O11: =+I11/12 -> 0 | P11: =+O11 -> 0 | Q11: =+P11+N11+O11 -> 0 | R11: =N11+O11 -> 0 | S11: =+R11*5% -> 0 | V11: =S11 -> 0 | W11: =-V11+N11+O11+P11 -> 0 | Y11: =W11 -> 0 | Z11: 0 | AA11: 0 | AB11: =+Y11-Z11 -> 0 | AC11: 195 | AD11: =W11-Z11-AC11 -> -195 | AF11: 0.155 | AG11: =+Q11-P11 -> 0 | AH11: =AF11*Q11 -> 0 | AJ11: 0 | AK11: =0.02*AD11 -> -3.9 | AL11: =AD11+AH11+AK11 -> -198.9
A12: 2 | B12: 12762134 | D12: ERICK MANUEL GARCIA | E12: M | F12: SOLDADOR | G12: 241 | H12: 6960 | I12: =(H12/30)*J12 -> 0 | J12: 0 | K12: =+L12*M12 -> 0 | L12: =G12*60% -> 144.6 | M12: 0 | N12: =+I12-O12-P12 -> 0 | O12: =I12/12 -> 0 | P12: =O12 -> 0 | Q12: =+P12+N12+O12 -> 0 | R12: =N12+O12 -> 0 | S12: =+R12*5% -> 0 | V12: =S12 -> 0 | W12: =-V12+N12+O12+P12 -> 0 | X12: 0 | Y12: =W12+X12 -> 0 | Z12: 0 | AA12: 0 | AB12: =+Y12-Z12 -> 0 | AC12: 0 | AD12: =+Y12-Z12-AC12 -> 0 | AF12: 0.155 | AG12: =+Q12-P12 -> 0 | AH12: =AF12*Q12 -> 0 | AJ12: 0 | AK12: =0.02*AD12 -> 0 | AL12: =AD12+AH12+AK12 -> 0
A13: 3 | B13: 12762134 | D13: ANGEL JAVIER GARCIA | E13: M | F13: BODEGUERO | G13: 350 | H13: 10500 | I13: =(H13/30)*J13 -> 0 | J13: 0 | K13: =+L13*M13 -> 0 | L13: =G13*60% -> 210 | M13: 0 | N13: =+I13-O13-P13 -> 0 | O13: =+I13/12 -> 0 | P13: =+O13 -> 0 | Q13: =+P13+N13+O13 -> 0 | R13: =N13+O13 -> 0 | S13: =+R13*5% -> 0 | V13: =S13 -> 0 | W13: =-V13+N13+O13+P13 -> 0 | X13: 750 | Y13: =W13 -> 0 | Z13: 0 | AC13: 0 | AD13: =W13-Z13-AC13 -> 0 | AF13: 0.155 | AG13: =+Q13-P13 -> 0 | AH13: =AF13*Q13 -> 0 | AJ13: 0 | AK13: =0.02*AD13 -> 0 | AL13: =AD13+AH13+AK13 -> 0
A14: 4 | B14: 0 | D14: ALBA SUYEN RODA PASOS | E14: F | F14: PLANILLERA | G14: 350 | H14: 10500 | I14: =(H14/30)*J14 -> 0 | J14: 0 | K14: =+L14*M14 -> 0 | L14: =G14*60% -> 210 | M14: 0 | N14: =+I14-O14-P14 -> 0 | O14: =+I14/12 -> 0 | P14: =+O14 -> 0 | Q14: =+P14+N14+O14 -> 0 | R14: =N14+O14 -> 0 | S14: =+R14*5% -> 0 | V14: =S14 -> 0 | W14: =-V14+N14+O14+P14 -> 0 | X14: 750 | Y14: =W14 -> 0 | Z14: 0 | AC14: 0 | AD14: =W14-Z14-AC14 -> 0 | AF14: 0.155 | AG14: =+Q14-P14 -> 0 | AH14: =AF14*Q14 -> 0 | AJ14: 0 | AK14: =0.02*AD14 -> 0 | AL14: =AD14+AH14+AK14 -> 0
A15: 2 | B15: 23724864 | D15: 0 | E15: M | F15: SOLDADOR | G15: 0 | H15: 6960 | I15: 0 | J15: 0 | K15: =+L15*M15 -> 0 | L15: =G15*60% -> 0 | N15: =+I15-O15-P15 -> 0 | O15: =+I15/12 -> 0 | P15: =+O15 -> 0 | Q15: =+P15+N15+O15 -> 0 | R15: =N15+O15 -> 0 | S15: =+R15*5% -> 0 | V15: =S15 -> 0 | W15: =-V15+N15+O15+P15 -> 0 | X15: 750 | Y15: =W15 -> 0 | Z15: 0 | AC15: 0 | AD15: 0 | AF15: 0.155 | AG15: =+Q15-P15 -> 0 | AH15: =AF15*Q15 -> 0 | AJ15: 0 | AK15: =0.02*AD15 -> 0 | AL15: =AD15+AH15+AK15 -> 0
A16: SUB TOTAL | G16: =+G11+G12+G15 -> 641 | H16: =+H11+H12+H15 -> 25920 | I16: =SUM(I11:I15) -> 0 | J16: =SUM(J11:J15) -> 0 | K16: =SUM(K11:K15) -> 0 | L16: =SUM(L11:L15) -> 804.6 | M16: =SUM(M11:M15) -> 0 | N16: =SUM(N11:N15) -> 0 | O16: =SUM(O11:O15) -> 0 | P16: =SUM(P11:P15) -> 0 | ... W16: =SUM(W11:W15) -> 0 | X16: 0 | Y16: =W16+X16 -> 0 | Z16: =SUM(Z11:Z15) -> 0 | AA16: 0 | AB16: =+Y16-Z16 -> 0 | AC16: =SUM(AC11:AC15) -> 195 | AD16: =SUM(AD10:AD14) -> -195 | AG16: =+AG11+AG12 -> 0 | AH16: =SUM(AH11:AH15) -> 0 | AI16: =SUM(AI11:AI15) -> 0 | AJ16: =SUM(AJ11:AJ15) -> 0 | AK16: =SUM(AK11:AK15) -> -3.9 | AL16: =SUM(AL11:AL15) -> -198.9
A17: TOTALES | G17: =+G16 -> 641 | H17: =+H16 -> 25920 | I17: =+I16 -> 0 | J17: =+J16 -> 0 | K17: =+K16 -> 0 | L17: =+L16 -> 804.6 | M17: =+M16 -> 0 | N17: =+N16 -> 0 | ... Z17: =+Z16 -> 0 | AA17: 0 | AB17: =+W17-Z17 -> 0 | AC17: =AC16 -> 195 | AD17: =+AB17-AC17 -> -195 | AE17: "EL SEÑOR ES MI PASTOR, NADA ME FALTARA" | AF17: =SUM(#REF!) -> #REF! | AG17: =+AG16 -> 0 | AH17: =+AH16 -> 0 | AI17: =+AI16 -> 0 | AJ17: =+AJ16 -> 0 | AK17: =+AK16 -> -3.9 | AL17: =+AL16 -> -198.9
G19: 10
G20: 350 | H20: 35.6948 | I20: =+G20*H20 -> 12493.18
I21: =+G20/H20 -> 9.8053498 | J21: =9.81*30 -> 294.3
H25: 0
C40: ELABORADO POR: | J40: REVISADO POR: | AD40: AUTORIZADO POR:
C41: WILFREDO ARGEÑAL BLANDON | J41: IVAN OROZCO OSEJO | AD41: LIC:OSMAN G GUTIERREZ MORENO

Sheet BENEFICIO SECO
A2: AGRÍCOLA SANTA ISABEL
A3: PLANILLA DE SALARIO QUINCENAL (BENEFICIO SECO SIN INSS)
A4: =+ADMON!A5 -> QUINCENA DEL 16 AL 30 DE ABRIL - 2026
A8: No | B8: INSS | C8: NUMERO DE CEDULA | D8: NOMBRES Y APELLIDOS | E8: GENERO | F8: CARGO | G8: cambio del dia | H8: SALARIO DIARIO | I8: SALARIO MENSUAL | J8: I N G R E S O S | R8: RETENCIONES | X8: TOTAL | Y8: FINCA | Z8: NETO A PAGAR | AA8: COMISARIATO | AB8: SALARIO DEVENGADO | AC8: FIRMA | AD8: =+P9 -> VACACIONES | AE8: =+Q9 -> 13VO MES
J9: SALARIO QUINCENAL | K9: DIAS LABORADOS | L9: total subcidio | M9: subcidio por dia | N9: DIAS SUBSIDIO | O9: TOTAL BASICO | P9: VACACIONES | Q9: 13VO MES | R9: TOTAL | T9: INSS | U9: IR | V9: ABONO POR PRESTAMOS | W9: TOTAL RETENCION
A11: 1 | B11: 0 | C11: 604-090489-0000R | D11: JAIRO CANO | E11: M | F11: RESPONSABLE DE BODEGA | G11: =+'Cambio del dia'!G31 -> 36.6243 | H11: 500 | I11: =+H11*30 -> 15000 | J11: =(I11)/30*K11 -> 0 | K11: 0 | L11: =+M11*N11 -> 0 | M11: 0 | N11: 0 | O11: =+J11-P11-Q11 -> 0 | P11: =+J11/12 -> 0 | Q11: =+P11 -> 0 | R11: =+Q11+O11+P11 -> 0 | S11: =O11+P11 -> 0 | W11: =T11 -> 0 | X11: =-W11+O11+P11+Q11 -> 0 | Y11: 0 | Z11: =+R11-Y11 -> 0 | AA11: 0 | AB11: =X11-Y11-AA11 -> 0 | AD11: 0 | AE11: 0
D12: JOTHAN MOISES GUTIERREZ CHAVEZ | E12: M | F12: MONTACARGA | H12: 500 | I12: =+H12*30 -> 15000 | J12: =(I12)/30*K12 -> 0 | K12: 0 | O12: =+J12-P12-Q12 -> 0 | P12: =+J12/12 -> 0 | Q12: =+P12 -> 0 | R12: =+Q12+O12+P12 -> 0 | X12: =-W12+O12+P12+Q12 -> 0 | Y12: 0 | Z12: =+R12-Y12 -> 0 | AA12: 1994 | AB12: =X12-Y12-AA12 -> -1994
A13: TOTALES | G13: =SUM(#REF!) -> #REF! | H13: =SUM(H11:H12) -> 1000 | I13: =SUM(I11:I12) -> 30000 | J13: =SUM(J11:J12) -> 0 | K13: =SUM(K11:K12) -> 0 | L13: =SUM(L11:L12) -> 0 | M13: =SUM(M11:M12) -> 0 | N13: =SUM(N11:N12) -> 0 | O13: =SUM(O11:O12) -> 0 | ... Y13: =SUM(Y11:Y12) -> 0 | Z13: =+R13-Y13 -> 0 | AA13: =SUM(AA11:AA12) -> 1994 | AB13: =SUM(AB11:AB12) -> -1994 | AC13: "EL SEÑOR ES MI PASTOR, NADA ME FALTARA" | AD13: =SUM(#REF!) -> #REF! | AE13: =SUM(#REF!) -> #REF!
D20: ELABORADO POR: | L20: REVISADO POR: | AC20: AUTORIZADO POR:
D21: WILFREDO ARGEÑAL BLANDON | L21: IVAN OROZCO OSEJO | AC21: LIC: OSMAN G GUTIERREZ MORENO

Sheet Hoja3

Sheet COMPLEMENTO DE SALARIO
A1: AGRICOLA-SANTA ISABEL
A2: COMPLEMENTO DE SALARIO DEL 16 AL 30 DE ABRIL 2026
A3: COMPLEMENTO
A5: No. | B5: NOMBRES Y APELLIDOS | C5: DEVENGADO | F5: COMISARIATO | G5: NETO A PAGAR | H5: RECIBIDO CONFORME
D6: FINCA | E6: DEVENGADO | Q6: =+#REF! -> #REF!
A7: 1 | B7: KEYLIN JOHANA MARTINEZ PEREZ | C7: =M14 -> 3409.2 | D7: 0 | E7: =C7-D7 -> 3409.2 | G7: =+E7-F7 -> 3409.2
A8: 2 | B8: IVAN OROZCO OSEJO | C8: 1600 | D8: 0 | E8: =C8-D8 -> 1600 | G8: =+E8-F8 -> 1600
A9: 3 | C9: 0 | D9: 0 | E9: =C9-D9 -> 0 | F9: 0 | G9: =+E9-F9 -> 0
A10: 3 | B10: MARIA ULDA GARCIA RIVAS | C10: 0 | D10: 0 | E10: =C10-D10 -> 0 | G10: =+E10-F10 -> 0
A11: 3 | B11: =+'ADMON COM. '!D21 -> ARMANDO GUIDO GONZALEZ | C11: 0 | D11: 0 | E11: =C11-D11 -> 0 | G11: =+E11-F11 -> 0
A12: Subtotal | C12: =SUM(C7:C11) -> 5009.2 | D12: =SUM(D7:D11) -> 0 | E12: =SUM(E7:E11) -> 5009.2 | F12: =SUM(F7:F11) -> 0 | G12: =SUM(G7:G11) -> 5009.2 | H12: 'EL SEÑOR ES MI PASTOR NADA ME FALTARA''
L14: =177.28*ADMON!L19 -> 2659.2 | M14: =L14+L17 -> 3409.2
M15: 2659.25
M16: 6409.25
B17: AUTORIZADO POR: | E17: REVISADO | L17: =ADMON!L19*50 -> 750
B18: Lic. Osman G. Gutierrez Moreno Ivan Orozco osejo | L18: =50*ADMON!L19 -> 750

Sheet VIATICOS PERS ACOPIO
A1: AGRICOLA SANTA ISABEL
A2: VIATICO PAGADO A PERSONAL DE ACOPIO
A3: QUINCENA DEL 16 AL 28 DE FEBRERO 2025
A4: N/O | B4: NOMBRE Y APELLIDOS | C4: LUGAR DE ACOPIO | D4: DIAS | E4: VALOR | F4: TOTAL | G4: FIRMA
A5: 15 | B5: MARIA ULDA GARCIA RIVAS | C5: ABICINIA/ INSS | D5: 0 | E5: 80 | F5: =(D5)*E5 -> 0
A6: 16 | B6: JOLMAN ARCENIO HIDALGO GONZALEZ | C6: ABICINIA/ INSS | D6: 0 | E6: 80 | F6: =(D6)*E6 -> 0
F7: =SUM(F5:F6) -> 0
B17: _______________________________ | D17: ______________________________
B18: REVISADO | D18: ACTORIZADO
B19: Lic. Sandro Osmany Gutierrez Sanchez | D19: Lic. Osman Gregorio Gutierrez Moreno

Sheet BODEGA-ACOPIO
A2: AGRÍCOLA SANTA ISABEL
A3: PLANILLA DE SALARIO QUINCENAL DE TÉCNICOS DE ACOPIO
A4: =+ADMON!A5 -> QUINCENA DEL 16 AL 30 DE ABRIL - 2026
A5: =+'ADMON COM. '!A6 -> 15
A6: No | B6: INSS | C6: NUMERO DE CEDULA | D6: NOMBRES Y APELLIDOS | E6: GENERO | F6: CARGO | G6: salario en dolares | H6: cambio del dia | I6: SALARIO DIARIO | J6: SALARIO MENSUAL | K6: I N G R E S O S | Q6: RETENCIONES | U6: TOTAL DEVENGADO | V6: COMISARIATO | W6: FINCA | X6: NETO A PAGAR DEVENGADO | Y6: FIRMAS | Z6: VACASIONES | AA6: 13VO MES | AB6: INSS PATRONAL | AC6: INATEC 2% | AD6: VACACIONES | AE6: 13VO MES | AF6: TOTAL GASTOS NOMINAS
K7: SALARIO QUINCENAL | L7: DIAS LABORADOS | M7: total subcidio | N7: subcidio por dia | O7: DIAS SUBSIDIO | P7: TOTAL INGRESOS | Q7: INSS LABORAL | R7: IR | S7: ABONO POR PRESTAMOS | T7: TOTAL RETENCION
A9: 1 | B9: 0 | C9: 001-060383-0004D | D9: DANIEL RODRIGUEZ | E9: M | F9: Bodega/ Acopio | G9: 350 | H9: =LOOKUP(A5,'Cambio del dia'!F7:G38) -> 36.6243 | I9: 300 | J9: =+I9*30 -> 9000 | K9: =+(J9/30)*L9 -> 0 | L9: 0 | M9: =+N9*O9 -> 0 | N9: =I9*60% -> 180 | O9: 0 | P9: =+K9-M9 -> 0 | Q9: 0 | R9: 0 | T9: =+Q9+R9+S9 -> 0 | U9: =-T9+P9 -> 0 | W9: 0 | X9: =U9-V9-W9 -> 0 | Z9: =+J9/30*1.25 -> 375 | AA9: =+J9/30*1.25 -> 375 | AB9: =IF(B9="",0,P9*21.5%) -> 0 | AC9: =IF(Q9>0,P9*2%,0) -> 0 | AD9: =+K9/12 -> 0 | AE9: =+AD9 -> 0 | AF9: =SUM(P9,AB9,AA9,Z9,AC9) -> 750
A10: 2 | B10: 25093885 | C10: 241-091087-0001E | D10: 0 | E10: M | F10: Técnico de acopio | G10: 350 | H10: =LOOKUP(A5,'Cambio del dia'!F7:G38) -> 36.6243 | I10: =+P10/L10 -> #DIV/0! | J10: =+H10*G10 -> 12818.505 | K10: =(J10/30)*L10 -> 0 | L10: 0 | M10: =+N10*O10 -> #DIV/0! | N10: =I10*60% -> #DIV/0! | O10: 0 | P10: =+K10 -> 0 | Q10: =IF(B10="",0,(P10*7%)) -> 0 | R10: =IF(AND(P10*24>100000,P10*24<=200000),((((P10-Q10)*24)-100000)*15%)/24,IF(AND(P10*24>100000,P10*24<=200000),(((((P10-Q10)*24)-100000)*15%))/24,)) -> 0 | T10: =+Q10+R10+S10 -> 0 | U10: =-T10+P10 -> 0 | V10: 0 | W10: 0 | X10: =+P10-T10+V10-W10 -> 0 | Z10: =+J10/30*1.25 -> 534.10437 | AA10: =+J10/30*1.25 -> 534.10437 | AB10: =IF(B10="",0,P10*21.5%) -> 0 | AC10: =IF(Q10>0,P10*2%,0) -> 0 | AD10: =+K10/12 -> 0 | AE10: =+AD10 -> 0 | AF10: =SUM(P10,AB10,AA10,Z10,AC10) -> 1068.2087
A11: 3 | B11: 21371240 | C11: 001-210878-0075X | D11: 0 | E11: M | F11: Técnico de acopio | G11: 350 | H11: =LOOKUP(A5,'Cambio del dia'!F8:G38) -> 36.6243 | I11: =+P11/L11 -> #DIV/0! | J11: =+H11*G11 -> 12818.505 | K11: =(J11/30)*L11 -> 0 | L11: 0 | M11: =+N11*O11 -> #DIV/0! | N11: =I11*60% -> #DIV/0! | O11: 0 | P11: =+K11 -> 0 | Q11: =IF(B11="",0,(P11*7%)) -> 0 | R11: =IF(AND(P11*24>100000,P11*24<=200000),((((P11-Q11)*24)-100000)*15%)/24,IF(AND(P11*24>100000,P11*24<=200000),(((((P11-Q11)*24)-100000)*15%))/24,)) -> 0 | T11: =+Q11+R11+S11 -> 0 | U11: =-T11+P11 -> 0 | V11: 0 | W11: 0 | X11: =+P11-T11+V11 -> 0 | Z11: =+J11/30*1.25 -> 534.10437 | AA11: =+J11/30*1.25 -> 534.10437 | AB11: =IF(B11="",0,P11*21.5%) -> 0 | AC11: =IF(Q11>0,P11*2%,0) -> 0 | AD11: =+K11/12 -> 0 | AE11: =+AD11 -> 0 | AF11: =SUM(P11,AB11,AA11,Z11,AC11) -> 1068.2087
A12: 4 | B12: 19144283 | C12: 241-210680-0011D | D12: 0 | E12: M | F12: Técnico de acopio | G12: 350 | H12: =LOOKUP(A5,'Cambio del dia'!F7:G38) -> 36.6243 | I12: =+P12/L12 -> #DIV/0! | J12: =+H12*G12 -> 12818.505 | K12: =(J12/30)*L12 -> 0 | L12: 0 | M12: =+N12*O12 -> #DIV/0! | N12: =I12*60% -> #DIV/0! | O12: 0 | P12: =+K12 -> 0 | Q12: =IF(B12="",0,(P12*7%)) -> 0 | R12: =IF(AND(P12*24>100000,P12*24<=200000),((((P12-Q12)*24)-100000)*15%)/24,IF(AND(P12*24>100000,P12*24<=200000),(((((P12-Q12)*24)-100000)*15%))/24,)) -> 0 | T12: =+Q12+R12+S12 -> 0 | U12: =-T12+P12 -> 0 | W12: 0 | X12: =+U12-V12-W12 -> 0 | Z12: =+J12/30*1.25 -> 534.10437 | AA12: =+J12/30*1.25 -> 534.10437 | AB12: =IF(B12="",0,P12*21.5%) -> 0 | AC12: =IF(Q12>0,P12*2%,0) -> 0 | AD12: =+K12/12 -> 0 | AE12: =+AD12 -> 0 | AF12: =SUM(P12,AB12,AA12,Z12,AC12) -> 1068.2087
A13: 5 | B13: 35126559 | C13: 241-241192-0000Q | D13: 0 | E13: F | F13: CAJERA | G13: 250 | H13: 0 | I13: 250 | J13: 7500 | K13: =(J13/30)*L13 -> 0 | L13: 0 | M13: =+N13*O13 -> 0 | N13: =I13*60% -> 150 | O13: 0 | P13: =+K13 -> 0 | Q13: =IF(B13="",0,(P13*5%)) -> 0 | R13: 0 | T13: =+Q13+R13+S13 -> 0 | U13: =-T13+P13 -> 0 | W13: 0 | X13: =+P13-T13+V13-W13 -> 0 | Z13: =+J13/30*1.25 -> 312.5 | AA13: =+J13/30*1.25 -> 312.5 | AB13: =IF(B13="",0,P13*21.5%) -> 0 | AC13: =IF(Q13>0,P13*2%,0) -> 0 | AD13: =+K13/12 -> 0 | AE13: =+AD13 -> 0 | AF13: =SUM(P13,AB13,AA13,Z13,AC13) -> 625
A14: 6 | B14: 8069333 | C14: 001-040170-0013R | D14: 0 | E14: M | F14: COORDINADOR DE ACOPIOS Y FINANZAS | G14: 700 | H14: =LOOKUP(A5,'Cambio del dia'!F7:G38) -> 36.6243 | I14: =+P14/L14 -> #DIV/0! | J14: =+H14*G14 -> 25637.01 | K14: =(J14/30)*L14 -> 0 | L14: 0 | M14: =+N14*O14 -> #DIV/0! | N14: =I14*60% -> #DIV/0! | O14: 0 | P14: =+K14 -> 0 | Q14: =IF(B14="",0,(P14*7%)) -> 0 | R14: =+((((P14-Q14)*24)-100000)*15%/24) -> -625 | T14: 0 | U14: 0 | W14: 0 | X14: 0 | Z14: =+J14/30*1.25 -> 1068.2087 | AA14: =+J14/30*1.25 -> 1068.2087 | AB14: =IF(B14="",0,P14*21.5%) -> 0 | AC14: =IF(Q14>0,P14*2%,0) -> 0 | AD14: =+K14/12 -> 0 | AE14: =+AD14 -> 0 | AF14: =SUM(P14,AB14,AA14,Z14,AC14) -> 2136.4175
A15: TOTALES | G15: =SUM(G9:G12) -> 1400 | I15: =SUM(I9:I9) -> 300 | J15: =SUM(J9:J9) -> 9000 | K15: =SUM(K9:K14) -> 0 | L15: =SUM(L9:L14) -> 0 | M15: =SUM(M9:M14) -> #DIV/0! | N15: =SUM(N9:N14) -> #DIV/0! | O15: =SUM(O9:O14) -> 0 | P15: =SUM(P9:P14) -> 0 | Q15: =SUM(Q9:Q14) -> 0 | R15: =SUM(R9:R14) -> -625 | ... X15: =SUM(X9:X14) -> 0 | Y15: "EL SEÑOR ES MI PASTOR, NADA ME FALTARA" | Z15: =SUM(Z9:Z10) -> 909.10437 | AA15: =SUM(AA9:AA10) -> 909.10437 | AB15: =SUM(AB9:AB14) -> 0 | AC15: =SUM(AC9:AC14) -> 0 | AD15: =SUM(AD9:AD14) -> 0 | AE15: =SUM(AE9:AE14) -> 0 | AF15: =SUM(AF9:AF14) -> 6716.0437
C23: ELABORADO POR: | L23: REVISADO POR: | X23: AUTORIZADO POR:
C24: =+'ADMON COM. '!C50:F50 -> Jose Martin Conrrado | L24: Ivan Orozco Osejo | X24: Lic. Osman Gregorio Gutiérrez Moreno

Sheet ACOPIOst
A2: PLANILLA DILLEROS
A3: =+#REF! -> #REF!
A4: ACOPIO
A7: No. INSS | B7: No. | C7: SALARIO | D7: NOMBRES Y APELLIDOS | E7: SALARIO DIARIO | F7: Actividad | G7: =+[1]ULDA!F9 -> 1 | H7: =+[1]ULDA!G9 -> 2 | I7: =+[1]ULDA!H9 -> 3 | J7: =+[1]ULDA!I9 -> 4 | K7: =+[1]ULDA!J9 -> 5 | L7: =+[1]ULDA!K9 -> 6 | M7: =+[1]ULDA!L9 -> 7 | N7: 1 semana | O7: SEPTIMO DIA | P7: =+[1]H!T12 -> 8 | Q7: =+[1]H!U12 -> 9 | R7: =+[1]H!V12 -> 10 | S7: =+[1]H!W12 -> 11 | T7: =+[1]H!X12 -> 12 | U7: =+[1]H!Y12 -> 13 | V7: =+[1]H!Z12 -> 14 | W7: =+[1]H!AA12 -> 15 | X7: =+[1]H!AB12 -> 16 | Y7: 2 semana | Z7: SEPTIMO DIA | AA7: SUMA SETIMOS | AB7: SUMA DIAS | AC7: DIAS TRAB | AD7: FER LBRS | AE7: HRS EXT | AF7: COSTE | AG7: TOTAL | AH7: DOMINGO LABORADO | AI7: SALARIO BASICO | AJ7: SETIMO | AK7: SETIMO | AL7: SEPT DIA | AM7: COSTE | AN7: COSTE | AO7: DOMINGOS | AP7: HORAS | AQ7: DIAS | AR7: TOTAL | AS7: Extras y/o Dom. Trab | AT7: DIAS | AU7: SALARIO | AV7: DODIGO | AW7: CONSTANTE | AX7: SALARIO 14CENAL | AY7: FORMUAL | AZ7: FORMULA | BA7: FORMULA | BB7: Adicional | BC7: INGRESO BASICO | BD7: VACASIONES | BE7: 13VO MES | BF7: TOTAL INGRESOS | BG7: DEDUCCIONES | BI7: INSS LAB | BJ7: SALARIO NETO | BK7: ALIMENTACION | BL7: NETO A PAGAR | BM7: RECIBIDO CONFORME | BN7: % | BO7: TOTAL INGRESO -TRECEAVO | BP7: INSS PATRONAL | BQ7: Tarifa | BR7: INATEC | BS7: GASTOS NOMINA
AF8: DE UNA | AG8: EN | AM8: DE DIA | AN8: DE UNA | AO8: TRABAJ | AP8: EXTRAS | AQ8: FERIADOS
G9: =+Holman!F16 -> S | H9: =+Holman!G16 -> D | I9: =+Holman!H16 -> L | J9: =+Holman!I16 -> M | K9: =+Holman!J16 -> M | L9: =+Holman!K16 -> J | M9: =+Holman!L16 -> V | P9: =+Holman!O16 -> S | Q9: =+Holman!P16 -> D | R9: =+Holman!Q16 -> L | S9: =+Holman!R16 -> M | T9: =+Holman!S16 -> M | U9: =+Holman!T16 -> J | V9: =+Holman!U16 -> V | W9: =+Holman!V16 -> S | X9: M | AF9: HORA | AG9: $ | AM9: LABORADO | AN9: HORA | BG9: 13v aguinaldo | BH9: %
A10: 17155823 | B10: 2 | C10: 250 | D10: Keylin Johana Martinez Perez | E10: 250 | F10: acopio | G10: 250 | H10: 250 | I10: 250 | J10: 1 | K10: 250 | L10: 250 | M10: 250 | N10: =COUNTIF(G10:M10,250) -> 6 | O10: =COUNTIF(N10,6) -> 1 | P10: 250 | Q10: 250 | R10: 250 | S10: 1 | T10: 250 | U10: 250 | V10: 250 | W10: 250 | X10: 0 | Y10: =COUNTIF(P10:V10,250) -> 6 | Z10: =COUNTIF(Y10,6) -> 1 | AA10: =+Z10+O10 -> 2 | AB10: =COUNTIF(G10:Z10,250) -> 13 | AC10: =+AB10+AA10+AH10+AD10+AE10 -> 18 | AD10: 1 | AE10: 0 | AF10: =+C10/8 -> 31.25 | AG10: =+AF10*AE10 -> 0 | AH10: 2 | AI10: 3500 | AJ10: =+E10*O10 -> 250 | AK10: =+E10*Z10 -> 250 | AL10: =+AJ10+AK10 -> 500 | AM10: =+E10 -> 250 | AN10: =+E10/8 -> 31.25 | AO10: =+AM10*AH10 -> 500 | AP10: =+AN10*AE10 -> 0 | AQ10: =+AD10*E10 -> 250 | AR10: =+AL10+AI10 -> 4000 | AS10: =+AJ10*J10+AK10*S10 -> 500 | AT10: =+AC10 -> 18 | AU10: =+C10 -> 250 | AV10: 84 | AW10: 0.857142 | AX10: =AT10*AU10 -> 4500 | AY10: =+AX10-BF10 -> 0 | AZ10: =AT10*AV10*AW10 -> 1295.9987 | BA10: 0.857142 | BB10: =+BC10-AR10 -> -142.861 | BC10: =+AX10*BA10 -> 3857.139 | BD10: 0 | BE10: 0 | BF10: =+AR10+AS10 -> 4500 | BG10: =+BF10-BE10 -> 4500 | BH10: 0.05 | BI10: =BF10*BH10 -> 225 | BJ10: =+BF10-BI10+AG10 -> 4275 | BK10: 0 | BL10: =+BJ10+BK10 -> 4275 | BM10: =+B10 -> 2 | BN10: 0.15 | BO10: =+BF10-BE10 -> 4500 | BP10: =BF10*BN10 -> 675 | BQ10: 0.02 | BR10: =BJ10*BQ10 -> 85.5 | BS10: =+BL10+BP10+BR10 -> 5035.5
G11: =SUM(G10:G10) -> 250 | H11: =SUM(H10:H10) -> 250 | I11: =SUM(I10:I10) -> 250 | J11: 1 | K11: =SUM(K10:K10) -> 250 | L11: =SUM(L10:L10) -> 250 | M11: =SUM(M10:M10) -> 250 | N11: =SUM(N10:N10) -> 6 | O11: =SUM(O10:O10) -> 1 | P11: =SUM(P10:P10) -> 250 | Q11: =SUM(Q10:Q10) -> 250 | R11: =SUM(R10:R10) -> 250 | ... AG11: =SUM(AG10:AG10) -> 0 | AH11: 2 | AI11: =SUM(AI10:AI10) -> 3500 | AJ11: =SUM(AJ10:AJ10) -> 250 | AK11: =SUM(AK10:AK10) -> 250 | AL11: =SUM(AL10:AL10) -> 500 | AM11: =SUM(AM10:AM10) -> 250 | AN11: =SUM(AN10:AN10) -> 31.25 | AO11: =SUM(AO10:AO10) -> 500 | AP11: =SUM(AP10:AP10) -> 0 | ... BL11: =SUM(BL10:BL10) -> 4275 | BP11: =+BP10 -> 675 | BQ11: =+BQ10 -> 0.02 | BR11: =+BR10 -> 85.5 | BS11: =+BS10 -> 5035.5
A14: SALARIO B | B14: =+AI11 -> 3500 | E14: SEP DIA | G14: =+AL11 -> 500 | H14: TOTAL | I14: =+AR11 -> 4000 | K14: EXT | L14: =+AS11 -> 500 | M14: ADICION | P14: 143 | R14: ING BAS | T14: =+BC11 -> 3857.139 | X14: VACAC | AC14: =+BD11 -> 0 | AE14: 13 VO | AI14: =+BE11 -> 0 | AL14: TOTAL ING | AS14: =+BF11 -> 4500
C15: =#REF! -> #REF! | E15: N/PAGAR | G15: =+BL11 -> 4275 | BG15: GASTOS NOMINA
BG21: =SUM(#REF!) -> #REF!
D22: ELABORADO POR: | M22: REVISADO POR: | AS22: AUTORIZADO POR> | BD22: AUTORIZADO POR:
D23: ANA ESTRADA SEVILLA | L23: Lic. Pastor de Jesús Chavarría Herrera | AS23: Lic Osman Gregorio Gutierrez Moreno | BD23: Lic. Osman Gregorio Gutiérrez Moreno
AV24: ____________________________________

Sheet COMI
A3: JINOTEGA, NICARAGUA
A4: ACOPIO OSMAN GUTIERREZ
A5: PLANILLA DE SALARIO CATORCENAL PERSONAL ADMINISTRATIVO
A6: PERIODO CORRESPONDIENTE DEL 16 AL 29 DE ENERO DEL 2020
A11: =+'ADMON COM. '!A6 -> 15
A12: No. | B12: SALARIO | C12: NOMBRES Y APELLIDOS | D12: SALARIO DIARIO | E12: Actividad | F12: 16 | G12: 17 | H12: 18 | I12: 19 | J12: 20 | K12: 21 | L12: 22 | M12: 1 semana | N12: SEPTIMO DIA | O12: 23 | P12: 24 | Q12: 25 | R12: 26 | S12: 27 | T12: 28 | U12: 29 | V12: 15 | W12: =+'COMISARIATO CON INSS'!Y7 -> 31 | X12: 2 semana | Y12: SEPTIMO DIA | Z12: SUMA SETIMOS | AA12: SUMA DIAS | AB12: DIAS TRABAJADOS | AC12: FERIADOS/ LIBRES | AD12: HRS EXT | AE12: DOM LAB | AF12: SALARIO BASICO | AI12: SEPTIMO DIA | AJ12: COSTE DIA | AK12: COSTE HORA | AL12: DOMINGOS TRABAJADOS | AM12: HORAS EXTRAS | AN12: DIAS FERIADOS | AO12: Extras y/o Dom. Trab | AP12: DIAS | AQ12: SALARIO | AR12: DODIGO | AS12: CONSTANTE | AT12: SALARIO 14CENAL | AU12: FORMUAL | AV12: FORMULA | AW12: FORMULA | AX12: TOTAOL | AY12: adicional | AZ12: INGRESO BASICO | BA12: VACASIONES | BB12: 13VO MES | BC12: TOTAL INGRESOS | BG12: SALARIO NETO | BH12: ALIMENTACION | BI12: NETO A PAGAR | BJ12: RECIBIDO CONFORME
F14: J | G14: V | H14: S | I14: D | J14: L | K14: M | L14: M | O14: J | P14: V | Q14: S | R14: D | S14: L | T14: M | U14: M | V14: S | W14: L
A15: 1 | B15: 0 | C15: EDDY HERNANDEZ | D15: 139.5 | E15: AYUDANTE COMI | F15: 139.5 | G15: 139.5 | H15: 139.5 | I15: 0 | J15: 0 | K15: 0 | L15: 139.5 | M15: =COUNTIF(F15:L15,139.5) -> 4 | N15: =COUNTIF(M15,6) -> 0 | O15: 0 | P15: 0 | Q15: 0 | R15: 0 | S15: 0 | T15: 0 | U15: 0 | V15: 0 | W15: 0 | X15: =COUNTIF(O15:U15,139.5) -> 0 | Y15: =COUNTIF(X15,6) -> 0 | Z15: =+Y15+N15 -> 0 | AA15: =COUNTIF(F15:Y15,139.5) -> 4 | AB15: =+AA15+Z15+AE15+AC15 -> 4 | AC15: 0 | AD15: 0 | AE15: =+R15+I15 -> 0 | AF15: =+W15+T15+S15+Q15+P15+O15+L15+K15+J15+H15+G15+F15+U15+V15 -> 558 | AG15: 138 | AH15: =D15*Y15 -> 0 | AI15: =+AG15*N15+AH15*Y15 -> 0 | AJ15: =+D15 -> 139.5 | AK15: =+D15/8 -> 17.4375 | AL15: =+AJ15*AE15 -> 0 | AM15: =+AK15*AD15 -> 0 | AN15: =+AC15*D15 -> 0 | AO15: =+AG15*I15+AH15*R15 -> 0 | AP15: =+AB15 -> 4 | AQ15: =+B15 -> 0 | AR15: #N/A | AS15: 0.857142 | AT15: =AP15*AQ15 -> 0 | AU15: =+AT15-BB15 -> 0 | AV15: =AP15*AR15*AS15 -> #N/A | AW15: 0.857142 | AX15: =+AI15+AF15 -> 558 | AY15: =+BC15-AX15 -> -558 | AZ15: =+AT15*AW15 -> 0 | BA15: =+AZ15/12 -> 0 | BB15: =+BA15 -> 0 | BC15: =+BB15+BA15+AZ15 -> 0 | BD15: =+BC15-BB15 -> 0 | BE15: 5 | BF15: 0 | BG15: =+BC15-BF15 -> 0 | BH15: 0 | BI15: =+BG15+BH15+AM15 -> 0 | BJ15: =+A15 -> 1
A16: 1 | B16: 0 | C16: FLAVIA HUETE | D16: 139.5 | E16: AYUDANTE COMI | F16: 139.5 | G16: 0 | H16: 0 | I16: 0 | J16: 0 | K16: 0 | L16: 0 | M16: =COUNTIF(F16:L16,139.5) -> 1 | N16: =COUNTIF(M16,6) -> 0 | O16: 0 | P16: 0 | Q16: 0 | R16: 0 | S16: 0 | T16: 0 | U16: 0 | V16: 0 | W16: 0 | X16: =COUNTIF(O16:U16,139.5) -> 0 | Y16: =COUNTIF(X16,6) -> 0 | Z16: =+Y16+N16 -> 0 | AA16: =COUNTIF(F16:Y16,139.5) -> 1 | AB16: =+AA16+Z16+AE16+AC16 -> 1 | AC16: 0 | AD16: 0 | AE16: =+R16+I16 -> 0 | AF16: =+W16+T16+S16+Q16+P16+O16+L16+K16+J16+H16+G16+F16+U16+V16 -> 139.5 | AG16: 138 | AH16: =D16*Y16 -> 0 | AI16: =+AG16*N16+AH16*Y16 -> 0 | AJ16: =+D16 -> 139.5 | AK16: =+D16/8 -> 17.4375 | AL16: =+AJ16*AE16 -> 0 | AM16: =+AK16*AD16 -> 0 | AN16: =+AC16*D16 -> 0 | AO16: =+AG16*I16+AH16*R16 -> 0 | AP16: =+AB16 -> 1 | AQ16: =+B16 -> 0 | AR16: #N/A | AS16: 0.857142 | AT16: =AP16*AQ16 -> 0 | AU16: =+AT16-BB16 -> 0 | AV16: =AP16*AR16*AS16 -> #N/A | AW16: 0.857142 | AX16: =+AI16+AF16 -> 139.5 | AY16: =+BC16-AX16 -> -139.5 | AZ16: =+AT16*AW16 -> 0 | BA16: =+AZ16/12 -> 0 | BB16: =+BA16 -> 0 | BC16: =+BB16+BA16+AZ16 -> 0 | BD16: =+BC16-BB16 -> 0 | BE16: 5 | BF16: 0 | BG16: =+BC16-BF16 -> 0 | BH16: 0 | BI16: =+BG16+BH16+AM16 -> 0 | BJ16: =+A16 -> 1
A17: 1 | B17: 0 | C17: MARIA ELENA FLORES | D17: 139.5 | E17: AYUDANTE COMI | F17: 139.5 | G17: 139.5 | H17: 139.5 | I17: 0 | J17: 0 | K17: 0 | L17: 0 | M17: =COUNTIF(F17:L17,139.5) -> 3 | N17: =COUNTIF(M17,6) -> 0 | O17: 0 | P17: 0 | Q17: 0 | R17: 0 | S17: 0 | T17: 0 | U17: 0 | V17: 0 | W17: 0 | X17: =COUNTIF(O17:U17,139.5) -> 0 | Y17: =COUNTIF(X17,6) -> 0 | Z17: =+Y17+N17 -> 0 | AA17: =COUNTIF(F17:Y17,139.5) -> 3 | AB17: =+AA17+Z17+AE17+AC17 -> 3 | AC17: 0 | AD17: 0 | AE17: =+R17+I17 -> 0 | AF17: =+W17+T17+S17+Q17+P17+O17+L17+K17+J17+H17+G17+F17+U17+V17 -> 418.5 | AG17: 138 | AH17: =D17*Y17 -> 0 | AI17: =+AG17*N17+AH17*Y17 -> 0 | AJ17: =+D17 -> 139.5 | AK17: =+D17/8 -> 17.4375 | AL17: =+AJ17*AE17 -> 0 | AM17: =+AK17*AD17 -> 0 | AN17: =+AC17*D17 -> 0 | AO17: =+AG17*I17+AH17*R17 -> 0 | AP17: =+AB17 -> 3 | AQ17: =+B17 -> 0 | AR17: #N/A | AS17: 0.857142 | AT17: =AP17*AQ17 -> 0 | AU17: =+AT17-BB17 -> 0 | AV17: =AP17*AR17*AS17 -> #N/A | AW17: 0.857142 | AX17: =+AI17+AF17 -> 418.5 | AY17: =+BC17-AX17 -> -418.5 | AZ17: =+AT17*AW17 -> 0 | BA17: =+AZ17/12 -> 0 | BB17: =+BA17 -> 0 | BC17: =+BB17+BA17+AZ17 -> 0 | BD17: =+BC17-BB17 -> 0 | BE17: 5 | BF17: 0 | BG17: =+BC17-BF17 -> 0 | BH17: 0 | BI17: =+BG17+BH17+AM17 -> 0 | BJ17: =+A17 -> 1
F18: =SUM(F15:F17) -> 418.5 | G18: =SUM(G15:G17) -> 279 | H18: =SUM(H15:H17) -> 279 | I18: =SUM(I15:I17) -> 0 | J18: =SUM(J15:J17) -> 0 | K18: =SUM(K15:K17) -> 0 | L18: =SUM(L15:L17) -> 139.5 | M18: =SUM(M15:M17) -> 8 | ... BI18: =SUM(BI15:BI17) -> 0
O26: _______________________________________________ | AO26: ____________________________________
C27: ELABORADO | P27: REVISADO | AO27: AUTORIZADO
C28: Maycol Frc. Molina | P28: LIC. PASTOR CHAVARRIA HERRERA | AO28: LIC. OSMAN GUTIERREZ

Sheet Martin
A6: JINOTEGA, NICARAGUA
A7: PLANILLA DE SALARIO QUINCENAL
A8: =+TECNICOS!A4 -> QUINCENA DEL 16 AL 30 DE ABRIL - 2026
A14: No. | B14: SALARIO | C14: NOMBRES Y APELLIDOS | D14: SALARIO DIARIO | E14: Actividad | F14: =+H!K12 -> 16 | G14: =+H!L12 -> 17 | H14: =+H!M12 -> 18 | I14: =+H!N12 -> 19 | J14: =+H!O12 -> 20 | K14: =+H!P12 -> 21 | L14: =+H!Q12 -> 22 | M14: 1 semana | N14: SEPTIMO DIA | O14: =+H!T12 -> 23 | P14: =+H!U12 -> 24 | Q14: =+H!V12 -> 25 | R14: =+H!W12 -> 26 | S14: =+H!X12 -> 27 | T14: =+H!Y12 -> 28 | U14: =+H!Z12 -> 29 | V14: =+H!AA12 -> 30 | W14: =+H!AB12 -> 16 | Y14: 2 semana | Z14: SEPTIMO DIA | AA14: SUMA SETIMOS | AB14: SUMA DIAS | AD14: DIAS TRABAJADOS | AE14: FERIADOS/ LIBRES | AF14: HRS EXT | AG14: DOM LAB | AH14: SALARIO BASICO | AK14: SEPTIMO DIA | AL14: COSTE DIA | AM14: COSTE HORA | AN14: DOMINGOS TRABAJADOS | AO14: HORAS EXTRAS | AP14: DIAS FERIADOS | AQ14: Extras y/o Dom. Trab | AR14: DIAS | AS14: SALARIO | AT14: DODIGO | AU14: CONSTANTE | AV14: SALARIO 14CENAL | AW14: FORMUAL | AX14: FORMULA | AY14: FORMULA | AZ14: TOTAL | BA14: Adicional | BB14: INGRESO BASICO | BC14: VACASIONES | BD14: 13VO MES | BE14: TOTAL INGRESOS | BI14: SALARIO NETO | BJ14: VIATICO | BK14: NETO A PAGAR | BL14: RECIBIDO CONFORME
F16: =+'COMISARIATO CON INSS'!H9 -> S | G16: =+'COMISARIATO CON INSS'!I9 -> D | H16: =+'COMISARIATO CON INSS'!J9 -> L | I16: =+'COMISARIATO CON INSS'!K9 -> M | J16: =+'COMISARIATO CON INSS'!L9 -> M | K16: =+'COMISARIATO CON INSS'!M9 -> J | L16: =+'COMISARIATO CON INSS'!N9 -> V | O16: =+'COMISARIATO CON INSS'!Q9 -> S | P16: =+'COMISARIATO CON INSS'!R9 -> D | Q16: =+'COMISARIATO CON INSS'!S9 -> L | R16: =+'COMISARIATO CON INSS'!T9 -> M | S16: =+'COMISARIATO CON INSS'!U9 -> M | T16: =+'COMISARIATO CON INSS'!V9 -> J | U16: =+'COMISARIATO CON INSS'!W9 -> V | V16: =+'COMISARIATO CON INSS'!X9 -> S | W16: M
A17: 1 | B17: 266.66 | C17: GEMA GUTIERREZ | D17: 147.16 | E17: ACOPIO | F17: 0 | G17: 0 | H17: 0 | I17: 0 | J17: 0 | K17: 0 | L17: 0 | M17: =COUNTIF(F17:L17,147.16) -> 0 | N17: =COUNTIF(M17,6) -> 0 | O17: 0 | P17: 0 | Q17: 0 | R17: 0 | S17: 0 | T17: 0 | U17: 0 | V17: 0 | W17: 0 | X17: =COUNTIF(N17:V17,147.16) -> 0 | Y17: =COUNTIF(O17:W17,147.16) -> 0 | Z17: =COUNTIF(X17,7) -> 0 | AA17: =+Z17+N17 -> 0 | AB17: =+Y17+M17 -> 0 | AC17: =+AB17+AA17 -> 0 | AD17: =+AB17+AA17+AG17+AE17 -> 0 | AE17: 0 | AF17: 0 | AG17: =+R17+I17 -> 0 | AH17: =+W17+T17+S17+Q17+P17+O17+L17+K17+J17+H17+G17+F17+U17+V17 -> 0 | AI17: 147.16 | AJ17: =D17*Z17 -> 0 | AK17: =+AI17*N17+AJ17*Z17 -> 0 | AL17: =+D17 -> 147.16 | AM17: =+D17/8 -> 18.395 | AN17: =+AL17*AG17 -> 0 | AO17: =+AM17*AF17 -> 0 | AP17: =+AE17*D17 -> 0 | AQ17: =+AI17*I17+AJ17*R17 -> 0 | AR17: =+AD17 -> 0 | AS17: =+B17 -> 266.66 | AT17: 84 | AU17: 0.857142 | AV17: =AR17*AS17 -> 0 | AW17: =+AV17-BD17 -> 0 | AX17: =AR17*AT17*AU17 -> 0 | AY17: 0.857142 | AZ17: =+AK17+AH17 -> 0 | BA17: =+BE17-AZ17 -> 0 | BB17: =+AV17*AY17 -> 0 | BC17: =+BB17/12 -> 0 | BD17: =+BC17 -> 0 | BE17: =+BD17+BC17+BB17 -> 0 | BF17: =+BE17-BD17 -> 0 | BG17: 5 | BH17: 0 | BI17: =+BE17-BH17 -> 0 | BJ17: 0 | BK17: =+BI17+BJ17+AO17 -> 0 | BL17: =+A17 -> 1
O26: _______________________________________________ | AQ26: ____________________________________
C27: ELABORADO | P27: REVISADO | AQ27: AUTORIZADO
C28: Henry Rizo H | P28: LIC. PASTOR CHAVARRIA HERRERA | AQ28: LIC. OSMAN GUTIERREZ

Sheet PERS-ACOPIO STA ISABEL
A2: PLANILLA DE ACOPIO SANTA ISABEL YEMIN DAVID )
A3: PLANILLA DE SALARIO QUINCENAL
A4: =+TECNICOS!A4 -> QUINCENA DEL 16 AL 30 DE ABRIL - 2026
L5: 6
A6: No | B6: INSS | C6: NUMERO DE CEDULA | D6: NOMBRES Y APELLIDOS | E6: GENERO | F6: CARGO | G6: cambio del dia | H6: SALARIO DIARIO | I6: SALARIO MENSUAL | J6: I N G R E S O S | R6: RETENCIONES | X6: TOTAL | Y6: COMISARIATO | Z6: FINCA | AA6: SALARIO DEVENGADO | AB6: FIRMAS | AC6: =+P7 -> VACACIONES | AD6: =+Q7 -> 13VO MES
J7: SALARIO QUINCENAL | K7: DIAS LABORADOS | L7: total subcidio | M7: subcidio por dia | N7: DIAS SUBSIDIO | O7: TOTAL BASICO | P7: VACACIONES | Q7: 13VO MES | R7: TOTAL | T7: INSS | U7: IR | V7: ABONO POR PRESTAMOS | W7: TOTAL RETENCION
A9: 1 | B9: 38675494 | C9: 241-060492-0003J | D9: NORLAN ALEXIS BLANDON MORALES | E9: M | F9: CONDUCTOR | G9: =+'Cambio del dia'!G36 -> 36.6243 | H9: 320 | I9: 9600 | J9: =(I9/30*K9) -> 0 | K9: 0 | L9: =+M9*N9 -> 0 | M9: =H9*60% -> 192 | N9: 0 | O9: =+J9-P9-Q9 -> 0 | P9: =+J9/12 -> 0 | Q9: =+P9 -> 0 | R9: =+Q9+O9+P9 -> 0 | S9: =O9+P9 -> 0 | W9: =T9 -> 0 | X9: =-W9+O9+P9+Q9 -> 0 | Y9: 0 | Z9: 0 | AA9: =X9-Y9-Z9 -> 0 | AC9: 0 | AD9: 0
A10: 1 | B10: 38675494 | C10: 0 | D10: JOSE NAHUM SOZA CASTRO | E10: M | F10: Resp/Bodega | G10: =+'Cambio del dia'!G35 -> 36.6243 | H10: 320 | I10: 9600 | J10: =(I10/30*K10) -> 0 | K10: 0 | L10: =+M10*N10 -> 192 | M10: =H10*60% -> 192 | N10: 1 | O10: =+J10-P10-Q10 -> 0 | P10: =+J10/12 -> 0 | Q10: =+P10 -> 0 | R10: =+Q10+O10+P10 -> 0 | S10: =O10+P10 -> 0 | W10: =T10 -> 0 | X10: =-W10+O10+P10+Q10 -> 0 | Y10: 0 | Z10: 0 | AA10: =X10-Y10-Z10 -> 0 | AC10: 0 | AD10: 0
A11: 1 | B11: 38675494 | C11: 0 | D11: DANIEL ANTONIO RODRIGUEZ | E11: M | F11: RECIBIDOR | G11: =+'Cambio del dia'!G36 -> 36.6243 | H11: 450 | I11: 13500 | J11: =(I11/30*K11) -> 0 | K11: 0 | L11: =+M11*N11 -> 270 | M11: =H11*60% -> 270 | N11: 1 | O11: =+J11-P11-Q11 -> 0 | P11: =+J11/12 -> 0 | Q11: =+P11 -> 0 | R11: =+Q11+O11+P11 -> 0 | S11: =O11+P11 -> 0 | W11: =T11 -> 0 | X11: =-W11+O11+P11+Q11 -> 0 | Y11: 0 | Z11: 0 | AA11: =X11-Y11-Z11 -> 0 | AC11: 0 | AD11: 0
A12: 1 | B12: 38675494 | C12: 0 | D12: JORDAN HERNANDEZ | E12: M | F12: ESTIBADOR | G12: =+'Cambio del dia'!G36 -> 36.6243 | H12: 290 | I12: 8700 | J12: =(I12/30*K12) -> 0 | K12: 0 | L12: =+M12*N12 -> 174 | M12: =H12*60% -> 174 | N12: 1 | O12: =+J12-P12-Q12 -> 0 | P12: =+J12/12 -> 0 | Q12: =+P12 -> 0 | R12: =+Q12+O12+P12 -> 0 | S12: =O12+P12 -> 0 | W12: =T12 -> 0 | X12: =-W12+O12+P12+Q12 -> 0 | Y12: 0 | Z12: 0 | AA12: =X12-Y12-Z12 -> 0 | AC12: 0 | AD12: 0
A13: 1 | B13: 38675494 | C13: 0 | D13: 0 | E13: M | F13: ESTIBADOR | G13: =+'Cambio del dia'!G36 -> 36.6243 | H13: 0 | I13: 0 | J13: =(I13/30*K13) -> 0 | K13: 0 | L13: =+M13*N13 -> 0 | M13: =H13*60% -> 0 | N13: 1 | O13: =+J13-P13-Q13 -> 0 | P13: =+J13/12 -> 0 | Q13: =+P13 -> 0 | R13: =+Q13+O13+P13 -> 0 | S13: =O13+P13 -> 0 | W13: =T13 -> 0 | X13: =-W13+O13+P13+Q13 -> 0 | Y13: 0 | Z13: 0 | AA13: =X13-Y13-Z13 -> 0 | AC13: 0 | AD13: 0
A14: 1 | B14: 38675494 | C14: 0 | D14: 0 | E14: M | F14: ESTIBADOR | G14: =+'Cambio del dia'!G36 -> 36.6243 | H14: 0 | I14: 0 | J14: =(I14/30*K14) -> 0 | K14: 0 | L14: =+M14*N14 -> 0 | M14: =H14*60% -> 0 | N14: 1 | O14: =+J14-P14-Q14 -> 0 | P14: =+J14/12 -> 0 | Q14: =+P14 -> 0 | R14: =+Q14+O14+P14 -> 0 | S14: =O14+P14 -> 0 | W14: =T14 -> 0 | X14: =-W14+O14+P14+Q14 -> 0 | Y14: 0 | Z14: 0 | AA14: =X14-Y14-Z14 -> 0 | AC14: 0 | AD14: 0
A15: 1 | B15: 38675494 | C15: 0 | D15: 0 | E15: M | F15: ESTIBADOR | G15: =+'Cambio del dia'!G36 -> 36.6243 | H15: 0 | I15: 0 | J15: =(I15/30*K15) -> 0 | K15: 0 | L15: =+M15*N15 -> 0 | M15: =H15*60% -> 0 | N15: 1 | O15: =+J15-P15-Q15 -> 0 | P15: =+J15/12 -> 0 | Q15: =+P15 -> 0 | R15: =+Q15+O15+P15 -> 0 | S15: =O15+P15 -> 0 | W15: =T15 -> 0 | X15: =-W15+O15+P15+Q15 -> 0 | Y15: 0 | Z15: 0 | AA15: =X15-Y15-Z15 -> 0 | AC15: 0 | AD15: 0
A16: 1 | B16: 38675494 | C16: 0 | D16: ELIEL FERNANDEZ | E16: M | F16: ESTIBADOR | G16: =+'Cambio del dia'!G35 -> 36.6243 | H16: 0 | I16: 0 | J16: 0 | K16: 0 | L16: =+M16*N16 -> 0 | M16: =H16*60% -> 0 | N16: 1 | O16: =+J16-P16-Q16 -> 0 | P16: =+J16/12 -> 0 | Q16: =+P16 -> 0 | R16: =+Q16+O16+P16 -> 0 | S16: =O16+P16 -> 0 | W16: =T16 -> 0 | X16: =-W16+O16+P16+Q16 -> 0 | Y16: 0 | Z16: 0 | AA16: =X16-Y16-Z16 -> 0 | AC16: 0 | AD16: 0
A17: 1 | B17: 38675494 | C17: 0 | D17: NORLAN ALEXIS BLANDON MORALES | E17: M | F17: CONDUCTOR | G17: =+'Cambio del dia'!G36 -> 36.6243 | H17: 320 | I17: 9600 | J17: =(I17/30*K17) -> 0 | K17: 0 | L17: =+M17*N17 -> 192 | M17: =H17*60% -> 192 | N17: 1 | O17: =+J17-P17-Q17 -> 0 | P17: =+J17/12 -> 0 | Q17: =+P17 -> 0 | R17: =+Q17+O17+P17 -> 0 | S17: =O17+P17 -> 0 | W17: =T17 -> 0 | X17: =-W17+O17+P17+Q17 -> 0 | Y17: 0 | Z17: 0 | AA17: =X17-Y17-Z17 -> 0 | AC17: 0 | AD17: 0
A18: 1 | B18: 38675494 | C18: 0 | D18: 0 | E18: M | F18: ESTIBADOR | G18: =+'Cambio del dia'!G37 -> 36.6243 | H18: 0 | I18: 0 | J18: 0 | K18: 0 | L18: =+M18*N18 -> 0 | M18: =H18*60% -> 0 | N18: 1 | O18: =+J18-P18-Q18 -> 0 | P18: =+J18/12 -> 0 | Q18: =+P18 -> 0 | R18: =+Q18+O18+P18 -> 0 | S18: =O18+P18 -> 0 | W18: =T18 -> 0 | X18: =-W18+O18+P18+Q18 -> 0 | Y18: 0 | Z18: 0 | AA18: =X18-Y18-Z18 -> 0 | AC18: 0 | AD18: 0
A19: TOTALES | F19: =SUM(F18) -> 0 | G19: =SUM(G18:G18) -> 36.6243 | H19: =SUM(H18:H18) -> 0 | I19: 9000 | J19: =SUM(J18:J18) -> 0 | K19: =SUM(K18:K18) -> 0 | L19: =SUM(L18:L18) -> 0 | M19: =SUM(M18:M18) -> 0 | N19: =SUM(N18) -> 1 | O19: =SUM(O9:O18) -> 0 | P19: =SUM(P9:P18) -> 0 | Q19: =SUM(Q9:Q18) -> 0 | R19: =SUM(R9:R18) -> 0 | S19: =SUM(S9:S18) -> 0 | T19: =SUM(T9:T18) -> 0 | U19: =SUM(U9:U18) -> 0 | V19: =SUM(V9:V18) -> 0 | ... AA19: =SUM(AA9:AA18) -> 0 | AB19: "EL SEÑOR ES MI PASTOR, NADA ME FALTARA" | AC19: =SUM(AC18:AC18) -> 0 | AD19: =SUM(AD18:AD18) -> 0
H21: 10
H22: 350 | I22: 35.6948 | J22: =+H22*I22 -> 12493.18
J23: =+H22/I22 -> 9.8053498 | K23: =9.81*30 -> 294.3
C33: ELABORADO POR: | K33: REVISADO POR: | AA33: AUTORIZADO POR:
C34: =+'ADMON COM. '!C50:F50 -> Jose Martin Conrrado | K34: Lic. Sandro Osmany Gutierrez Sanchez | AA34: Lic. Osman Gregorio Gutiérrez Moreno

Sheet EVENTUAL
A2: AGRICOLA SANTA ISABEL
A3: =+ADMON!A5 -> QUINCENA DEL 16 AL 30 DE ABRIL - 2026
A4: TRABAJO EVENTUAL
A7: NOMBRES Y APELLIDOS | C7: DEVENGADO | D7: FINCA | E7: NETO A PAGAR | F7: RECIBI CONFORME
A8: =+'Cambio del dia'!D48 -> PEDRO JOAQUIN HUETE | C8: =+'Cambio del dia'!U48 -> 9339.2 | E8: =C8-D8 -> 9339.2
A9: =+'Cambio del dia'!D49 -> YEMIN DAVID GUTIERREZ MORENO | C9: =+'Cambio del dia'!U49 -> 3334.2763 | D9: 0 | E9: =C9-D9 -> 3334.2763
A10: =+'Cambio del dia'!D50 -> JOAQUIN ENRRIQUE CASTILLO CARCACHE | C10: =+'Cambio del dia'!U50 -> 6409.2525 | E10: =C10-D10 -> 6409.2525
A11: =+'Cambio del dia'!D51 -> LUIS FERNANDO PALACIOS RIOS | C11: =+'Cambio del dia'!U51 -> 6409.2525 | E11: =C11-D11 -> 6409.2525
A12: ='Cambio del dia'!D52 -> MARTIN CONRRADO RIZO | C12: ='Cambio del dia'!L52 -> 6000.0034 | E12: =C12-D12 -> 6000.0034
A13: =+'Cambio del dia'!D53 -> NELLY DEL CARMEN SOBALVARRO THOMAS | C13: =+'Cambio del dia'!U53 -> 5474.9996 | E13: =C13-D13 -> 5474.9996
A14: Subtotal | C14: =SUM(C8:C13) -> 36966.984 | D14: =SUM(D8:D13) -> 0 | E14: =SUM(E8:E13) -> 36966.984 | F14: "EL SEÑOR ES MI PASTOR NADA ME FALTARA"
A20: AUTORIZADO POR
A21: Lic. Osman Gregorio Gutierrez Moreno

Sheet ABISINIA INSS
M1: YEMIN ABEL GUTIERREZ PORRAS
A2: YEMIN ABEL GUTIERREZ PORRAS
A3: AGRÍCOLA SANTA ISABEL
A4: PLANILLA DE SALARIO QUINCENAL ABISINIA
A5: =+ADMON!A5 -> QUINCENA DEL 16 AL 30 DE ABRIL - 2026
A7: No | B7: INSS | C7: NUMERO DE CEDULA | D7: NOMBRES Y APELLIDOS | E7: GENERO | F7: CARGO | G7: SALARIO DIARIO | H7: SALARIO MENSUAL | I7: I N G R E S O S | Q7: RETENCIONES | W7: TOTAL | X7: COMISARIATO | Y7: FINCA | Z7: SALARIO DEVENGADO | AA7: FIRMAS | AD7: INSS PATRONAL | AE7: VACACIONES | AF7: 13VO MES | AG7: INATEC 2% | AH7: TOTAL GASTOS NOMINAS
I8: SALARIO QUINCENAL | J8: DIAS LABORADOS | K8: total subcidio | L8: subcidio por dia | M8: DIAS SUBSIDIO | N8: TOTAL BASICO | O8: VACACIONES | P8: 13VO MES | Q8: TOTAL | S8: INSS | T8: IR | U8: ABONO POR PRESTAMOS | V8: TOTAL RETENCION
A10: 1 | B10: 7305067 | D10: MARIA ULDA GARCIA RIVAS | E10: F | F10: ATENCION AL CLIENTE Y CAJA | G10: 240 | H10: 0 | I10: =(H10/30)*J10 -> 0 | J10: 15 | K10: =+L10*M10 -> 0 | L10: =G10*60% -> 144 | M10: 0 | N10: =+I10-O10-P10 -> 0 | O10: 0 | P10: =+O10 -> 0 | Q10: =+P10+N10+O10 -> 0 | R10: =N10+O10 -> 0 | S10: =+R10*5% -> 0 | V10: =S10 -> 0 | W10: =-V10+N10+O10+P10 -> 0 | X10: 0 | Y10: 0 | Z10: =W10-X10-Y10 -> 0 | AB10: 0.155 | AC10: =+Q10-P10 -> 0 | AD10: =AB10*Q10 -> 0 | AE10: =+I10/12 -> 0 | AF10: =+I10/12 -> 0 | AG10: =0.02*Z10 -> 0 | AH10: =Z10+AD10+AG10+AE10+AF10 -> 0
A11: 1 | B11: 36922907 | C11: 241-240392-0004S | D11: HOLMAN ARCENIO HIDALGO GONZALEZ | E11: M | F11: RESPONSABLE DE BODEGA | G11: 257.16 | H11: 6171.6 | I11: =(H11/30)*J11 -> 3085.8 | J11: 15 | K11: =+L11*M11 -> 0 | L11: =G11*60% -> 154.296 | M11: 0 | N11: =G11*J11 -> 3857.4 | O11: 0 | P11: 0 | Q11: =+P11+N11+O11 -> 3857.4 | R11: =N11+O11 -> 3857.4 | S11: =+R11*5% -> 192.87 | V11: =S11 -> 192.87 | W11: =-V11+N11+O11+P11 -> 3664.53 | X11: 0 | Y11: 0 | Z11: =W11-X11-Y11 -> 3664.53 | AB11: 0.155 | AC11: =+Q11-P11 -> 3857.4 | AD11: =AB11*Q11 -> 597.897 | AE11: 0 | AF11: 0 | AG11: =0.02*Z11 -> 73.2906 | AH11: =Z11+AD11+AG11 -> 4335.7176
A12: TOTALES | G12: 0 | H12: =SUM(H10:H11) -> 6171.6 | I12: =SUM(I10:I11) -> 3085.8 | J12: =SUM(J10:J11) -> 30 | K12: =SUM(K10:K11) -> 0 | L12: =SUM(L10:L11) -> 298.296 | M12: =SUM(M10:M11) -> 0 | N12: =SUM(N10:N11) -> 3857.4 | O12: =SUM(O10:O11) -> 0 | Q12: =SUM(Q10:Q11) -> 3857.4 | R12: =SUM(R10:R11) -> 3857.4 | S12: =SUM(S10:S11) -> 192.87 | U12: =SUM(U10:U11) -> 0 | V12: =SUM(V10:V11) -> 192.87 | W12: =SUM(W10:W11) -> 3664.53 | X12: =SUM(X10:X11) -> 0 | Y12: =SUM(Y10:Y11) -> 0 | Z12: =SUM(Z10:Z11) -> 3664.53 | AA12: "EL SEÑOR ES MI PASTOR, NADA ME FALTARA" | AB12: =SUM(#REF!) -> #REF! | AC12: =SUM(#REF!) -> #REF! | AD12: =SUM(AD10:AD11) -> 597.897 | AE12: =SUM(AE10:AE11) -> 0 | AF12: =SUM(AF10:AF11) -> 0 | AG12: =SUM(AG10:AG11) -> 73.2906 | AH12: =SUM(AH10:AH11) -> 4335.7176
G14: 10
G15: 350 | H15: 35.6948 | I15: =+G15*H15 -> 12493.18
I16: =+G15/H15 -> 9.8053498 | J16: =9.81*30 -> 294.3
C28: ELABORADO POR: | J28: REVISADO POR: | Z28: AUTORIZADO POR:
C29: =+'ADMON COM. '!C50:F50 -> Jose Martin Conrrado | J29: IVAN OROZCO OSEJO | Z29: LIC:OSMAN G GREGORIO GUTIERREZ MORENO

Sheet ACOP MONTECRISTO
A1: SANDRO OSMANY GUTIERREZ SANCHEZ
A2: AGRÍCOLA SANTA ISABEL (MONTECRISTO)
A3: PLANILLA DE SALARIO QUINCENAL
B4: =+ADMON!A5 -> QUINCENA DEL 16 AL 30 DE ABRIL - 2026
L5: 6
A6: No | B6: INSS | C6: NUMERO DE CEDULA | D6: NOMBRES Y APELLIDOS | E6: GENERO | F6: CARGO | G6: cambio del dia | H6: SALARIO DIARIO | I6: SALARIO MENSUAL | J6: I N G R E S O S | R6: RETENCIONES | X6: TOTAL | Y6: FINCA | AA6: NEATO A PAGAR | AB6: COMISARIATO | AC6: SALARIO DEVENGADO | AD6: FIRMAS | AE6: =+P7 -> VACACIONES | AF6: =+Q7 -> 13VO MES
J7: SALARIO QUINCENAL | K7: DIAS LABORADOS | L7: total subcidio | M7: subcidio por dia | N7: DIAS SUBSIDIO | O7: TOTAL BASICO | P7: VACACIONES | Q7: 13VO MES | R7: TOTAL | T7: INSS | U7: IR | V7: ABONO POR PRESTAMOS | W7: TOTAL RETENCION | Z7: TOTAL
A9: 1 | B9: 0 | C9: 241-200179-0014C | D9: JOSE JAVIER GONZALEZ LOPEZ | E9: M | F9: RESPONSABLE ACOPIO | G9: =+#REF! -> #REF! | H9: 400 | I9: =+H9*30 -> 12000 | J9: =(I9/30*K9) -> 0 | K9: 0 | L9: =+M9*N9 -> 0 | M9: =H9*60% -> 240 | N9: 0 | O9: =+J9-P9-Q9 -> 0 | P9: =+J9/12 -> 0 | Q9: =+P9 -> 0 | R9: =+Q9+O9+P9 -> 0 | S9: =O9+P9 -> 0 | W9: =T9 -> 0 | X9: =-W9+O9+P9+Q9 -> 0 | Y9: 0 | Z9: 0 | AA9: =+R9-Y9 -> 0 | AB9: 0 | AC9: =X9-Y9-AB9 -> 0 | AE9: 0 | AF9: 0
A10: 2 | B10: 0 | C10: 0 | D10: LESSIN NOEL PICADO | E10: M | F10: CONDUCTOR | G10: =+#REF! -> #REF! | H10: 400 | I10: =+H10*30 -> 12000 | J10: =(I10/30*K10) -> 0 | K10: 0 | L10: =+M10*N10 -> 0 | M10: =H10*60% -> 240 | N10: 0 | O10: =+J10-P10-Q10 -> 0 | P10: =+J10/12 -> 0 | Q10: =+P10 -> 0 | R10: =+Q10+O10+P10 -> 0 | S10: =O10+P10 -> 0 | W10: =T10 -> 0 | X10: =-W10+O10+P10+Q10 -> 0 | Y10: 0 | Z10: 0 | AA10: =+R10-Y10 -> 0 | AB10: 0 | AC10: =X10-Y10-AB10 -> 0 | AE10: 0 | AF10: 0
A11: 3 | B11: 38675494 | C11: 0 | D11: ALEXIS URIEL PALACIOS PALACIOS | E11: M | F11: ESTIBADOR | G11: =+#REF! -> #REF! | H11: 500 | I11: =+H11*30 -> 15000 | J11: =(I11/30*K11) -> 0 | K11: 0 | L11: =+M11*N11 -> 0 | M11: =H11*60% -> 300 | N11: 0 | O11: =+J11-P11-Q11 -> 0 | P11: =+J11/12 -> 0 | Q11: =+P11 -> 0 | R11: =+Q11+O11+P11 -> 0 | S11: =O11+P11 -> 0 | W11: =T11 -> 0 | X11: =-W11+O11+P11+Q11 -> 0 | Y11: 0 | Z11: 0 | AA11: =+R11-Y11 -> 0 | AB11: 0 | AC11: =X11-Y11-AB11 -> 0 | AE11: 0 | AF11: 0
A12: TOTALES | G12: =SUM(#REF!) -> #REF! | H12: =SUM(H9:H11) -> 1300 | I12: =SUM(I9:I11) -> 39000 | J12: =SUM(J9:J11) -> 0 | K12: =SUM(K9:K11) -> 0 | L12: =SUM(L9:L11) -> 0 | M12: =SUM(M9:M11) -> 780 | N12: =SUM(N9:N11) -> 0 | O12: =SUM(O9:O11) -> 0 | ... W12: =SUM(W9:W11) -> 0 | X12: =R12 -> 0 | Y12: =SUM(Y9:Y11) -> 0 | Z12: =SUM(Z9:Z11) -> 0 | AA12: =+R12-Y12 -> 0 | AB12: =SUM(AB9:AB11) -> 0 | AC12: =+AA12-AB12 -> 0 | AD12: "EL SEÑOR ES MI PASTOR, NADA ME FALTARA" | AE12: =SUM(AE9:AE11) -> 0 | AF12: =SUM(AF9:AF11) -> 0
C26: ELABORADO POR: | K26: REVISADO POR: | AC26: AUTORIZADO POR:
C27: =+ADMON!C30 -> Jose Martin Conrrado | K27: Lic. Sandro Osmany Gutierrez Sanchez | AC27: Lic. Osman Gregorio Gutiérrez Moreno

Sheet ACOP LAS MORENAS
A1: DENISSA DALILA MONTIEL GONZALEZ
A2: AGRICOLA SANTA ISABEL (LAS MORENAS)
A3: PLANILLA DE SALARIO QUINCENAL ( LAS MORENAS)
B4: =+ADMON!A5 -> QUINCENA DEL 16 AL 30 DE ABRIL - 2026
L5: 6
A6: No | B6: INSS | C6: NUMERO DE CEDULA | D6: NOMBRES Y APELLIDOS | E6: GENERO | F6: CARGO | G6: cambio del dia | H6: SALARIO DIARIO | I6: SALARIO MENSUAL | J6: I N G R E S O S | R6: RETENCIONES | X6: TOTAL | Y6: FINCA | Z6: NETO A PAGAR | AA6: COMISARIATO | AB6: SALARIO DEVENGADO | AC6: FIRMAS | AD6: =+P7 -> VACACIONES | AE6: =+Q7 -> 13VO MES
J7: SALARIO QUINCENAL | K7: DIAS LABORADOS | L7: total subcidio | M7: subcidio por dia | N7: DIAS SUBSIDIO | O7: TOTAL BASICO | P7: VACACIONES | Q7: 13VO MES | R7: TOTAL | T7: INSS | U7: IR | V7: ABONO POR PRESTAMOS | W7: TOTAL RETENCION
A9: 1 | B9: 0 | C9: 452-021292-0003W | D9: HARVIN ENOC MARIN | E9: M | F9: RESPONSABLE ACOPIO | G9: =+#REF! -> #REF! | H9: 400 | I9: =+H9*30 -> 12000 | J9: =(I9/30*K9) -> 0 | K9: 0 | L9: =+M9*N9 -> 0 | M9: =H9*60% -> 240 | N9: 0 | O9: =+J9-P9-Q9 -> 0 | P9: =+J9/12 -> 0 | Q9: =+P9 -> 0 | R9: =+Q9+O9+P9 -> 0 | S9: =O9+P9 -> 0 | W9: =T9 -> 0 | X9: =-W9+O9+P9+Q9 -> 0 | Y9: 0 | Z9: =+X9-Y9 -> 0 | AA9: 0 | AB9: =X9-Y9-AA9 -> 0 | AD9: 0 | AE9: 0
A10: 2 | C10: 452-080793-0002V | D10: ELVIN ARIEL MARIN RIZO | E10: M | F10: CONDUCTOR | G10: =+#REF! -> #REF! | H10: 400 | I10: =+H10*30 -> 12000 | J10: =(I10/30*K10) -> 0 | K10: 0 | L10: =+M10*N10 -> 0 | M10: =H10*60% -> 240 | N10: 0 | O10: =+J10-P10-Q10 -> 0 | P10: =+J10/12 -> 0 | Q10: =+P10 -> 0 | R10: =+Q10+O10+P10 -> 0 | S10: =O10+P10 -> 0 | W10: =T10 -> 0 | X10: =-W10+O10+P10+Q10 -> 0 | Y10: 0 | Z10: =+X10-Y10 -> 0 | AA10: 0 | AB10: =X10-Y10-AA10 -> 0 | AD10: 0 | AE10: 0
A11: 3 | B11: 0 | C11: 0 | D11: CARLOS ALEMAN | E11: M | F11: ESTIBADOR | G11: =+#REF! -> #REF! | H11: 500 | I11: =+H11*30 -> 15000 | J11: =(I11/30*K11) -> 0 | K11: 0 | L11: =+M11*N11 -> 0 | M11: =H11*60% -> 300 | N11: 0 | O11: =+J11-P11-Q11 -> 0 | P11: =+J11/12 -> 0 | Q11: =+P11 -> 0 | R11: =+Q11+O11+P11 -> 0 | S11: =O11+P11 -> 0 | W11: =T11 -> 0 | X11: =-W11+O11+P11+Q11 -> 0 | Y11: 0 | Z11: =+X11-Y11 -> 0 | AA11: 0 | AB11: =X11-Y11-AA11 -> 0 | AD11: 0 | AE11: 0
A12: 3 | B12: 0 | C12: 0 | D12: MANUEL MAIRENA | E12: M | F12: ESTIBADOR | G12: =+#REF! -> #REF! | H12: 500 | I12: =+H12*30 -> 15000 | J12: =(I12/30*K12) -> 0 | K12: 0 | L12: =+M12*N12 -> 0 | M12: =H12*60% -> 300 | N12: 0 | O12: =+J12-P12-Q12 -> 0 | P12: =+J12/12 -> 0 | Q12: =+P12 -> 0 | R12: =+Q12+O12+P12 -> 0 | S12: =O12+P12 -> 0 | W12: =T12 -> 0 | X12: =-W12+O12+P12+Q12 -> 0 | Y12: 0 | Z12: =+X12-Y12 -> 0 | AA12: 0 | AB12: =X12-Y12-AA12 -> 0 | AD12: 0 | AE12: 0
A13: TOTALES | G13: =SUM(#REF!) -> #REF! | H13: =SUM(H9:H12) -> 1800 | I13: =SUM(I9:I12) -> 54000 | J13: =SUM(J9:J12) -> 0 | K13: =SUM(K9:K12) -> 0 | L13: =SUM(L9:L12) -> 0 | M13: =SUM(M9:M12) -> 1080 | N13: =SUM(N9:N12) -> 0 | O13: =SUM(O9:O12) -> 0 | ... Y13: =SUM(Y9:Y12) -> 0 | Z13: =+X13-Y13 -> 0 | AA13: =SUM(AA9:AA12) -> 0 | AB13: =SUM(AB9:AB12) -> 0 | AC13: "EL SEÑOR ES MI PASTOR, NADA ME FALTARA" | AD13: =SUM(AD9:AD12) -> 0 | AE13: =SUM(AE9:AE12) -> 0
C27: ELABORADO POR: | K27: REVISADO POR: | AB27: AUTORIZADO POR:
C28: =+ADMON!C30 -> Jose Martin Conrrado | K28: Lic. Sandro Osmany Gutierrez Sanchez | AB28: Lic. Osman Gregorio Gutiérrez Moreno

Sheet ACOP ABISINIA SIN INSS
A1: YEMIN ABEL GUTIERREZ PORRAS
A3: AGRÍCOLA SANTA ISABEL (ABISINIA)
A4: PLANILLA DE SALARIO QUINCENAL
B5: =+ADMON!A5 -> QUINCENA DEL 16 AL 30 DE ABRIL - 2026
L6: 6
A7: No | B7: INSS | C7: NUMERO DE CEDULA | D7: NOMBRES Y APELLIDOS | E7: GENERO | F7: CARGO | G7: cambio del dia | H7: SALARIO DIARIO | I7: SALARIO MENSUAL | J7: I N G R E S O S | R7: RETENCIONES | X7: TOTAL | Y7: FINCA | Z7: COMISARIATO | AA7: SALARIO DEVENGADO | AB7: FIRMAS | AC7: =+P8 -> VACACIONES | AD7: =+Q8 -> 13VO MES
J8: SALARIO QUINCENAL | K8: DIAS LABORADOS | L8: total subcidio | M8: subcidio por dia | N8: DIAS SUBSIDIO | O8: TOTAL BASICO | P8: VACACIONES | Q8: 13VO MES | R8: TOTAL | T8: INSS | U8: IR | V8: ABONO POR PRESTAMOS | W8: TOTAL RETENCION
A10: 1 | B10: 0 | C10: 0 | D10: DAVID ISRRAEL ALMENDARES ROCHA | E10: M | F10: ESTIBADOR | G10: =+#REF! -> #REF! | H10: 320 | I10: =+H10*30 -> 9600 | J10: =(I10/30*K10) -> 0 | K10: 0 | L10: =+M10*N10 -> 0 | M10: =H10*60% -> 192 | N10: 0 | O10: =+J10-P10-Q10 -> 0 | P10: =+J10/12 -> 0 | Q10: =+P10 -> 0 | R10: =+Q10+O10+P10 -> 0 | S10: =O10+P10 -> 0 | W10: =T10 -> 0 | X10: =-W10+O10+P10+Q10 -> 0 | Y10: 0 | Z10: 0 | AA10: =X10-Y10-Z10 -> 0 | AC10: 0 | AD10: 0
A11: 1 | B11: 0 | C11: 0 | D11: JOSE MIGUEL BERRIOS ROCHA | E11: M | F11: ESTIBADOR | G11: =+#REF! -> #REF! | H11: 320 | I11: =+H11*30 -> 9600 | J11: =(I11/30*K11) -> 0 | K11: 0 | L11: =+M11*N11 -> 0 | M11: =H11*60% -> 192 | N11: 0 | O11: =+J11-P11-Q11 -> 0 | P11: =+J11/12 -> 0 | Q11: =+P11 -> 0 | R11: =+Q11+O11+P11 -> 0 | S11: =O11+P11 -> 0 | W11: =T11 -> 0 | X11: =-W11+O11+P11+Q11 -> 0 | Y11: 0 | Z11: 0 | AA11: =X11-Y11-Z11 -> 0 | AC11: 0 | AD11: 0
A12: 2 | B12: 0 | C12: 0 | D12: DAVID ISRRAEL ALMENDARES ROCHA | E12: M | F12: ESTIBADOR | G12: =+#REF! -> #REF! | H12: 320 | I12: =+H12*30 -> 9600 | J12: =(I12/30*K12) -> 0 | K12: 0 | L12: =+M12*N12 -> 0 | M12: =H12*60% -> 192 | N12: 0 | O12: =+J12-P12-Q12 -> 0 | P12: =+J12/12 -> 0 | Q12: =+P12 -> 0 | R12: =+Q12+O12+P12 -> 0 | S12: =O12+P12 -> 0 | W12: =T12 -> 0 | X12: =-W12+O12+P12+Q12 -> 0 | Y12: 0 | Z12: 0 | AA12: =X12-Y12-Z12 -> 0 | AC12: 0 | AD12: 0
A14: TOTALES | G14: =SUM(#REF!) -> #REF! | H14: =SUM(H10:H11) -> 640 | I14: =SUM(I10:I11) -> 19200 | J14: =SUM(J10:J11) -> 0 | K14: =SUM(K10:K11) -> 0 | L14: =SUM(L10:L11) -> 0 | M14: =SUM(M10:M11) -> 384 | N14: =SUM(N10:N11) -> 0 | O14: =SUM(O10:O11) -> 0 | ... AA14: =SUM(AA10:AA11) -> 0 | AB14: "EL SEÑOR ES MI PASTOR, NADA ME FALTARA" | AC14: =SUM(#REF!) -> #REF! | AD14: =SUM(#REF!) -> #REF!
C28: ELABORADO POR: | K28: REVISADO POR: | AA28: AUTORIZADO POR:
C29: =+ADMON!C30 -> Jose Martin Conrrado | K29: Lic. Sandro Osmany Gutierrez Sanchez | AA29: Lic. Osman Gregorio Gutiérrez Moreno

Sheet ACOP ESCAMBRAY
A1: DONALD JOSE BALTODANO PALACIOS
A2: AGRÍCOLA SANTA ISABEL (ESCAMBRAY)
A3: PLANILLA DE SALARIO QUINCENAL ( ESCAMBRAY)
B4: =+ADMON!A5 -> QUINCENA DEL 16 AL 30 DE ABRIL - 2026
A6: No | B6: INSS | C6: NUMERO DE CEDULA | D6: NOMBRES Y APELLIDOS | E6: GENERO | F6: CARGO | G6: cambio del dia | H6: SALARIO DIARIO | I6: SALARIO MENSUAL | J6: I N G R E S O S | P6: RETENCIONES | V6: TOTAL | W6: FINCA | X6: COMISARIATO | Y6: SALARIO DEVENGADO | Z6: FIRMAS | AA6: =+N7 -> VACACIONES | AB6: =+O7 -> 13VO MES
J7: SALARIO QUINCENAL | K7: DIAS LABORADOS | L7: DIAS SUBSIDIO | M7: TOTAL BASICO | N7: VACACIONES | O7: 13VO MES | P7: TOTAL | R7: INSS | S7: IR | T7: ABONO POR PRESTAMOS | U7: TOTAL RETENCION
A9: 1 | B9: 0 | C9: 241-20097-1004H | D9: GLENDA MARGINES SILES HERNANDEZ | E9: F | F9: RESPONSABLE ACOPIO | G9: =+#REF! -> #REF! | H9: 350 | I9: =+H9*30 -> 10500 | J9: =(I9/30*K9) -> 0 | K9: 0 | L9: 0 | M9: =+J9-N9-O9 -> 0 | N9: =+J9/12 -> 0 | O9: =+N9 -> 0 | P9: =+O9+M9+N9 -> 0 | Q9: =M9+N9 -> 0 | U9: =R9 -> 0 | V9: =-U9+M9+N9+O9 -> 0 | W9: 0 | X9: 0 | Y9: =V9-W9-X9 -> 0 | AA9: 0 | AB9: 0
A10: 2 | B10: 0 | C10: 492-031098-1002K | D10: ABNNER ELIACM JIRON GONZALEZ | E10: M | F10: ESTIBADOR | G10: =+#REF! -> #REF! | H10: 320 | I10: =+H10*30 -> 9600 | J10: =(I10/30*K10) -> 0 | K10: 0 | L10: 0 | M10: =+J10-N10-O10 -> 0 | N10: =+J10/12 -> 0 | O10: =+N10 -> 0 | P10: =+O10+M10+N10 -> 0 | Q10: =M10+N10 -> 0 | U10: =R10 -> 0 | V10: =-U10+M10+N10+O10 -> 0 | W10: 0 | X10: 0 | Y10: =V10-W10-X10 -> 0 | AA10: 0 | AB10: 0
A11: TOTALES | G11: =SUM(#REF!) -> #REF! | H11: =SUM(H10:H10) -> 320 | I11: =SUM(I9:I10) -> 20100 | J11: =SUM(J10:J10) -> 0 | K11: =SUM(K10:K10) -> 0 | L11: =SUM(L9:L10) -> 0 | M11: =SUM(M9:M10) -> 0 | N11: =SUM(N9:N10) -> 0 | O11: =SUM(O9:O10) -> 0 | P11: =SUM(P9:P10) -> 0 | Q11: =SUM(Q9:Q10) -> 0 | R11: =SUM(R9:R10) -> 0 | S11: =SUM(S9:S10) -> 0 | ... Y11: =SUM(Y9:Y10) -> 0 | Z11: "EL SEÑOR ES MI PASTOR, NADA ME FALTARA" | AA11: =SUM(#REF!) -> #REF! | AB11: =SUM(#REF!) -> #REF!
C25: ELABORADO POR: | K25: REVISADO POR: | Y25: AUTORIZADO POR:
C26: =+ADMON!C30 -> Jose Martin Conrrado | K26: Lic. Sandro Osmany Gutierrez Sanchez | Y26: Lic. Osman Gregorio Gutiérrez Moreno

Sheet VIATICOS ACOPIO
A1: AGRICOLA SANTA ISABEL
A2: VIATICO PAGADO A PERSONAL DE ACOPIO
A3: =+ADMON!A5 -> QUINCENA DEL 16 AL 30 DE ABRIL - 2026
A5: N/O | B5: NOMBRE Y APELLIDOS | C5: LUGAR DE ACOPIO | D5: DIAS | E5: VALOR | F5: TOTAL | G5: FIRMA
A6: 1 | B6: MARIA ULDA GARCIA RIVAS | C6: ABISINIA | D6: 0 | E6: 80 | F6: =(D6)*E6 -> 0
A7: 2 | B7: JOLMAN ARCENIO HIDALGO GONZALEZ | C7: ABISINIA | D7: 0 | E7: 80 | F7: =(D7)*E7 -> 0
A8: 3 | B8: JOSE MIGUEL BERRIOS ROCHA | C8: ABISINIA | D8: 0 | E8: 80 | F8: =(D8)*E8 -> 0
A9: 3 | B9: DAVID ISRAEL ALMENDARES ROCHA | C9: ABISNIA | D9: 0 | E9: 80 | F9: =(D9)*E9 -> 0
A10: 4 | B10: RICARDO ALBERTO PORTILLO HERRERA | C10: EL CONSUELO | D10: 0 | E10: 75 | F10: =(D10)*E10 -> 0
A11: 5 | B11: EVELYN JUNNIETH PORTILLO | C11: EL CONSUELO | D11: 0 | E11: 75 | F11: =(D11)*E11 -> 0
A12: 8 | B12: ABNNER ELIAM JIRON GONZALEZ | C12: ESCAMBRAY | D12: 0 | E12: 75 | F12: =(D12)*E12 -> 0
A13: 9 | B13: GLENDA MARGINES SILES HERNANDEZ | C13: ESCAMBRAY | D13: 0 | E13: 100 | F13: =(D13)*E13 -> 0
A14: 5 | B14: HARVIN ENOC MARIN | C14: LAS MORENAS | D14: 0 | E14: 100 | F14: =(D14)*E14 -> 0
A15: 6 | B15: ELVIN ARIEL MARIN RIZO | C15: LAS MORENAS | D15: 0 | E15: 100 | F15: =(D15)*E15 -> 0
A16: 7 | B16: JOSE JAVIER GONZALEZ LOPEZ | C16: MONTECRISTO | D16: 0 | E16: 100 | F16: =(D16)*E16 -> 0
A17: 8 | B17: LESSIN NOEL PICADO | C17: MONTECRISTO | D17: 0 | E17: 100 | F17: =(D17)*E17 -> 0
A18: TOTAL | F18: =SUM(F6:F17) -> 0
A23: ____________________________________ | C23: __________________ | F23: _______________________________________________
A24: ELABORADO POR: | C24: REVISADO POR: | F24: AUTORIZADO POR:
A25: WILFREDO ARGEÑAL BLANDON | C25: IVAN OROZCO OSEJO | F25: LIC. OSMAN GREGORIO GUTIERREZ MORENO

Sheet ACOP EL CONSUELO
A1: OSMAN GREOGORIO GUTIERREZ MORENO | AH1: OSMAN GREOGORIO GUTIERREZ MORENO | AP1: OSMAN GREOGORIO GUTIERREZ MORENO | AX1: OSMAN GREOGORIO GUTIERREZ MORENO | BF1: OSMAN GREOGORIO GUTIERREZ MORENO | BN1: OSMAN GREOGORIO GUTIERREZ MORENO | BV1: OSMAN GREOGORIO GUTIERREZ MORENO | CD1: OSMAN GREOGORIO GUTIERREZ MORENO | CL1: OSMAN GREOGORIO GUTIERREZ MORENO | CT1: OSMAN GREOGORIO GUTIERREZ MORENO | DB1: OSMAN GREOGORIO GUTIERREZ MORENO | DJ1: OSMAN GREOGORIO GUTIERREZ MORENO | DR1: OSMAN GREOGORIO GUTIERREZ MORENO | DZ1: OSMAN GREOGORIO GUTIERREZ MORENO | EH1: OSMAN GREOGORIO GUTIERREZ MORENO | EP1: OSMAN GREOGORIO GUTIERREZ MORENO | EX1: OSMAN GREOGORIO GUTIERREZ MORENO | FF1: OSMAN GREOGORIO GUTIERREZ MORENO | FN1: OSMAN GREOGORIO GUTIERREZ MORENO | FV1: OSMAN GREOGORIO GUTIERREZ MORENO | GD1: OSMAN GREOGORIO GUTIERREZ MORENO | GL1: OSMAN GREOGORIO GUTIERREZ MORENO | GT1: OSMAN GREOGORIO GUTIERREZ MORENO | HB1: OSMAN GREOGORIO GUTIERREZ MORENO | HJ1: OSMAN GREOGORIO GUTIERREZ MORENO | HR1: OSMAN GREOGORIO GUTIERREZ MORENO | HZ1: OSMAN GREOGORIO GUTIERREZ MORENO | IH1: OSMAN GREOGORIO GUTIERREZ MORENO | IP1: OSMAN GREOGORIO GUTIERREZ MORENO | IX1: OSMAN GREOGORIO GUTIERREZ MORENO | JF1: OSMAN GREOGORIO GUTIERREZ MORENO | JN1: OSMAN GREOGORIO GUTIERREZ MORENO | JV1: OSMAN GREOGORIO GUTIERREZ MORENO | KD1: OSMAN GREOGORIO GUTIERREZ MORENO | KL1: OSMAN GREOGORIO GUTIERREZ MORENO | KT1: OSMAN GREOGORIO GUTIERREZ MORENO | LB1: OSMAN GREOGORIO GUTIERREZ MORENO | LJ1: OSMAN GREOGORIO GUTIERREZ MORENO | LR1: OSMAN GREOGORIO GUTIERREZ MORENO | LZ1: OSMAN GREOGORIO GUTIERREZ MORENO | MH1: OSMAN GREOGORIO GUTIERREZ MORENO | MP1: OSMAN GREOGORIO GUTIERREZ MORENO | MX1: OSMAN GREOGORIO GUTIERREZ MORENO | NF1: OSMAN GREOGORIO GUTIERREZ MORENO | NN1: OSMAN GREOGORIO GUTIERREZ MORENO | NV1: OSMAN GREOGORIO GUTIERREZ MORENO | OD1: OSMAN GREOGORIO GUTIERREZ MORENO | OL1: OSMAN GREOGORIO GUTIERREZ MORENO | OT1: OSMAN GREOGORIO GUTIERREZ MORENO | PB1: OSMAN GREOGORIO GUTIERREZ MORENO | PJ1: OSMAN GREOGORIO GUTIERREZ MORENO | PR1: OSMAN GREOGORIO GUTIERREZ MORENO | PZ1: OSMAN GREOGORIO GUTIERREZ MORENO | QH1: OSMAN GREOGORIO GUTIERREZ MORENO | QP1: OSMAN GREOGORIO GUTIERREZ MORENO | QX1: OSMAN GREOGORIO GUTIERREZ MORENO | RF1: OSMAN GREOGORIO GUTIERREZ MORENO | RN1: OSMAN GREOGORIO GUTIERREZ MORENO | RV1: OSMAN GREOGORIO GUTIERREZ MORENO | SD1: OSMAN GREOGORIO GUTIERREZ MORENO | SL1: OSMAN GREOGORIO GUTIERREZ MORENO | ST1: OSMAN GREOGORIO GUTIERREZ MORENO | TB1: OSMAN GREOGORIO GUTIERREZ MORENO | TJ1: OSMAN GREOGORIO GUTIERREZ MORENO | TR1: OSMAN GREOGORIO GUTIERREZ MORENO | TZ1: OSMAN GREOGORIO GUTIERREZ MORENO | UH1: OSMAN GREOGORIO GUTIERREZ MORENO | UP1: OSMAN GREOGORIO GUTIERREZ MORENO | UX1: OSMAN GREOGORIO GUTIERREZ MORENO | VF1: OSMAN GREOGORIO GUTIERREZ MORENO | VN1: OSMAN GREOGORIO GUTIERREZ MORENO | VV1: OSMAN GREOGORIO GUTIERREZ MORENO | WD1: OSMAN GREOGORIO GUTIERREZ MORENO | WL1: OSMAN GREOGORIO GUTIERREZ MORENO | WT1: OSMAN GREOGORIO GUTIERREZ MORENO | XB1: OSMAN GREOGORIO GUTIERREZ MORENO | XJ1: OSMAN GREOGORIO GUTIERREZ MORENO | XR1: OSMAN GREOGORIO GUTIERREZ MORENO | XZ1: OSMAN GREOGORIO GUTIERREZ MORENO | YH1: OSMAN GREOGORIO GUTIERREZ MORENO | YP1: OSMAN GREOGORIO GUTIERREZ MORENO | YX1: OSMAN GREOGORIO GUTIERREZ MORENO | ZF1: OSMAN GREOGORIO GUTIERREZ MORENO | ZN1: OSMAN GREOGORIO GUTIERREZ MORENO | ZV1: OSMAN GREOGORIO GUTIERREZ MORENO | AAD1: OSMAN GREOGORIO GUTIERREZ MORENO | AAL1: OSMAN GREOGORIO GUTIERREZ MORENO | AAT1: OSMAN GREOGORIO GUTIERREZ MORENO | ABB1: OSMAN GREOGORIO GUTIERREZ MORENO | ABJ1: OSMAN GREOGORIO GUTIERREZ MORENO | ABR1: OSMAN GREOGORIO GUTIERREZ MORENO | ABZ1: OSMAN GREOGORIO GUTIERREZ MORENO | ACH1: OSMAN GREOGORIO GUTIERREZ MORENO | ACP1: OSMAN GREOGORIO GUTIERREZ MORENO | ACX1: OSMAN GREOGORIO GUTIERREZ MORENO | ADF1: OSMAN GREOGORIO GUTIERREZ MORENO | ADN1: OSMAN GREOGORIO GUTIERREZ MORENO | ADV1: OSMAN GREOGORIO GUTIERREZ MORENO | AED1: OSMAN GREOGORIO GUTIERREZ MORENO | AEL1: OSMAN GREOGORIO GUTIERREZ MORENO | AET1: OSMAN GREOGORIO GUTIERREZ MORENO | AFB1: OSMAN GREOGORIO GUTIERREZ MORENO | AFJ1: OSMAN GREOGORIO GUTIERREZ MORENO | AFR1: OSMAN GREOGORIO GUTIERREZ MORENO | AFZ1: OSMAN GREOGORIO GUTIERREZ MORENO | AGH1: OSMAN GREOGORIO GUTIERREZ MORENO | AGP1: OSMAN GREOGORIO GUTIERREZ MORENO | AGX1: OSMAN GREOGORIO GUTIERREZ MORENO | AHF1: OSMAN GREOGORIO GUTIERREZ MORENO | AHN1: OSMAN GREOGORIO GUTIERREZ MORENO | AHV1: OSMAN GREOGORIO GUTIERREZ MORENO | AID1: OSMAN GREOGORIO GUTIERREZ MORENO | AIL1: OSMAN GREOGORIO GUTIERREZ MORENO | AIT1: OSMAN GREOGORIO GUTIERREZ MORENO | AJB1: OSMAN GREOGORIO GUTIERREZ MORENO | AJJ1: OSMAN GREOGORIO GUTIERREZ MORENO | AJR1: OSMAN GREOGORIO GUTIERREZ MORENO | AJZ1: OSMAN GREOGORIO GUTIERREZ MORENO | AKH1: OSMAN GREOGORIO GUTIERREZ MORENO | AKP1: OSMAN GREOGORIO GUTIERREZ MORENO | AKX1: OSMAN GREOGORIO GUTIERREZ MORENO | ALF1: OSMAN GREOGORIO GUTIERREZ MORENO | ALN1: OSMAN GREOGORIO GUTIERREZ MORENO | ALV1: OSMAN GREOGORIO GUTIERREZ MORENO | AMD1: OSMAN GREOGORIO GUTIERREZ MORENO | AML1: OSMAN GREOGORIO GUTIERREZ MORENO | AMT1: OSMAN GREOGORIO GUTIERREZ MORENO | ANB1: OSMAN GREOGORIO GUTIERREZ MORENO | ANJ1: OSMAN GREOGORIO GUTIERREZ MORENO | ANR1: OSMAN GREOGORIO GUTIERREZ MORENO | ANZ1: OSMAN GREOGORIO GUTIERREZ MORENO | AOH1: OSMAN GREOGORIO GUTIERREZ MORENO | AOP1: OSMAN GREOGORIO GUTIERREZ MORENO | AOX1: OSMAN GREOGORIO GUTIERREZ MORENO | APF1: OSMAN GREOGORIO GUTIERREZ MORENO | APN1: OSMAN GREOGORIO GUTIERREZ MORENO | APV1: OSMAN GREOGORIO GUTIERREZ MORENO | AQD1: OSMAN GREOGORIO GUTIERREZ MORENO | AQL1: OSMAN GREOGORIO GUTIERREZ MORENO | AQT1: OSMAN GREOGORIO GUTIERREZ MORENO | ARB1: OSMAN GREOGORIO GUTIERREZ MORENO | ARJ1: OSMAN GREOGORIO GUTIERREZ MORENO | ARR1: OSMAN GREOGORIO GUTIERREZ MORENO | ARZ1: OSMAN GREOGORIO GUTIERREZ MORENO | ASH1: OSMAN GREOGORIO GUTIERREZ MORENO | ASP1: OSMAN GREOGORIO GUTIERREZ MORENO | ASX1: OSMAN GREOGORIO GUTIERREZ MORENO | ATF1: OSMAN GREOGORIO GUTIERREZ MORENO | ATN1: OSMAN GREOGORIO GUTIERREZ MORENO | ATV1: OSMAN GREOGORIO GUTIERREZ MORENO | AUD1: OSMAN GREOGORIO GUTIERREZ MORENO | AUL1: OSMAN GREOGORIO GUTIERREZ MORENO | AUT1: OSMAN GREOGORIO GUTIERREZ MORENO | AVB1: OSMAN GREOGORIO GUTIERREZ MORENO | AVJ1: OSMAN GREOGORIO GUTIERREZ MORENO | AVR1: OSMAN GREOGORIO GUTIERREZ MORENO | AVZ1: OSMAN GREOGORIO GUTIERREZ MORENO | AWH1: OSMAN GREOGORIO GUTIERREZ MORENO | AWP1: OSMAN GREOGORIO GUTIERREZ MORENO | AWX1: OSMAN GREOGORIO GUTIERREZ MORENO | AXF1: OSMAN GREOGORIO GUTIERREZ MORENO | AXN1: OSMAN GREOGORIO GUTIERREZ MORENO | AXV1: OSMAN GREOGORIO GUTIERREZ MORENO | AYD1: OSMAN GREOGORIO GUTIERREZ MORENO | AYL1: OSMAN GREOGORIO GUTIERREZ MORENO | AYT1: OSMAN GREOGORIO GUTIERREZ MORENO | AZB1: OSMAN GREOGORIO GUTIERREZ MORENO | AZJ1: OSMAN GREOGORIO GUTIERREZ MORENO | AZR1: OSMAN GREOGORIO GUTIERREZ MORENO | AZZ1: OSMAN GREOGORIO GUTIERREZ MORENO | BAH1: OSMAN GREOGORIO GUTIERREZ MORENO | BAP1: OSMAN GREOGORIO GUTIERREZ MORENO | BAX1: OSMAN GREOGORIO GUTIERREZ MORENO | BBF1: OSMAN GREOGORIO GUTIERREZ MORENO | BBN1: OSMAN GREOGORIO GUTIERREZ MORENO | BBV1: OSMAN GREOGORIO GUTIERREZ MORENO | BCD1: OSMAN GREOGORIO GUTIERREZ MORENO | BCL1: OSMAN GREOGORIO GUTIERREZ MORENO | BCT1: OSMAN GREOGORIO GUTIERREZ MORENO | BDB1: OSMAN GREOGORIO GUTIERREZ MORENO | BDJ1: OSMAN GREOGORIO GUTIERREZ MORENO | BDR1: OSMAN GREOGORIO GUTIERREZ MORENO | BDZ1: OSMAN GREOGORIO GUTIERREZ MORENO | BEH1: OSMAN GREOGORIO GUTIERREZ MORENO | BEP1: OSMAN GREOGORIO GUTIERREZ MORENO | BEX1: OSMAN GREOGORIO GUTIERREZ MORENO | BFF1: OSMAN GREOGORIO GUTIERREZ MORENO | BFN1: OSMAN GREOGORIO GUTIERREZ MORENO | BFV1: OSMAN GREOGORIO GUTIERREZ MORENO | BGD1: OSMAN GREOGORIO GUTIERREZ MORENO | BGL1: OSMAN GREOGORIO GUTIERREZ MORENO | BGT1: OSMAN GREOGORIO GUTIERREZ MORENO | BHB1: OSMAN GREOGORIO GUTIERREZ MORENO | BHJ1: OSMAN GREOGORIO GUTIERREZ MORENO | BHR1: OSMAN GREOGORIO GUTIERREZ MORENO | BHZ1: OSMAN GREOGORIO GUTIERREZ MORENO | BIH1: OSMAN GREOGORIO GUTIERREZ MORENO | BIP1: OSMAN GREOGORIO GUTIERREZ MORENO | BIX1: OSMAN GREOGORIO GUTIERREZ MORENO | BJF1: OSMAN GREOGORIO GUTIERREZ MORENO | BJN1: OSMAN GREOGORIO GUTIERREZ MORENO | BJV1: OSMAN GREOGORIO GUTIERREZ MORENO | BKD1: OSMAN GREOGORIO GUTIERREZ MORENO | BKL1: OSMAN GREOGORIO GUTIERREZ MORENO | BKT1: OSMAN GREOGORIO GUTIERREZ MORENO | BLB1: OSMAN GREOGORIO GUTIERREZ MORENO | BLJ1: OSMAN GREOGORIO GUTIERREZ MORENO | BLR1: OSMAN GREOGORIO GUTIERREZ MORENO | BLZ1: OSMAN GREOGORIO GUTIERREZ MORENO | BMH1: OSMAN GREOGORIO GUTIERREZ MORENO | BMP1: OSMAN GREOGORIO GUTIERREZ MORENO | BMX1: OSMAN GREOGORIO GUTIERREZ MORENO | BNF1: OSMAN GREOGORIO GUTIERREZ MORENO | BNN1: OSMAN GREOGORIO GUTIERREZ MORENO | BNV1: OSMAN GREOGORIO GUTIERREZ MORENO | BOD1: OSMAN GREOGORIO GUTIERREZ MORENO | BOL1: OSMAN GREOGORIO GUTIERREZ MORENO | BOT1: OSMAN GREOGORIO GUTIERREZ MORENO | BPB1: OSMAN GREOGORIO GUTIERREZ MORENO | BPJ1: OSMAN GREOGORIO GUTIERREZ MORENO | BPR1: OSMAN GREOGORIO GUTIERREZ MORENO | BPZ1: OSMAN GREOGORIO GUTIERREZ MORENO | BQH1: OSMAN GREOGORIO GUTIERREZ MORENO | BQP1: OSMAN GREOGORIO GUTIERREZ MORENO | BQX1: OSMAN GREOGORIO GUTIERREZ MORENO | BRF1: OSMAN GREOGORIO GUTIERREZ MORENO | BRN1: OSMAN GREOGORIO GUTIERREZ MORENO | BRV1: OSMAN GREOGORIO GUTIERREZ MORENO | BSD1: OSMAN GREOGORIO GUTIERREZ MORENO | BSL1: OSMAN GREOGORIO GUTIERREZ MORENO | BST1: OSMAN GREOGORIO GUTIERREZ MORENO | BTB1: OSMAN GREOGORIO GUTIERREZ MORENO | BTJ1: OSMAN GREOGORIO GUTIERREZ MORENO | BTR1: OSMAN GREOGORIO GUTIERREZ MORENO | BTZ1: OSMAN GREOGORIO GUTIERREZ MORENO | BUH1: OSMAN GREOGORIO GUTIERREZ MORENO | BUP1: OSMAN GREOGORIO GUTIERREZ MORENO | BUX1: OSMAN GREOGORIO GUTIERREZ MORENO | BVF1: OSMAN GREOGORIO GUTIERREZ MORENO | BVN1: OSMAN GREOGORIO GUTIERREZ MORENO | BVV1: OSMAN GREOGORIO GUTIERREZ MORENO | BWD1: OSMAN GREOGORIO GUTIERREZ MORENO | BWL1: OSMAN GREOGORIO GUTIERREZ MORENO | BWT1: OSMAN GREOGORIO GUTIERREZ MORENO | BXB1: OSMAN GREOGORIO GUTIERREZ MORENO | BXJ1: OSMAN GREOGORIO GUTIERREZ MORENO | BXR1: OSMAN GREOGORIO GUTIERREZ MORENO | BXZ1: OSMAN GREOGORIO GUTIERREZ MORENO | BYH1: OSMAN GREOGORIO GUTIERREZ MORENO | BYP1: OSMAN GREOGORIO GUTIERREZ MORENO | BYX1: OSMAN GREOGORIO GUTIERREZ MORENO | BZF1: OSMAN GREOGORIO GUTIERREZ MORENO | BZN1: OSMAN GREOGORIO GUTIERREZ MORENO | BZV1: OSMAN GREOGORIO GUTIERREZ MORENO | CAD1: OSMAN GREOGORIO GUTIERREZ MORENO | CAL1: OSMAN GREOGORIO GUTIERREZ MORENO | CAT1: OSMAN GREOGORIO GUTIERREZ MORENO | CBB1: OSMAN GREOGORIO GUTIERREZ MORENO | CBJ1: OSMAN GREOGORIO GUTIERREZ MORENO | CBR1: OSMAN GREOGORIO GUTIERREZ MORENO | CBZ1: OSMAN GREOGORIO GUTIERREZ MORENO | CCH1: OSMAN GREOGORIO GUTIERREZ MORENO | CCP1: OSMAN GREOGORIO GUTIERREZ MORENO | CCX1: OSMAN GREOGORIO GUTIERREZ MORENO | CDF1: OSMAN GREOGORIO GUTIERREZ MORENO | CDN1: OSMAN GREOGORIO GUTIERREZ MORENO | CDV1: OSMAN GREOGORIO GUTIERREZ MORENO | CED1: OSMAN GREOGORIO GUTIERREZ MORENO | CEL1: OSMAN GREOGORIO GUTIERREZ MORENO | CET1: OSMAN GREOGORIO GUTIERREZ MORENO | CFB1: OSMAN GREOGORIO GUTIERREZ MORENO | CFJ1: OSMAN GREOGORIO GUTIERREZ MORENO | CFR1: OSMAN GREOGORIO GUTIERREZ MORENO | CFZ1: OSMAN GREOGORIO GUTIERREZ MORENO | CGH1: OSMAN GREOGORIO GUTIERREZ MORENO | CGP1: OSMAN GREOGORIO GUTIERREZ MORENO | CGX1: OSMAN GREOGORIO GUTIERREZ MORENO | CHF1: OSMAN GREOGORIO GUTIERREZ MORENO | CHN1: OSMAN GREOGORIO GUTIERREZ MORENO | CHV1: OSMAN GREOGORIO GUTIERREZ MORENO | CID1: OSMAN GREOGORIO GUTIERREZ MORENO | CIL1: OSMAN GREOGORIO GUTIERREZ MORENO | CIT1: OSMAN GREOGORIO GUTIERREZ MORENO | CJB1: OSMAN GREOGORIO GUTIERREZ MORENO | CJJ1: OSMAN GREOGORIO GUTIERREZ MORENO | CJR1: OSMAN GREOGORIO GUTIERREZ MORENO | CJZ1: OSMAN GREOGORIO GUTIERREZ MORENO | CKH1: OSMAN GREOGORIO GUTIERREZ MORENO | CKP1: OSMAN GREOGORIO GUTIERREZ MORENO | CKX1: OSMAN GREOGORIO GUTIERREZ MORENO | CLF1: OSMAN GREOGORIO GUTIERREZ MORENO | CLN1: OSMAN GREOGORIO GUTIERREZ MORENO | CLV1: OSMAN GREOGORIO GUTIERREZ MORENO | CMD1: OSMAN GREOGORIO GUTIERREZ MORENO | CML1: OSMAN GREOGORIO GUTIERREZ MORENO | CMT1: OSMAN GREOGORIO GUTIERREZ MORENO | CNB1: OSMAN GREOGORIO GUTIERREZ MORENO | CNJ1: OSMAN GREOGORIO GUTIERREZ MORENO | CNR1: OSMAN GREOGORIO GUTIERREZ MORENO | CNZ1: OSMAN GREOGORIO GUTIERREZ MORENO | COH1: OSMAN GREOGORIO GUTIERREZ MORENO | COP1: OSMAN GREOGORIO GUTIERREZ MORENO | COX1: OSMAN GREOGORIO GUTIERREZ MORENO | CPF1: OSMAN GREOGORIO GUTIERREZ MORENO | CPN1: OSMAN GREOGORIO GUTIERREZ MORENO | CPV1: OSMAN GREOGORIO GUTIERREZ MORENO | CQD1: OSMAN GREOGORIO GUTIERREZ MORENO | CQL1: OSMAN GREOGORIO GUTIERREZ MORENO | CQT1: OSMAN GREOGORIO GUTIERREZ MORENO | CRB1: OSMAN GREOGORIO GUTIERREZ MORENO | CRJ1: OSMAN GREOGORIO GUTIERREZ MORENO | CRR1: OSMAN GREOGORIO GUTIERREZ MORENO | CRZ1: OSMAN GREOGORIO GUTIERREZ MORENO | CSH1: OSMAN GREOGORIO GUTIERREZ MORENO | CSP1: OSMAN GREOGORIO GUTIERREZ MORENO | CSX1: OSMAN GREOGORIO GUTIERREZ MORENO | CTF1: OSMAN GREOGORIO GUTIERREZ MORENO | CTN1: OSMAN GREOGORIO GUTIERREZ MORENO | CTV1: OSMAN GREOGORIO GUTIERREZ MORENO | CUD1: OSMAN GREOGORIO GUTIERREZ MORENO | CUL1: OSMAN GREOGORIO GUTIERREZ MORENO | CUT1: OSMAN GREOGORIO GUTIERREZ MORENO | CVB1: OSMAN GREOGORIO GUTIERREZ MORENO | CVJ1: OSMAN GREOGORIO GUTIERREZ MORENO | CVR1: OSMAN GREOGORIO GUTIERREZ MORENO | CVZ1: OSMAN GREOGORIO GUTIERREZ MORENO | CWH1: OSMAN GREOGORIO GUTIERREZ MORENO | CWP1: OSMAN GREOGORIO GUTIERREZ MORENO | CWX1: OSMAN GREOGORIO GUTIERREZ MORENO | CXF1: OSMAN GREOGORIO GUTIERREZ MORENO | CXN1: OSMAN GREOGORIO GUTIERREZ MORENO | CXV1: OSMAN GREOGORIO GUTIERREZ MORENO | CYD1: OSMAN GREOGORIO GUTIERREZ MORENO | CYL1: OSMAN GREOGORIO GUTIERREZ MORENO | CYT1: OSMAN GREOGORIO GUTIERREZ MORENO | CZB1: OSMAN GREOGORIO GUTIERREZ MORENO | CZJ1: OSMAN GREOGORIO GUTIERREZ MORENO | CZR1: OSMAN GREOGORIO GUTIERREZ MORENO | CZZ1: OSMAN GREOGORIO GUTIERREZ MORENO | DAH1: OSMAN GREOGORIO GUTIERREZ MORENO | DAP1: OSMAN GREOGORIO GUTIERREZ MORENO | DAX1: OSMAN GREOGORIO GUTIERREZ MORENO | DBF1: OSMAN GREOGORIO GUTIERREZ MORENO | DBN1: OSMAN GREOGORIO GUTIERREZ MORENO | DBV1: OSMAN GREOGORIO GUTIERREZ MORENO | DCD1: OSMAN GREOGORIO GUTIERREZ MORENO | DCL1: OSMAN GREOGORIO GUTIERREZ MORENO | DCT1: OSMAN GREOGORIO GUTIERREZ MORENO | DDB1: OSMAN GREOGORIO GUTIERREZ MORENO | DDJ1: OSMAN GREOGORIO GUTIERREZ MORENO | DDR1: OSMAN GREOGORIO GUTIERREZ MORENO | DDZ1: OSMAN GREOGORIO GUTIERREZ MORENO | DEH1: OSMAN GREOGORIO GUTIERREZ MORENO | DEP1: OSMAN GREOGORIO GUTIERREZ MORENO | DEX1: OSMAN GREOGORIO GUTIERREZ MORENO | DFF1: OSMAN GREOGORIO GUTIERREZ MORENO | DFN1: OSMAN GREOGORIO GUTIERREZ MORENO | DFV1: OSMAN GREOGORIO GUTIERREZ MORENO | DGD1: OSMAN GREOGORIO GUTIERREZ MORENO | DGL1: OSMAN GREOGORIO GUTIERREZ MORENO | DGT1: OSMAN GREOGORIO GUTIERREZ MORENO | DHB1: OSMAN GREOGORIO GUTIERREZ MORENO | DHJ1: OSMAN GREOGORIO GUTIERREZ MORENO | DHR1: OSMAN GREOGORIO GUTIERREZ MORENO | DHZ1: OSMAN GREOGORIO GUTIERREZ MORENO | DIH1: OSMAN GREOGORIO GUTIERREZ MORENO | DIP1: OSMAN GREOGORIO GUTIERREZ MORENO | DIX1: OSMAN GREOGORIO GUTIERREZ MORENO | DJF1: OSMAN GREOGORIO GUTIERREZ MORENO | DJN1: OSMAN GREOGORIO GUTIERREZ MORENO | DJV1: OSMAN GREOGORIO GUTIERREZ MORENO | DKD1: OSMAN GREOGORIO GUTIERREZ MORENO | DKL1: OSMAN GREOGORIO GUTIERREZ MORENO | DKT1: OSMAN GREOGORIO GUTIERREZ MORENO | DLB1: OSMAN GREOGORIO GUTIERREZ MORENO | DLJ1: OSMAN GREOGORIO GUTIERREZ MORENO | DLR1: OSMAN GREOGORIO GUTIERREZ MORENO | DLZ1: OSMAN GREOGORIO GUTIERREZ MORENO | DMH1: OSMAN GREOGORIO GUTIERREZ MORENO | DMP1: OSMAN GREOGORIO GUTIERREZ MORENO | DMX1: OSMAN GREOGORIO GUTIERREZ MORENO | DNF1: OSMAN GREOGORIO GUTIERREZ MORENO | DNN1: OSMAN GREOGORIO GUTIERREZ MORENO | DNV1: OSMAN GREOGORIO GUTIERREZ MORENO | DOD1: OSMAN GREOGORIO GUTIERREZ MORENO | DOL1: OSMAN GREOGORIO GUTIERREZ MORENO | DOT1: OSMAN GREOGORIO GUTIERREZ MORENO | DPB1: OSMAN GREOGORIO GUTIERREZ MORENO | DPJ1: OSMAN GREOGORIO GUTIERREZ MORENO | DPR1: OSMAN GREOGORIO GUTIERREZ MORENO | DPZ1: OSMAN GREOGORIO GUTIERREZ MORENO | DQH1: OSMAN GREOGORIO GUTIERREZ MORENO | DQP1: OSMAN GREOGORIO GUTIERREZ MORENO | DQX1: OSMAN GREOGORIO GUTIERREZ MORENO | DRF1: OSMAN GREOGORIO GUTIERREZ MORENO | DRN1: OSMAN GREOGORIO GUTIERREZ MORENO | DRV1: OSMAN GREOGORIO GUTIERREZ MORENO | DSD1: OSMAN GREOGORIO GUTIERREZ MORENO | DSL1: OSMAN GREOGORIO GUTIERREZ MORENO | DST1: OSMAN GREOGORIO GUTIERREZ MORENO | DTB1: OSMAN GREOGORIO GUTIERREZ MORENO | DTJ1: OSMAN GREOGORIO GUTIERREZ MORENO | DTR1: OSMAN GREOGORIO GUTIERREZ MORENO | DTZ1: OSMAN GREOGORIO GUTIERREZ MORENO | DUH1: OSMAN GREOGORIO GUTIERREZ MORENO | DUP1: OSMAN GREOGORIO GUTIERREZ MORENO | DUX1: OSMAN GREOGORIO GUTIERREZ MORENO | DVF1: OSMAN GREOGORIO GUTIERREZ MORENO | DVN1: OSMAN GREOGORIO GUTIERREZ MORENO | DVV1: OSMAN GREOGORIO GUTIERREZ MORENO | DWD1: OSMAN GREOGORIO GUTIERREZ MORENO | DWL1: OSMAN GREOGORIO GUTIERREZ MORENO | DWT1: OSMAN GREOGORIO GUTIERREZ MORENO | DXB1: OSMAN GREOGORIO GUTIERREZ MORENO | DXJ1: OSMAN GREOGORIO GUTIERREZ MORENO | DXR1: OSMAN GREOGORIO GUTIERREZ MORENO | DXZ1: OSMAN GREOGORIO GUTIERREZ MORENO | DYH1: OSMAN GREOGORIO GUTIERREZ MORENO | DYP1: OSMAN GREOGORIO GUTIERREZ MORENO | DYX1: OSMAN GREOGORIO GUTIERREZ MORENO | DZF1: OSMAN GREOGORIO GUTIERREZ MORENO | DZN1: OSMAN GREOGORIO GUTIERREZ MORENO | DZV1: OSMAN GREOGORIO GUTIERREZ MORENO | EAD1: OSMAN GREOGORIO GUTIERREZ MORENO | EAL1: OSMAN GREOGORIO GUTIERREZ MORENO | EAT1: OSMAN GREOGORIO GUTIERREZ MORENO | EBB1: OSMAN GREOGORIO GUTIERREZ MORENO | EBJ1: OSMAN GREOGORIO GUTIERREZ MORENO | EBR1: OSMAN GREOGORIO GUTIERREZ MORENO | EBZ1: OSMAN GREOGORIO GUTIERREZ MORENO | ECH1: OSMAN GREOGORIO GUTIERREZ MORENO | ECP1: OSMAN GREOGORIO GUTIERREZ MORENO | ECX1: OSMAN GREOGORIO GUTIERREZ MORENO | EDF1: OSMAN GREOGORIO GUTIERREZ MORENO | EDN1: OSMAN GREOGORIO GUTIERREZ MORENO | EDV1: OSMAN GREOGORIO GUTIERREZ MORENO | EED1: OSMAN GREOGORIO GUTIERREZ MORENO | EEL1: OSMAN GREOGORIO GUTIERREZ MORENO | EET1: OSMAN GREOGORIO GUTIERREZ MORENO | EFB1: OSMAN GREOGORIO GUTIERREZ MORENO | EFJ1: OSMAN GREOGORIO GUTIERREZ MORENO | EFR1: OSMAN GREOGORIO GUTIERREZ MORENO | EFZ1: OSMAN GREOGORIO GUTIERREZ MORENO | EGH1: OSMAN GREOGORIO GUTIERREZ MORENO | EGP1: OSMAN GREOGORIO GUTIERREZ MORENO | EGX1: OSMAN GREOGORIO GUTIERREZ MORENO | EHF1: OSMAN GREOGORIO GUTIERREZ MORENO | EHN1: OSMAN GREOGORIO GUTIERREZ MORENO | EHV1: OSMAN GREOGORIO GUTIERREZ MORENO | EID1: OSMAN GREOGORIO GUTIERREZ MORENO | EIL1: OSMAN GREOGORIO GUTIERREZ MORENO | EIT1: OSMAN GREOGORIO GUTIERREZ MORENO | EJB1: OSMAN GREOGORIO GUTIERREZ MORENO | EJJ1: OSMAN GREOGORIO GUTIERREZ MORENO | EJR1: OSMAN GREOGORIO GUTIERREZ MORENO | EJZ1: OSMAN GREOGORIO GUTIERREZ MORENO | EKH1: OSMAN GREOGORIO GUTIERREZ MORENO | EKP1: OSMAN GREOGORIO GUTIERREZ MORENO | EKX1: OSMAN GREOGORIO GUTIERREZ MORENO | ELF1: OSMAN GREOGORIO GUTIERREZ MORENO | ELN1: OSMAN GREOGORIO GUTIERREZ MORENO | ELV1: OSMAN GREOGORIO GUTIERREZ MORENO | EMD1: OSMAN GREOGORIO GUTIERREZ MORENO | EML1: OSMAN GREOGORIO GUTIERREZ MORENO | EMT1: OSMAN GREOGORIO GUTIERREZ MORENO | ENB1: OSMAN GREOGORIO GUTIERREZ MORENO | ENJ1: OSMAN GREOGORIO GUTIERREZ MORENO | ENR1: OSMAN GREOGORIO GUTIERREZ MORENO | ENZ1: OSMAN GREOGORIO GUTIERREZ MORENO | EOH1: OSMAN GREOGORIO GUTIERREZ MORENO | EOP1: OSMAN GREOGORIO GUTIERREZ MORENO | EOX1: OSMAN GREOGORIO GUTIERREZ MORENO | EPF1: OSMAN GREOGORIO GUTIERREZ MORENO | EPN1: OSMAN GREOGORIO GUTIERREZ MORENO | EPV1: OSMAN GREOGORIO GUTIERREZ MORENO | EQD1: OSMAN GREOGORIO GUTIERREZ MORENO | EQL1: OSMAN GREOGORIO GUTIERREZ MORENO | EQT1: OSMAN GREOGORIO GUTIERREZ MORENO | ERB1: OSMAN GREOGORIO GUTIERREZ MORENO | ERJ1: OSMAN GREOGORIO GUTIERREZ MORENO | ERR1: OSMAN GREOGORIO GUTIERREZ MORENO | ERZ1: OSMAN GREOGORIO GUTIERREZ MORENO | ESH1: OSMAN GREOGORIO GUTIERREZ MORENO | ESP1: OSMAN GREOGORIO GUTIERREZ MORENO | ESX1: OSMAN GREOGORIO GUTIERREZ MORENO | ETF1: OSMAN GREOGORIO GUTIERREZ MORENO | ETN1: OSMAN GREOGORIO GUTIERREZ MORENO | ETV1: OSMAN GREOGORIO GUTIERREZ MORENO | EUD1: OSMAN GREOGORIO GUTIERREZ MORENO | EUL1: OSMAN GREOGORIO GUTIERREZ MORENO | EUT1: OSMAN GREOGORIO GUTIERREZ MORENO | EVB1: OSMAN GREOGORIO GUTIERREZ MORENO | EVJ1: OSMAN GREOGORIO GUTIERREZ MORENO | EVR1: OSMAN GREOGORIO GUTIERREZ MORENO | EVZ1: OSMAN GREOGORIO GUTIERREZ MORENO | EWH1: OSMAN GREOGORIO GUTIERREZ MORENO | EWP1: OSMAN GREOGORIO GUTIERREZ MORENO | EWX1: OSMAN GREOGORIO GUTIERREZ MORENO | EXF1: OSMAN GREOGORIO GUTIERREZ MORENO | EXN1: OSMAN GREOGORIO GUTIERREZ MORENO | EXV1: OSMAN GREOGORIO GUTIERREZ MORENO | EYD1: OSMAN GREOGORIO GUTIERREZ MORENO | EYL1: OSMAN GREOGORIO GUTIERREZ MORENO | EYT1: OSMAN GREOGORIO GUTIERREZ MORENO | EZB1: OSMAN GREOGORIO GUTIERREZ MORENO | EZJ1: OSMAN GREOGORIO GUTIERREZ MORENO | EZR1: OSMAN GREOGORIO GUTIERREZ MORENO | EZZ1: OSMAN GREOGORIO GUTIERREZ MORENO | FAH1: OSMAN GREOGORIO GUTIERREZ MORENO | FAP1: OSMAN GREOGORIO GUTIERREZ MORENO | FAX1: OSMAN GREOGORIO GUTIERREZ MORENO | FBF1: OSMAN GREOGORIO GUTIERREZ MORENO | FBN1: OSMAN GREOGORIO GUTIERREZ MORENO | FBV1: OSMAN GREOGORIO GUTIERREZ MORENO | FCD1: OSMAN GREOGORIO GUTIERREZ MORENO | FCL1: OSMAN GREOGORIO GUTIERREZ MORENO | FCT1: OSMAN GREOGORIO GUTIERREZ MORENO | FDB1: OSMAN GREOGORIO GUTIERREZ MORENO | FDJ1: OSMAN GREOGORIO GUTIERREZ MORENO | FDR1: OSMAN GREOGORIO GUTIERREZ MORENO | FDZ1: OSMAN GREOGORIO GUTIERREZ MORENO | FEH1: OSMAN GREOGORIO GUTIERREZ MORENO | FEP1: OSMAN GREOGORIO GUTIERREZ MORENO | FEX1: OSMAN GREOGORIO GUTIERREZ MORENO | FFF1: OSMAN GREOGORIO GUTIERREZ MORENO | FFN1: OSMAN GREOGORIO GUTIERREZ MORENO | FFV1: OSMAN GREOGORIO GUTIERREZ MORENO | FGD1: OSMAN GREOGORIO GUTIERREZ MORENO | FGL1: OSMAN GREOGORIO GUTIERREZ MORENO | FGT1: OSMAN GREOGORIO GUTIERREZ MORENO | FHB1: OSMAN GREOGORIO GUTIERREZ MORENO | FHJ1: OSMAN GREOGORIO GUTIERREZ MORENO | FHR1: OSMAN GREOGORIO GUTIERREZ MORENO | FHZ1: OSMAN GREOGORIO GUTIERREZ MORENO | FIH1: OSMAN GREOGORIO GUTIERREZ MORENO | FIP1: OSMAN GREOGORIO GUTIERREZ MORENO | FIX1: OSMAN GREOGORIO GUTIERREZ MORENO | FJF1: OSMAN GREOGORIO GUTIERREZ MORENO | FJN1: OSMAN GREOGORIO GUTIERREZ MORENO | FJV1: OSMAN GREOGORIO GUTIERREZ MORENO | FKD1: OSMAN GREOGORIO GUTIERREZ MORENO | FKL1: OSMAN GREOGORIO GUTIERREZ MORENO | FKT1: OSMAN GREOGORIO GUTIERREZ MORENO | FLB1: OSMAN GREOGORIO GUTIERREZ MORENO | FLJ1: OSMAN GREOGORIO GUTIERREZ MORENO | FLR1: OSMAN GREOGORIO GUTIERREZ MORENO | FLZ1: OSMAN GREOGORIO GUTIERREZ MORENO | FMH1: OSMAN GREOGORIO GUTIERREZ MORENO | FMP1: OSMAN GREOGORIO GUTIERREZ MORENO | FMX1: OSMAN GREOGORIO GUTIERREZ MORENO | FNF1: OSMAN GREOGORIO GUTIERREZ MORENO | FNN1: OSMAN GREOGORIO GUTIERREZ MORENO | FNV1: OSMAN GREOGORIO GUTIERREZ MORENO | FOD1: OSMAN GREOGORIO GUTIERREZ MORENO | FOL1: OSMAN GREOGORIO GUTIERREZ MORENO | FOT1: OSMAN GREOGORIO GUTIERREZ MORENO | FPB1: OSMAN GREOGORIO GUTIERREZ MORENO | FPJ1: OSMAN GREOGORIO GUTIERREZ MORENO | FPR1: OSMAN GREOGORIO GUTIERREZ MORENO | FPZ1: OSMAN GREOGORIO GUTIERREZ MORENO | FQH1: OSMAN GREOGORIO GUTIERREZ MORENO | FQP1: OSMAN GREOGORIO GUTIERREZ MORENO | FQX1: OSMAN GREOGORIO GUTIERREZ MORENO | FRF1: OSMAN GREOGORIO GUTIERREZ MORENO | FRN1: OSMAN GREOGORIO GUTIERREZ MORENO | FRV1: OSMAN GREOGORIO GUTIERREZ MORENO | FSD1: OSMAN GREOGORIO GUTIERREZ MORENO | FSL1: OSMAN GREOGORIO GUTIERREZ MORENO | FST1: OSMAN GREOGORIO GUTIERREZ MORENO | FTB1: OSMAN GREOGORIO GUTIERREZ MORENO | FTJ1: OSMAN GREOGORIO GUTIERREZ MORENO | FTR1: OSMAN GREOGORIO GUTIERREZ MORENO | FTZ1: OSMAN GREOGORIO GUTIERREZ MORENO | FUH1: OSMAN GREOGORIO GUTIERREZ MORENO | FUP1: OSMAN GREOGORIO GUTIERREZ MORENO | FUX1: OSMAN GREOGORIO GUTIERREZ MORENO | FVF1: OSMAN GREOGORIO GUTIERREZ MORENO | FVN1: OSMAN GREOGORIO GUTIERREZ MORENO | FVV1: OSMAN GREOGORIO GUTIERREZ MORENO | FWD1: OSMAN GREOGORIO GUTIERREZ MORENO | FWL1: OSMAN GREOGORIO GUTIERREZ MORENO | FWT1: OSMAN GREOGORIO GUTIERREZ MORENO | FXB1: OSMAN GREOGORIO GUTIERREZ MORENO | FXJ1: OSMAN GREOGORIO GUTIERREZ MORENO | FXR1: OSMAN GREOGORIO GUTIERREZ MORENO | FXZ1: OSMAN GREOGORIO GUTIERREZ MORENO | FYH1: OSMAN GREOGORIO GUTIERREZ MORENO | FYP1: OSMAN GREOGORIO GUTIERREZ MORENO | FYX1: OSMAN GREOGORIO GUTIERREZ MORENO | FZF1: OSMAN GREOGORIO GUTIERREZ MORENO | FZN1: OSMAN GREOGORIO GUTIERREZ MORENO | FZV1: OSMAN GREOGORIO GUTIERREZ MORENO | GAD1: OSMAN GREOGORIO GUTIERREZ MORENO | GAL1: OSMAN GREOGORIO GUTIERREZ MORENO | GAT1: OSMAN GREOGORIO GUTIERREZ MORENO | GBB1: OSMAN GREOGORIO GUTIERREZ MORENO | GBJ1: OSMAN GREOGORIO GUTIERREZ MORENO | GBR1: OSMAN GREOGORIO GUTIERREZ MORENO | GBZ1: OSMAN GREOGORIO GUTIERREZ MORENO | GCH1: OSMAN GREOGORIO GUTIERREZ MORENO | GCP1: OSMAN GREOGORIO GUTIERREZ MORENO | GCX1: OSMAN GREOGORIO GUTIERREZ MORENO | GDF1: OSMAN GREOGORIO GUTIERREZ MORENO | GDN1: OSMAN GREOGORIO GUTIERREZ MORENO | GDV1: OSMAN GREOGORIO GUTIERREZ MORENO | GED1: OSMAN GREOGORIO GUTIERREZ MORENO | GEL1: OSMAN GREOGORIO GUTIERREZ MORENO | GET1: OSMAN GREOGORIO GUTIERREZ MORENO | GFB1: OSMAN GREOGORIO GUTIERREZ MORENO | GFJ1: OSMAN GREOGORIO GUTIERREZ MORENO | GFR1: OSMAN GREOGORIO GUTIERREZ MORENO | GFZ1: OSMAN GREOGORIO GUTIERREZ MORENO | GGH1: OSMAN GREOGORIO GUTIERREZ MORENO | GGP1: OSMAN GREOGORIO GUTIERREZ MORENO | GGX1: OSMAN GREOGORIO GUTIERREZ MORENO | GHF1: OSMAN GREOGORIO GUTIERREZ MORENO | GHN1: OSMAN GREOGORIO GUTIERREZ MORENO | GHV1: OSMAN GREOGORIO GUTIERREZ MORENO | GID1: OSMAN GREOGORIO GUTIERREZ MORENO | GIL1: OSMAN GREOGORIO GUTIERREZ MORENO | GIT1: OSMAN GREOGORIO GUTIERREZ MORENO | GJB1: OSMAN GREOGORIO GUTIERREZ MORENO | GJJ1: OSMAN GREOGORIO GUTIERREZ MORENO | GJR1: OSMAN GREOGORIO GUTIERREZ MORENO | GJZ1: OSMAN GREOGORIO GUTIERREZ MORENO | GKH1: OSMAN GREOGORIO GUTIERREZ MORENO | GKP1: OSMAN GREOGORIO GUTIERREZ MORENO | GKX1: OSMAN GREOGORIO GUTIERREZ MORENO | GLF1: OSMAN GREOGORIO GUTIERREZ MORENO | GLN1: OSMAN GREOGORIO GUTIERREZ MORENO | GLV1: OSMAN GREOGORIO GUTIERREZ MORENO | GMD1: OSMAN GREOGORIO GUTIERREZ MORENO | GML1: OSMAN GREOGORIO GUTIERREZ MORENO | GMT1: OSMAN GREOGORIO GUTIERREZ MORENO | GNB1: OSMAN GREOGORIO GUTIERREZ MORENO | GNJ1: OSMAN GREOGORIO GUTIERREZ MORENO | GNR1: OSMAN GREOGORIO GUTIERREZ MORENO | GNZ1: OSMAN GREOGORIO GUTIERREZ MORENO | GOH1: OSMAN GREOGORIO GUTIERREZ MORENO | GOP1: OSMAN GREOGORIO GUTIERREZ MORENO | GOX1: OSMAN GREOGORIO GUTIERREZ MORENO | GPF1: OSMAN GREOGORIO GUTIERREZ MORENO | GPN1: OSMAN GREOGORIO GUTIERREZ MORENO | GPV1: OSMAN GREOGORIO GUTIERREZ MORENO | GQD1: OSMAN GREOGORIO GUTIERREZ MORENO | GQL1: OSMAN GREOGORIO GUTIERREZ MORENO | GQT1: OSMAN GREOGORIO GUTIERREZ MORENO | GRB1: OSMAN GREOGORIO GUTIERREZ MORENO | GRJ1: OSMAN GREOGORIO GUTIERREZ MORENO | GRR1: OSMAN GREOGORIO GUTIERREZ MORENO | GRZ1: OSMAN GREOGORIO GUTIERREZ MORENO | GSH1: OSMAN GREOGORIO GUTIERREZ MORENO | GSP1: OSMAN GREOGORIO GUTIERREZ MORENO | GSX1: OSMAN GREOGORIO GUTIERREZ MORENO | GTF1: OSMAN GREOGORIO GUTIERREZ MORENO | GTN1: OSMAN GREOGORIO GUTIERREZ MORENO | GTV1: OSMAN GREOGORIO GUTIERREZ MORENO | GUD1: OSMAN GREOGORIO GUTIERREZ MORENO | GUL1: OSMAN GREOGORIO GUTIERREZ MORENO | GUT1: OSMAN GREOGORIO GUTIERREZ MORENO | GVB1: OSMAN GREOGORIO GUTIERREZ MORENO | GVJ1: OSMAN GREOGORIO GUTIERREZ MORENO | GVR1: OSMAN GREOGORIO GUTIERREZ MORENO | GVZ1: OSMAN GREOGORIO GUTIERREZ MORENO | GWH1: OSMAN GREOGORIO GUTIERREZ MORENO | GWP1: OSMAN GREOGORIO GUTIERREZ MORENO | GWX1: OSMAN GREOGORIO GUTIERREZ MORENO | GXF1: OSMAN GREOGORIO GUTIERREZ MORENO | GXN1: OSMAN GREOGORIO GUTIERREZ MORENO | GXV1: OSMAN GREOGORIO GUTIERREZ MORENO | GYD1: OSMAN GREOGORIO GUTIERREZ MORENO | GYL1: OSMAN GREOGORIO GUTIERREZ MORENO | GYT1: OSMAN GREOGORIO GUTIERREZ MORENO | GZB1: OSMAN GREOGORIO GUTIERREZ MORENO | GZJ1: OSMAN GREOGORIO GUTIERREZ MORENO | GZR1: OSMAN GREOGORIO GUTIERREZ MORENO | GZZ1: OSMAN GREOGORIO GUTIERREZ MORENO | HAH1: OSMAN GREOGORIO GUTIERREZ MORENO | HAP1: OSMAN GREOGORIO GUTIERREZ MORENO | HAX1: OSMAN GREOGORIO GUTIERREZ MORENO | HBF1: OSMAN GREOGORIO GUTIERREZ MORENO | HBN1: OSMAN GREOGORIO GUTIERREZ MORENO | HBV1: OSMAN GREOGORIO GUTIERREZ MORENO | HCD1: OSMAN GREOGORIO GUTIERREZ MORENO | HCL1: OSMAN GREOGORIO GUTIERREZ MORENO | HCT1: OSMAN GREOGORIO GUTIERREZ MORENO | HDB1: OSMAN GREOGORIO GUTIERREZ MORENO | HDJ1: OSMAN GREOGORIO GUTIERREZ MORENO | HDR1: OSMAN GREOGORIO GUTIERREZ MORENO | HDZ1: OSMAN GREOGORIO GUTIERREZ MORENO | HEH1: OSMAN GREOGORIO GUTIERREZ MORENO | HEP1: OSMAN GREOGORIO GUTIERREZ MORENO | HEX1: OSMAN GREOGORIO GUTIERREZ MORENO | HFF1: OSMAN GREOGORIO GUTIERREZ MORENO | HFN1: OSMAN GREOGORIO GUTIERREZ MORENO | HFV1: OSMAN GREOGORIO GUTIERREZ MORENO | HGD1: OSMAN GREOGORIO GUTIERREZ MORENO | HGL1: OSMAN GREOGORIO GUTIERREZ MORENO | HGT1: OSMAN GREOGORIO GUTIERREZ MORENO | HHB1: OSMAN GREOGORIO GUTIERREZ MORENO | HHJ1: OSMAN GREOGORIO GUTIERREZ MORENO | HHR1: OSMAN GREOGORIO GUTIERREZ MORENO | HHZ1: OSMAN GREOGORIO GUTIERREZ MORENO | HIH1: OSMAN GREOGORIO GUTIERREZ MORENO | HIP1: OSMAN GREOGORIO GUTIERREZ MORENO | HIX1: OSMAN GREOGORIO GUTIERREZ MORENO | HJF1: OSMAN GREOGORIO GUTIERREZ MORENO | HJN1: OSMAN GREOGORIO GUTIERREZ MORENO | HJV1: OSMAN GREOGORIO GUTIERREZ MORENO | HKD1: OSMAN GREOGORIO GUTIERREZ MORENO | HKL1: OSMAN GREOGORIO GUTIERREZ MORENO | HKT1: OSMAN GREOGORIO GUTIERREZ MORENO | HLB1: OSMAN GREOGORIO GUTIERREZ MORENO | HLJ1: OSMAN GREOGORIO GUTIERREZ MORENO | HLR1: OSMAN GREOGORIO GUTIERREZ MORENO | HLZ1: OSMAN GREOGORIO GUTIERREZ MORENO | HMH1: OSMAN GREOGORIO GUTIERREZ MORENO | HMP1: OSMAN GREOGORIO GUTIERREZ MORENO | HMX1: OSMAN GREOGORIO GUTIERREZ MORENO | HNF1: OSMAN GREOGORIO GUTIERREZ MORENO | HNN1: OSMAN GREOGORIO GUTIERREZ MORENO | HNV1: OSMAN GREOGORIO GUTIERREZ MORENO | HOD1: OSMAN GREOGORIO GUTIERREZ MORENO | HOL1: OSMAN GREOGORIO GUTIERREZ MORENO | HOT1: OSMAN GREOGORIO GUTIERREZ MORENO | HPB1: OSMAN GREOGORIO GUTIERREZ MORENO | HPJ1: OSMAN GREOGORIO GUTIERREZ MORENO | HPR1: OSMAN GREOGORIO GUTIERREZ MORENO | HPZ1: OSMAN GREOGORIO GUTIERREZ MORENO | HQH1: OSMAN GREOGORIO GUTIERREZ MORENO | HQP1: OSMAN GREOGORIO GUTIERREZ MORENO | HQX1: OSMAN GREOGORIO GUTIERREZ MORENO | HRF1: OSMAN GREOGORIO GUTIERREZ MORENO | HRN1: OSMAN GREOGORIO GUTIERREZ MORENO | HRV1: OSMAN GREOGORIO GUTIERREZ MORENO | HSD1: OSMAN GREOGORIO GUTIERREZ MORENO | HSL1: OSMAN GREOGORIO GUTIERREZ MORENO | HST1: OSMAN GREOGORIO GUTIERREZ MORENO | HTB1: OSMAN GREOGORIO GUTIERREZ MORENO | HTJ1: OSMAN GREOGORIO GUTIERREZ MORENO | HTR1: OSMAN GREOGORIO GUTIERREZ MORENO | HTZ1: OSMAN GREOGORIO GUTIERREZ MORENO | HUH1: OSMAN GREOGORIO GUTIERREZ MORENO | HUP1: OSMAN GREOGORIO GUTIERREZ MORENO | HUX1: OSMAN GREOGORIO GUTIERREZ MORENO | HVF1: OSMAN GREOGORIO GUTIERREZ MORENO | HVN1: OSMAN GREOGORIO GUTIERREZ MORENO | HVV1: OSMAN GREOGORIO GUTIERREZ MORENO | HWD1: OSMAN GREOGORIO GUTIERREZ MORENO | HWL1: OSMAN GREOGORIO GUTIERREZ MORENO | HWT1: OSMAN GREOGORIO GUTIERREZ MORENO | HXB1: OSMAN GREOGORIO GUTIERREZ MORENO | HXJ1: OSMAN GREOGORIO GUTIERREZ MORENO | HXR1: OSMAN GREOGORIO GUTIERREZ MORENO | HXZ1: OSMAN GREOGORIO GUTIERREZ MORENO | HYH1: OSMAN GREOGORIO GUTIERREZ MORENO | HYP1: OSMAN GREOGORIO GUTIERREZ MORENO | HYX1: OSMAN GREOGORIO GUTIERREZ MORENO | HZF1: OSMAN GREOGORIO GUTIERREZ MORENO | HZN1: OSMAN GREOGORIO GUTIERREZ MORENO | HZV1: OSMAN GREOGORIO GUTIERREZ MORENO | IAD1: OSMAN GREOGORIO GUTIERREZ MORENO | IAL1: OSMAN GREOGORIO GUTIERREZ MORENO | IAT1: OSMAN GREOGORIO GUTIERREZ MORENO | IBB1: OSMAN GREOGORIO GUTIERREZ MORENO | IBJ1: OSMAN GREOGORIO GUTIERREZ MORENO | IBR1: OSMAN GREOGORIO GUTIERREZ MORENO | IBZ1: OSMAN GREOGORIO GUTIERREZ MORENO | ICH1: OSMAN GREOGORIO GUTIERREZ MORENO | ICP1: OSMAN GREOGORIO GUTIERREZ MORENO | ICX1: OSMAN GREOGORIO GUTIERREZ MORENO | IDF1: OSMAN GREOGORIO GUTIERREZ MORENO | IDN1: OSMAN GREOGORIO GUTIERREZ MORENO | IDV1: OSMAN GREOGORIO GUTIERREZ MORENO | IED1: OSMAN GREOGORIO GUTIERREZ MORENO | IEL1: OSMAN GREOGORIO GUTIERREZ MORENO | IET1: OSMAN GREOGORIO GUTIERREZ MORENO | IFB1: OSMAN GREOGORIO GUTIERREZ MORENO | IFJ1: OSMAN GREOGORIO GUTIERREZ MORENO | IFR1: OSMAN GREOGORIO GUTIERREZ MORENO | IFZ1: OSMAN GREOGORIO GUTIERREZ MORENO | IGH1: OSMAN GREOGORIO GUTIERREZ MORENO | IGP1: OSMAN GREOGORIO GUTIERREZ MORENO | IGX1: OSMAN GREOGORIO GUTIERREZ MORENO | IHF1: OSMAN GREOGORIO GUTIERREZ MORENO | IHN1: OSMAN GREOGORIO GUTIERREZ MORENO | IHV1: OSMAN GREOGORIO GUTIERREZ MORENO | IID1: OSMAN GREOGORIO GUTIERREZ MORENO | IIL1: OSMAN GREOGORIO GUTIERREZ MORENO | IIT1: OSMAN GREOGORIO GUTIERREZ MORENO | IJB1: OSMAN GREOGORIO GUTIERREZ MORENO | IJJ1: OSMAN GREOGORIO GUTIERREZ MORENO | IJR1: OSMAN GREOGORIO GUTIERREZ MORENO | IJZ1: OSMAN GREOGORIO GUTIERREZ MORENO | IKH1: OSMAN GREOGORIO GUTIERREZ MORENO | IKP1: OSMAN GREOGORIO GUTIERREZ MORENO | IKX1: OSMAN GREOGORIO GUTIERREZ MORENO | ILF1: OSMAN GREOGORIO GUTIERREZ MORENO | ILN1: OSMAN GREOGORIO GUTIERREZ MORENO | ILV1: OSMAN GREOGORIO GUTIERREZ MORENO | IMD1: OSMAN GREOGORIO GUTIERREZ MORENO | IML1: OSMAN GREOGORIO GUTIERREZ MORENO | IMT1: OSMAN GREOGORIO GUTIERREZ MORENO | INB1: OSMAN GREOGORIO GUTIERREZ MORENO | INJ1: OSMAN GREOGORIO GUTIERREZ MORENO | INR1: OSMAN GREOGORIO GUTIERREZ MORENO | INZ1: OSMAN GREOGORIO GUTIERREZ MORENO | IOH1: OSMAN GREOGORIO GUTIERREZ MORENO | IOP1: OSMAN GREOGORIO GUTIERREZ MORENO | IOX1: OSMAN GREOGORIO GUTIERREZ MORENO | IPF1: OSMAN GREOGORIO GUTIERREZ MORENO | IPN1: OSMAN GREOGORIO GUTIERREZ MORENO | IPV1: OSMAN GREOGORIO GUTIERREZ MORENO | IQD1: OSMAN GREOGORIO GUTIERREZ MORENO | IQL1: OSMAN GREOGORIO GUTIERREZ MORENO | IQT1: OSMAN GREOGORIO GUTIERREZ MORENO | IRB1: OSMAN GREOGORIO GUTIERREZ MORENO | IRJ1: OSMAN GREOGORIO GUTIERREZ MORENO | IRR1: OSMAN GREOGORIO GUTIERREZ MORENO | IRZ1: OSMAN GREOGORIO GUTIERREZ MORENO | ISH1: OSMAN GREOGORIO GUTIERREZ MORENO | ISP1: OSMAN GREOGORIO GUTIERREZ MORENO | ISX1: OSMAN GREOGORIO GUTIERREZ MORENO | ITF1: OSMAN GREOGORIO GUTIERREZ MORENO | ITN1: OSMAN GREOGORIO GUTIERREZ MORENO | ITV1: OSMAN GREOGORIO GUTIERREZ MORENO | IUD1: OSMAN GREOGORIO GUTIERREZ MORENO | IUL1: OSMAN GREOGORIO GUTIERREZ MORENO | IUT1: OSMAN GREOGORIO GUTIERREZ MORENO | IVB1: OSMAN GREOGORIO GUTIERREZ MORENO | IVJ1: OSMAN GREOGORIO GUTIERREZ MORENO | IVR1: OSMAN GREOGORIO GUTIERREZ MORENO | IVZ1: OSMAN GREOGORIO GUTIERREZ MORENO | IWH1: OSMAN GREOGORIO GUTIERREZ MORENO | IWP1: OSMAN GREOGORIO GUTIERREZ MORENO | IWX1: OSMAN GREOGORIO GUTIERREZ MORENO | IXF1: OSMAN GREOGORIO GUTIERREZ MORENO | IXN1: OSMAN GREOGORIO GUTIERREZ MORENO | IXV1: OSMAN GREOGORIO GUTIERREZ MORENO | IYD1: OSMAN GREOGORIO GUTIERREZ MORENO | IYL1: OSMAN GREOGORIO GUTIERREZ MORENO | IYT1: OSMAN GREOGORIO GUTIERREZ MORENO | IZB1: OSMAN GREOGORIO GUTIERREZ MORENO | IZJ1: OSMAN GREOGORIO GUTIERREZ MORENO | IZR1: OSMAN GREOGORIO GUTIERREZ MORENO | IZZ1: OSMAN GREOGORIO GUTIERREZ MORENO | JAH1: OSMAN GREOGORIO GUTIERREZ MORENO | JAP1: OSMAN GREOGORIO GUTIERREZ MORENO | JAX1: OSMAN GREOGORIO GUTIERREZ MORENO | JBF1: OSMAN GREOGORIO GUTIERREZ MORENO | JBN1: OSMAN GREOGORIO GUTIERREZ MORENO | JBV1: OSMAN GREOGORIO GUTIERREZ MORENO | JCD1: OSMAN GREOGORIO GUTIERREZ MORENO | JCL1: OSMAN GREOGORIO GUTIERREZ MORENO | JCT1: OSMAN GREOGORIO GUTIERREZ MORENO | JDB1: OSMAN GREOGORIO GUTIERREZ MORENO | JDJ1: OSMAN GREOGORIO GUTIERREZ MORENO | JDR1: OSMAN GREOGORIO GUTIERREZ MORENO | JDZ1: OSMAN GREOGORIO GUTIERREZ MORENO | JEH1: OSMAN GREOGORIO GUTIERREZ MORENO | JEP1: OSMAN GREOGORIO GUTIERREZ MORENO | JEX1: OSMAN GREOGORIO GUTIERREZ MORENO | JFF1: OSMAN GREOGORIO GUTIERREZ MORENO | JFN1: OSMAN GREOGORIO GUTIERREZ MORENO | JFV1: OSMAN GREOGORIO GUTIERREZ MORENO | JGD1: OSMAN GREOGORIO GUTIERREZ MORENO | JGL1: OSMAN GREOGORIO GUTIERREZ MORENO | JGT1: OSMAN GREOGORIO GUTIERREZ MORENO | JHB1: OSMAN GREOGORIO GUTIERREZ MORENO | JHJ1: OSMAN GREOGORIO GUTIERREZ MORENO | JHR1: OSMAN GREOGORIO GUTIERREZ MORENO | JHZ1: OSMAN GREOGORIO GUTIERREZ MORENO | JIH1: OSMAN GREOGORIO GUTIERREZ MORENO | JIP1: OSMAN GREOGORIO GUTIERREZ MORENO | JIX1: OSMAN GREOGORIO GUTIERREZ MORENO | JJF1: OSMAN GREOGORIO GUTIERREZ MORENO | JJN1: OSMAN GREOGORIO GUTIERREZ MORENO | JJV1: OSMAN GREOGORIO GUTIERREZ MORENO | JKD1: OSMAN GREOGORIO GUTIERREZ MORENO | JKL1: OSMAN GREOGORIO GUTIERREZ MORENO | JKT1: OSMAN GREOGORIO GUTIERREZ MORENO | JLB1: OSMAN GREOGORIO GUTIERREZ MORENO | JLJ1: OSMAN GREOGORIO GUTIERREZ MORENO | JLR1: OSMAN GREOGORIO GUTIERREZ MORENO | JLZ1: OSMAN GREOGORIO GUTIERREZ MORENO | JMH1: OSMAN GREOGORIO GUTIERREZ MORENO | JMP1: OSMAN GREOGORIO GUTIERREZ MORENO | JMX1: OSMAN GREOGORIO GUTIERREZ MORENO | JNF1: OSMAN GREOGORIO GUTIERREZ MORENO | JNN1: OSMAN GREOGORIO GUTIERREZ MORENO | JNV1: OSMAN GREOGORIO GUTIERREZ MORENO | JOD1: OSMAN GREOGORIO GUTIERREZ MORENO | JOL1: OSMAN GREOGORIO GUTIERREZ MORENO | JOT1: OSMAN GREOGORIO GUTIERREZ MORENO | JPB1: OSMAN GREOGORIO GUTIERREZ MORENO | JPJ1: OSMAN GREOGORIO GUTIERREZ MORENO | JPR1: OSMAN GREOGORIO GUTIERREZ MORENO | JPZ1: OSMAN GREOGORIO GUTIERREZ MORENO | JQH1: OSMAN GREOGORIO GUTIERREZ MORENO | JQP1: OSMAN GREOGORIO GUTIERREZ MORENO | JQX1: OSMAN GREOGORIO GUTIERREZ MORENO | JRF1: OSMAN GREOGORIO GUTIERREZ MORENO | JRN1: OSMAN GREOGORIO GUTIERREZ MORENO | JRV1: OSMAN GREOGORIO GUTIERREZ MORENO | JSD1: OSMAN GREOGORIO GUTIERREZ MORENO | JSL1: OSMAN GREOGORIO GUTIERREZ MORENO | JST1: OSMAN GREOGORIO GUTIERREZ MORENO | JTB1: OSMAN GREOGORIO GUTIERREZ MORENO | JTJ1: OSMAN GREOGORIO GUTIERREZ MORENO | JTR1: OSMAN GREOGORIO GUTIERREZ MORENO | JTZ1: OSMAN GREOGORIO GUTIERREZ MORENO | JUH1: OSMAN GREOGORIO GUTIERREZ MORENO | JUP1: OSMAN GREOGORIO GUTIERREZ MORENO | JUX1: OSMAN GREOGORIO GUTIERREZ MORENO | JVF1: OSMAN GREOGORIO GUTIERREZ MORENO | JVN1: OSMAN GREOGORIO GUTIERREZ MORENO | JVV1: OSMAN GREOGORIO GUTIERREZ MORENO | JWD1: OSMAN GREOGORIO GUTIERREZ MORENO | JWL1: OSMAN GREOGORIO GUTIERREZ MORENO | JWT1: OSMAN GREOGORIO GUTIERREZ MORENO | JXB1: OSMAN GREOGORIO GUTIERREZ MORENO | JXJ1: OSMAN GREOGORIO GUTIERREZ MORENO | JXR1: OSMAN GREOGORIO GUTIERREZ MORENO | JXZ1: OSMAN GREOGORIO GUTIERREZ MORENO | JYH1: OSMAN GREOGORIO GUTIERREZ MORENO | JYP1: OSMAN GREOGORIO GUTIERREZ MORENO | JYX1: OSMAN GREOGORIO GUTIERREZ MORENO | JZF1: OSMAN GREOGORIO GUTIERREZ MORENO | JZN1: OSMAN GREOGORIO GUTIERREZ MORENO | JZV1: OSMAN GREOGORIO GUTIERREZ MORENO | KAD1: OSMAN GREOGORIO GUTIERREZ MORENO | KAL1: OSMAN GREOGORIO GUTIERREZ MORENO | KAT1: OSMAN GREOGORIO GUTIERREZ MORENO | KBB1: OSMAN GREOGORIO GUTIERREZ MORENO | KBJ1: OSMAN GREOGORIO GUTIERREZ MORENO | KBR1: OSMAN GREOGORIO GUTIERREZ MORENO | KBZ1: OSMAN GREOGORIO GUTIERREZ MORENO | KCH1: OSMAN GREOGORIO GUTIERREZ MORENO | KCP1: OSMAN GREOGORIO GUTIERREZ MORENO | KCX1: OSMAN GREOGORIO GUTIERREZ MORENO | KDF1: OSMAN GREOGORIO GUTIERREZ MORENO | KDN1: OSMAN GREOGORIO GUTIERREZ MORENO | KDV1: OSMAN GREOGORIO GUTIERREZ MORENO | KED1: OSMAN GREOGORIO GUTIERREZ MORENO | KEL1: OSMAN GREOGORIO GUTIERREZ MORENO | KET1: OSMAN GREOGORIO GUTIERREZ MORENO | KFB1: OSMAN GREOGORIO GUTIERREZ MORENO | KFJ1: OSMAN GREOGORIO GUTIERREZ MORENO | KFR1: OSMAN GREOGORIO GUTIERREZ MORENO | KFZ1: OSMAN GREOGORIO GUTIERREZ MORENO | KGH1: OSMAN GREOGORIO GUTIERREZ MORENO | KGP1: OSMAN GREOGORIO GUTIERREZ MORENO | KGX1: OSMAN GREOGORIO GUTIERREZ MORENO | KHF1: OSMAN GREOGORIO GUTIERREZ MORENO | KHN1: OSMAN GREOGORIO GUTIERREZ MORENO | KHV1: OSMAN GREOGORIO GUTIERREZ MORENO | KID1: OSMAN GREOGORIO GUTIERREZ MORENO | KIL1: OSMAN GREOGORIO GUTIERREZ MORENO | KIT1: OSMAN GREOGORIO GUTIERREZ MORENO | KJB1: OSMAN GREOGORIO GUTIERREZ MORENO | KJJ1: OSMAN GREOGORIO GUTIERREZ MORENO | KJR1: OSMAN GREOGORIO GUTIERREZ MORENO | KJZ1: OSMAN GREOGORIO GUTIERREZ MORENO | KKH1: OSMAN GREOGORIO GUTIERREZ MORENO | KKP1: OSMAN GREOGORIO GUTIERREZ MORENO | KKX1: OSMAN GREOGORIO GUTIERREZ MORENO | KLF1: OSMAN GREOGORIO GUTIERREZ MORENO | KLN1: OSMAN GREOGORIO GUTIERREZ MORENO | KLV1: OSMAN GREOGORIO GUTIERREZ MORENO | KMD1: OSMAN GREOGORIO GUTIERREZ MORENO | KML1: OSMAN GREOGORIO GUTIERREZ MORENO | KMT1: OSMAN GREOGORIO GUTIERREZ MORENO | KNB1: OSMAN GREOGORIO GUTIERREZ MORENO | KNJ1: OSMAN GREOGORIO GUTIERREZ MORENO | KNR1: OSMAN GREOGORIO GUTIERREZ MORENO | KNZ1: OSMAN GREOGORIO GUTIERREZ MORENO | KOH1: OSMAN GREOGORIO GUTIERREZ MORENO | KOP1: OSMAN GREOGORIO GUTIERREZ MORENO | KOX1: OSMAN GREOGORIO GUTIERREZ MORENO | KPF1: OSMAN GREOGORIO GUTIERREZ MORENO | KPN1: OSMAN GREOGORIO GUTIERREZ MORENO | KPV1: OSMAN GREOGORIO GUTIERREZ MORENO | KQD1: OSMAN GREOGORIO GUTIERREZ MORENO | KQL1: OSMAN GREOGORIO GUTIERREZ MORENO | KQT1: OSMAN GREOGORIO GUTIERREZ MORENO | KRB1: OSMAN GREOGORIO GUTIERREZ MORENO | KRJ1: OSMAN GREOGORIO GUTIERREZ MORENO | KRR1: OSMAN GREOGORIO GUTIERREZ MORENO | KRZ1: OSMAN GREOGORIO GUTIERREZ MORENO | KSH1: OSMAN GREOGORIO GUTIERREZ MORENO | KSP1: OSMAN GREOGORIO GUTIERREZ MORENO | KSX1: OSMAN GREOGORIO GUTIERREZ MORENO | KTF1: OSMAN GREOGORIO GUTIERREZ MORENO | KTN1: OSMAN GREOGORIO GUTIERREZ MORENO | KTV1: OSMAN GREOGORIO GUTIERREZ MORENO | KUD1: OSMAN GREOGORIO GUTIERREZ MORENO | KUL1: OSMAN GREOGORIO GUTIERREZ MORENO | KUT1: OSMAN GREOGORIO GUTIERREZ MORENO | KVB1: OSMAN GREOGORIO GUTIERREZ MORENO | KVJ1: OSMAN GREOGORIO GUTIERREZ MORENO | KVR1: OSMAN GREOGORIO GUTIERREZ MORENO | KVZ1: OSMAN GREOGORIO GUTIERREZ MORENO | KWH1: OSMAN GREOGORIO GUTIERREZ MORENO | KWP1: OSMAN GREOGORIO GUTIERREZ MORENO | KWX1: OSMAN GREOGORIO GUTIERREZ MORENO | KXF1: OSMAN GREOGORIO GUTIERREZ MORENO | KXN1: OSMAN GREOGORIO GUTIERREZ MORENO | KXV1: OSMAN GREOGORIO GUTIERREZ MORENO | KYD1: OSMAN GREOGORIO GUTIERREZ MORENO | KYL1: OSMAN GREOGORIO GUTIERREZ MORENO | KYT1: OSMAN GREOGORIO GUTIERREZ MORENO | KZB1: OSMAN GREOGORIO GUTIERREZ MORENO | KZJ1: OSMAN GREOGORIO GUTIERREZ MORENO | KZR1: OSMAN GREOGORIO GUTIERREZ MORENO | KZZ1: OSMAN GREOGORIO GUTIERREZ MORENO | LAH1: OSMAN GREOGORIO GUTIERREZ MORENO | LAP1: OSMAN GREOGORIO GUTIERREZ MORENO | LAX1: OSMAN GREOGORIO GUTIERREZ MORENO | LBF1: OSMAN GREOGORIO GUTIERREZ MORENO | LBN1: OSMAN GREOGORIO GUTIERREZ MORENO | LBV1: OSMAN GREOGORIO GUTIERREZ MORENO | LCD1: OSMAN GREOGORIO GUTIERREZ MORENO | LCL1: OSMAN GREOGORIO GUTIERREZ MORENO | LCT1: OSMAN GREOGORIO GUTIERREZ MORENO | LDB1: OSMAN GREOGORIO GUTIERREZ MORENO | LDJ1: OSMAN GREOGORIO GUTIERREZ MORENO | LDR1: OSMAN GREOGORIO GUTIERREZ MORENO | LDZ1: OSMAN GREOGORIO GUTIERREZ MORENO | LEH1: OSMAN GREOGORIO GUTIERREZ MORENO | LEP1: OSMAN GREOGORIO GUTIERREZ MORENO | LEX1: OSMAN GREOGORIO GUTIERREZ MORENO | LFF1: OSMAN GREOGORIO GUTIERREZ MORENO | LFN1: OSMAN GREOGORIO GUTIERREZ MORENO | LFV1: OSMAN GREOGORIO GUTIERREZ MORENO | LGD1: OSMAN GREOGORIO GUTIERREZ MORENO | LGL1: OSMAN GREOGORIO GUTIERREZ MORENO | LGT1: OSMAN GREOGORIO GUTIERREZ MORENO | LHB1: OSMAN GREOGORIO GUTIERREZ MORENO | LHJ1: OSMAN GREOGORIO GUTIERREZ MORENO | LHR1: OSMAN GREOGORIO GUTIERREZ MORENO | LHZ1: OSMAN GREOGORIO GUTIERREZ MORENO | LIH1: OSMAN GREOGORIO GUTIERREZ MORENO | LIP1: OSMAN GREOGORIO GUTIERREZ MORENO | LIX1: OSMAN GREOGORIO GUTIERREZ MORENO | LJF1: OSMAN GREOGORIO GUTIERREZ MORENO | LJN1: OSMAN GREOGORIO GUTIERREZ MORENO | LJV1: OSMAN GREOGORIO GUTIERREZ MORENO | LKD1: OSMAN GREOGORIO GUTIERREZ MORENO | LKL1: OSMAN GREOGORIO GUTIERREZ MORENO | LKT1: OSMAN GREOGORIO GUTIERREZ MORENO | LLB1: OSMAN GREOGORIO GUTIERREZ MORENO | LLJ1: OSMAN GREOGORIO GUTIERREZ MORENO | LLR1: OSMAN GREOGORIO GUTIERREZ MORENO | LLZ1: OSMAN GREOGORIO GUTIERREZ MORENO | LMH1: OSMAN GREOGORIO GUTIERREZ MORENO | LMP1: OSMAN GREOGORIO GUTIERREZ MORENO | LMX1: OSMAN GREOGORIO GUTIERREZ MORENO | LNF1: OSMAN GREOGORIO GUTIERREZ MORENO | LNN1: OSMAN GREOGORIO GUTIERREZ MORENO | LNV1: OSMAN GREOGORIO GUTIERREZ MORENO | LOD1: OSMAN GREOGORIO GUTIERREZ MORENO | LOL1: OSMAN GREOGORIO GUTIERREZ MORENO | LOT1: OSMAN GREOGORIO GUTIERREZ MORENO | LPB1: OSMAN GREOGORIO GUTIERREZ MORENO | LPJ1: OSMAN GREOGORIO GUTIERREZ MORENO | LPR1: OSMAN GREOGORIO GUTIERREZ MORENO | LPZ1: OSMAN GREOGORIO GUTIERREZ MORENO | LQH1: OSMAN GREOGORIO GUTIERREZ MORENO | LQP1: OSMAN GREOGORIO GUTIERREZ MORENO | LQX1: OSMAN GREOGORIO GUTIERREZ MORENO | LRF1: OSMAN GREOGORIO GUTIERREZ MORENO | LRN1: OSMAN GREOGORIO GUTIERREZ MORENO | LRV1: OSMAN GREOGORIO GUTIERREZ MORENO | LSD1: OSMAN GREOGORIO GUTIERREZ MORENO | LSL1: OSMAN GREOGORIO GUTIERREZ MORENO | LST1: OSMAN GREOGORIO GUTIERREZ MORENO | LTB1: OSMAN GREOGORIO GUTIERREZ MORENO | LTJ1: OSMAN GREOGORIO GUTIERREZ MORENO | LTR1: OSMAN GREOGORIO GUTIERREZ MORENO | LTZ1: OSMAN GREOGORIO GUTIERREZ MORENO | LUH1: OSMAN GREOGORIO GUTIERREZ MORENO | LUP1: OSMAN GREOGORIO GUTIERREZ MORENO | LUX1: OSMAN GREOGORIO GUTIERREZ MORENO | LVF1: OSMAN GREOGORIO GUTIERREZ MORENO | LVN1: OSMAN GREOGORIO GUTIERREZ MORENO | LVV1: OSMAN GREOGORIO GUTIERREZ MORENO | LWD1: OSMAN GREOGORIO GUTIERREZ MORENO | LWL1: OSMAN GREOGORIO GUTIERREZ MORENO | LWT1: OSMAN GREOGORIO GUTIERREZ MORENO | LXB1: OSMAN GREOGORIO GUTIERREZ MORENO | LXJ1: OSMAN GREOGORIO GUTIERREZ MORENO | LXR1: OSMAN GREOGORIO GUTIERREZ MORENO | LXZ1: OSMAN GREOGORIO GUTIERREZ MORENO | LYH1: OSMAN GREOGORIO GUTIERREZ MORENO | LYP1: OSMAN GREOGORIO GUTIERREZ MORENO | LYX1: OSMAN GREOGORIO GUTIERREZ MORENO | LZF1: OSMAN GREOGORIO GUTIERREZ MORENO | LZN1: OSMAN GREOGORIO GUTIERREZ MORENO | LZV1: OSMAN GREOGORIO GUTIERREZ MORENO | MAD1: OSMAN GREOGORIO GUTIERREZ MORENO | MAL1: OSMAN GREOGORIO GUTIERREZ MORENO | MAT1: OSMAN GREOGORIO GUTIERREZ MORENO | MBB1: OSMAN GREOGORIO GUTIERREZ MORENO | MBJ1: OSMAN GREOGORIO GUTIERREZ MORENO | MBR1: OSMAN GREOGORIO GUTIERREZ MORENO | MBZ1: OSMAN GREOGORIO GUTIERREZ MORENO | MCH1: OSMAN GREOGORIO GUTIERREZ MORENO | MCP1: OSMAN GREOGORIO GUTIERREZ MORENO | MCX1: OSMAN GREOGORIO GUTIERREZ MORENO | MDF1: OSMAN GREOGORIO GUTIERREZ MORENO | MDN1: OSMAN GREOGORIO GUTIERREZ MORENO | MDV1: OSMAN GREOGORIO GUTIERREZ MORENO | MED1: OSMAN GREOGORIO GUTIERREZ MORENO | MEL1: OSMAN GREOGORIO GUTIERREZ MORENO | MET1: OSMAN GREOGORIO GUTIERREZ MORENO | MFB1: OSMAN GREOGORIO GUTIERREZ MORENO | MFJ1: OSMAN GREOGORIO GUTIERREZ MORENO | MFR1: OSMAN GREOGORIO GUTIERREZ MORENO | MFZ1: OSMAN GREOGORIO GUTIERREZ MORENO | MGH1: OSMAN GREOGORIO GUTIERREZ MORENO | MGP1: OSMAN GREOGORIO GUTIERREZ MORENO | MGX1: OSMAN GREOGORIO GUTIERREZ MORENO | MHF1: OSMAN GREOGORIO GUTIERREZ MORENO | MHN1: OSMAN GREOGORIO GUTIERREZ MORENO | MHV1: OSMAN GREOGORIO GUTIERREZ MORENO | MID1: OSMAN GREOGORIO GUTIERREZ MORENO | MIL1: OSMAN GREOGORIO GUTIERREZ MORENO | MIT1: OSMAN GREOGORIO GUTIERREZ MORENO | MJB1: OSMAN GREOGORIO GUTIERREZ MORENO | MJJ1: OSMAN GREOGORIO GUTIERREZ MORENO | MJR1: OSMAN GREOGORIO GUTIERREZ MORENO | MJZ1: OSMAN GREOGORIO GUTIERREZ MORENO | MKH1: OSMAN GREOGORIO GUTIERREZ MORENO | MKP1: OSMAN GREOGORIO GUTIERREZ MORENO | MKX1: OSMAN GREOGORIO GUTIERREZ MORENO | MLF1: OSMAN GREOGORIO GUTIERREZ MORENO | MLN1: OSMAN GREOGORIO GUTIERREZ MORENO | MLV1: OSMAN GREOGORIO GUTIERREZ MORENO | MMD1: OSMAN GREOGORIO GUTIERREZ MORENO | MML1: OSMAN GREOGORIO GUTIERREZ MORENO | MMT1: OSMAN GREOGORIO GUTIERREZ MORENO | MNB1: OSMAN GREOGORIO GUTIERREZ MORENO | MNJ1: OSMAN GREOGORIO GUTIERREZ MORENO | MNR1: OSMAN GREOGORIO GUTIERREZ MORENO | MNZ1: OSMAN GREOGORIO GUTIERREZ MORENO | MOH1: OSMAN GREOGORIO GUTIERREZ MORENO | MOP1: OSMAN GREOGORIO GUTIERREZ MORENO | MOX1: OSMAN GREOGORIO GUTIERREZ MORENO | MPF1: OSMAN GREOGORIO GUTIERREZ MORENO | MPN1: OSMAN GREOGORIO GUTIERREZ MORENO | MPV1: OSMAN GREOGORIO GUTIERREZ MORENO | MQD1: OSMAN GREOGORIO GUTIERREZ MORENO | MQL1: OSMAN GREOGORIO GUTIERREZ MORENO | MQT1: OSMAN GREOGORIO GUTIERREZ MORENO | MRB1: OSMAN GREOGORIO GUTIERREZ MORENO | MRJ1: OSMAN GREOGORIO GUTIERREZ MORENO | MRR1: OSMAN GREOGORIO GUTIERREZ MORENO | MRZ1: OSMAN GREOGORIO GUTIERREZ MORENO | MSH1: OSMAN GREOGORIO GUTIERREZ MORENO | MSP1: OSMAN GREOGORIO GUTIERREZ MORENO | MSX1: OSMAN GREOGORIO GUTIERREZ MORENO | MTF1: OSMAN GREOGORIO GUTIERREZ MORENO | MTN1: OSMAN GREOGORIO GUTIERREZ MORENO | MTV1: OSMAN GREOGORIO GUTIERREZ MORENO | MUD1: OSMAN GREOGORIO GUTIERREZ MORENO | MUL1: OSMAN GREOGORIO GUTIERREZ MORENO | MUT1: OSMAN GREOGORIO GUTIERREZ MORENO | MVB1: OSMAN GREOGORIO GUTIERREZ MORENO | MVJ1: OSMAN GREOGORIO GUTIERREZ MORENO | MVR1: OSMAN GREOGORIO GUTIERREZ MORENO | MVZ1: OSMAN GREOGORIO GUTIERREZ MORENO | MWH1: OSMAN GREOGORIO GUTIERREZ MORENO | MWP1: OSMAN GREOGORIO GUTIERREZ MORENO | MWX1: OSMAN GREOGORIO GUTIERREZ MORENO | MXF1: OSMAN GREOGORIO GUTIERREZ MORENO | MXN1: OSMAN GREOGORIO GUTIERREZ MORENO | MXV1: OSMAN GREOGORIO GUTIERREZ MORENO | MYD1: OSMAN GREOGORIO GUTIERREZ MORENO | MYL1: OSMAN GREOGORIO GUTIERREZ MORENO | MYT1: OSMAN GREOGORIO GUTIERREZ MORENO | MZB1: OSMAN GREOGORIO GUTIERREZ MORENO | MZJ1: OSMAN GREOGORIO GUTIERREZ MORENO | MZR1: OSMAN GREOGORIO GUTIERREZ MORENO | MZZ1: OSMAN GREOGORIO GUTIERREZ MORENO | NAH1: OSMAN GREOGORIO GUTIERREZ MORENO | NAP1: OSMAN GREOGORIO GUTIERREZ MORENO | NAX1: OSMAN GREOGORIO GUTIERREZ MORENO | NBF1: OSMAN GREOGORIO GUTIERREZ MORENO | NBN1: OSMAN GREOGORIO GUTIERREZ MORENO | NBV1: OSMAN GREOGORIO GUTIERREZ MORENO | NCD1: OSMAN GREOGORIO GUTIERREZ MORENO | NCL1: OSMAN GREOGORIO GUTIERREZ MORENO | NCT1: OSMAN GREOGORIO GUTIERREZ MORENO | NDB1: OSMAN GREOGORIO GUTIERREZ MORENO | NDJ1: OSMAN GREOGORIO GUTIERREZ MORENO | NDR1: OSMAN GREOGORIO GUTIERREZ MORENO | NDZ1: OSMAN GREOGORIO GUTIERREZ MORENO | NEH1: OSMAN GREOGORIO GUTIERREZ MORENO | NEP1: OSMAN GREOGORIO GUTIERREZ MORENO | NEX1: OSMAN GREOGORIO GUTIERREZ MORENO | NFF1: OSMAN GREOGORIO GUTIERREZ MORENO | NFN1: OSMAN GREOGORIO GUTIERREZ MORENO | NFV1: OSMAN GREOGORIO GUTIERREZ MORENO | NGD1: OSMAN GREOGORIO GUTIERREZ MORENO | NGL1: OSMAN GREOGORIO GUTIERREZ MORENO | NGT1: OSMAN GREOGORIO GUTIERREZ MORENO | NHB1: OSMAN GREOGORIO GUTIERREZ MORENO | NHJ1: OSMAN GREOGORIO GUTIERREZ MORENO | NHR1: OSMAN GREOGORIO GUTIERREZ MORENO | NHZ1: OSMAN GREOGORIO GUTIERREZ MORENO | NIH1: OSMAN GREOGORIO GUTIERREZ MORENO | NIP1: OSMAN GREOGORIO GUTIERREZ MORENO | NIX1: OSMAN GREOGORIO GUTIERREZ MORENO | NJF1: OSMAN GREOGORIO GUTIERREZ MORENO | NJN1: OSMAN GREOGORIO GUTIERREZ MORENO | NJV1: OSMAN GREOGORIO GUTIERREZ MORENO | NKD1: OSMAN GREOGORIO GUTIERREZ MORENO | NKL1: OSMAN GREOGORIO GUTIERREZ MORENO | NKT1: OSMAN GREOGORIO GUTIERREZ MORENO | NLB1: OSMAN GREOGORIO GUTIERREZ MORENO | NLJ1: OSMAN GREOGORIO GUTIERREZ MORENO | NLR1: OSMAN GREOGORIO GUTIERREZ MORENO | NLZ1: OSMAN GREOGORIO GUTIERREZ MORENO | NMH1: OSMAN GREOGORIO GUTIERREZ MORENO | NMP1: OSMAN GREOGORIO GUTIERREZ MORENO | NMX1: OSMAN GREOGORIO GUTIERREZ MORENO | NNF1: OSMAN GREOGORIO GUTIERREZ MORENO | NNN1: OSMAN GREOGORIO GUTIERREZ MORENO | NNV1: OSMAN GREOGORIO GUTIERREZ MORENO | NOD1: OSMAN GREOGORIO GUTIERREZ MORENO | NOL1: OSMAN GREOGORIO GUTIERREZ MORENO | NOT1: OSMAN GREOGORIO GUTIERREZ MORENO | NPB1: OSMAN GREOGORIO GUTIERREZ MORENO | NPJ1: OSMAN GREOGORIO GUTIERREZ MORENO | NPR1: OSMAN GREOGORIO GUTIERREZ MORENO | NPZ1: OSMAN GREOGORIO GUTIERREZ MORENO | NQH1: OSMAN GREOGORIO GUTIERREZ MORENO | NQP1: OSMAN GREOGORIO GUTIERREZ MORENO | NQX1: OSMAN GREOGORIO GUTIERREZ MORENO | NRF1: OSMAN GREOGORIO GUTIERREZ MORENO | NRN1: OSMAN GREOGORIO GUTIERREZ MORENO | NRV1: OSMAN GREOGORIO GUTIERREZ MORENO | NSD1: OSMAN GREOGORIO GUTIERREZ MORENO | NSL1: OSMAN GREOGORIO GUTIERREZ MORENO | NST1: OSMAN GREOGORIO GUTIERREZ MORENO | NTB1: OSMAN GREOGORIO GUTIERREZ MORENO | NTJ1: OSMAN GREOGORIO GUTIERREZ MORENO | NTR1: OSMAN GREOGORIO GUTIERREZ MORENO | NTZ1: OSMAN GREOGORIO GUTIERREZ MORENO | NUH1: OSMAN GREOGORIO GUTIERREZ MORENO | NUP1: OSMAN GREOGORIO GUTIERREZ MORENO | NUX1: OSMAN GREOGORIO GUTIERREZ MORENO | NVF1: OSMAN GREOGORIO GUTIERREZ MORENO | NVN1: OSMAN GREOGORIO GUTIERREZ MORENO | NVV1: OSMAN GREOGORIO GUTIERREZ MORENO | NWD1: OSMAN GREOGORIO GUTIERREZ MORENO | NWL1: OSMAN GREOGORIO GUTIERREZ MORENO | NWT1: OSMAN GREOGORIO GUTIERREZ MORENO | NXB1: OSMAN GREOGORIO GUTIERREZ MORENO | NXJ1: OSMAN GREOGORIO GUTIERREZ MORENO | NXR1: OSMAN GREOGORIO GUTIERREZ MORENO | NXZ1: OSMAN GREOGORIO GUTIERREZ MORENO | NYH1: OSMAN GREOGORIO GUTIERREZ MORENO | NYP1: OSMAN GREOGORIO GUTIERREZ MORENO | NYX1: OSMAN GREOGORIO GUTIERREZ MORENO | NZF1: OSMAN GREOGORIO GUTIERREZ MORENO | NZN1: OSMAN GREOGORIO GUTIERREZ MORENO | NZV1: OSMAN GREOGORIO GUTIERREZ MORENO | OAD1: OSMAN GREOGORIO GUTIERREZ MORENO | OAL1: OSMAN GREOGORIO GUTIERREZ MORENO | OAT1: OSMAN GREOGORIO GUTIERREZ MORENO | OBB1: OSMAN GREOGORIO GUTIERREZ MORENO | OBJ1: OSMAN GREOGORIO GUTIERREZ MORENO | OBR1: OSMAN GREOGORIO GUTIERREZ MORENO | OBZ1: OSMAN GREOGORIO GUTIERREZ MORENO | OCH1: OSMAN GREOGORIO GUTIERREZ MORENO | OCP1: OSMAN GREOGORIO GUTIERREZ MORENO | OCX1: OSMAN GREOGORIO GUTIERREZ MORENO | ODF1: OSMAN GREOGORIO GUTIERREZ MORENO | ODN1: OSMAN GREOGORIO GUTIERREZ MORENO | ODV1: OSMAN GREOGORIO GUTIERREZ MORENO | OED1: OSMAN GREOGORIO GUTIERREZ MORENO | OEL1: OSMAN GREOGORIO GUTIERREZ MORENO | OET1: OSMAN GREOGORIO GUTIERREZ MORENO | OFB1: OSMAN GREOGORIO GUTIERREZ MORENO | OFJ1: OSMAN GREOGORIO GUTIERREZ MORENO | OFR1: OSMAN GREOGORIO GUTIERREZ MORENO | OFZ1: OSMAN GREOGORIO GUTIERREZ MORENO | OGH1: OSMAN GREOGORIO GUTIERREZ MORENO | OGP1: OSMAN GREOGORIO GUTIERREZ MORENO | OGX1: OSMAN GREOGORIO GUTIERREZ MORENO | OHF1: OSMAN GREOGORIO GUTIERREZ MORENO | OHN1: OSMAN GREOGORIO GUTIERREZ MORENO | OHV1: OSMAN GREOGORIO GUTIERREZ MORENO | OID1: OSMAN GREOGORIO GUTIERREZ MORENO | OIL1: OSMAN GREOGORIO GUTIERREZ MORENO | OIT1: OSMAN GREOGORIO GUTIERREZ MORENO | OJB1: OSMAN GREOGORIO GUTIERREZ MORENO | OJJ1: OSMAN GREOGORIO GUTIERREZ MORENO | OJR1: OSMAN GREOGORIO GUTIERREZ MORENO | OJZ1: OSMAN GREOGORIO GUTIERREZ MORENO | OKH1: OSMAN GREOGORIO GUTIERREZ MORENO | OKP1: OSMAN GREOGORIO GUTIERREZ MORENO | OKX1: OSMAN GREOGORIO GUTIERREZ MORENO | OLF1: OSMAN GREOGORIO GUTIERREZ MORENO | OLN1: OSMAN GREOGORIO GUTIERREZ MORENO | OLV1: OSMAN GREOGORIO GUTIERREZ MORENO | OMD1: OSMAN GREOGORIO GUTIERREZ MORENO | OML1: OSMAN GREOGORIO GUTIERREZ MORENO | OMT1: OSMAN GREOGORIO GUTIERREZ MORENO | ONB1: OSMAN GREOGORIO GUTIERREZ MORENO | ONJ1: OSMAN GREOGORIO GUTIERREZ MORENO | ONR1: OSMAN GREOGORIO GUTIERREZ MORENO | ONZ1: OSMAN GREOGORIO GUTIERREZ MORENO | OOH1: OSMAN GREOGORIO GUTIERREZ MORENO | OOP1: OSMAN GREOGORIO GUTIERREZ MORENO | OOX1: OSMAN GREOGORIO GUTIERREZ MORENO | OPF1: OSMAN GREOGORIO GUTIERREZ MORENO | OPN1: OSMAN GREOGORIO GUTIERREZ MORENO | OPV1: OSMAN GREOGORIO GUTIERREZ MORENO | OQD1: OSMAN GREOGORIO GUTIERREZ MORENO | OQL1: OSMAN GREOGORIO GUTIERREZ MORENO | OQT1: OSMAN GREOGORIO GUTIERREZ MORENO | ORB1: OSMAN GREOGORIO GUTIERREZ MORENO | ORJ1: OSMAN GREOGORIO GUTIERREZ MORENO | ORR1: OSMAN GREOGORIO GUTIERREZ MORENO | ORZ1: OSMAN GREOGORIO GUTIERREZ MORENO | OSH1: OSMAN GREOGORIO GUTIERREZ MORENO | OSP1: OSMAN GREOGORIO GUTIERREZ MORENO | OSX1: OSMAN GREOGORIO GUTIERREZ MORENO | OTF1: OSMAN GREOGORIO GUTIERREZ MORENO | OTN1: OSMAN GREOGORIO GUTIERREZ MORENO | OTV1: OSMAN GREOGORIO GUTIERREZ MORENO | OUD1: OSMAN GREOGORIO GUTIERREZ MORENO | OUL1: OSMAN GREOGORIO GUTIERREZ MORENO | OUT1: OSMAN GREOGORIO GUTIERREZ MORENO | OVB1: OSMAN GREOGORIO GUTIERREZ MORENO | OVJ1: OSMAN GREOGORIO GUTIERREZ MORENO | OVR1: OSMAN GREOGORIO GUTIERREZ MORENO | OVZ1: OSMAN GREOGORIO GUTIERREZ MORENO | OWH1: OSMAN GREOGORIO GUTIERREZ MORENO | OWP1: OSMAN GREOGORIO GUTIERREZ MORENO | OWX1: OSMAN GREOGORIO GUTIERREZ MORENO | OXF1: OSMAN GREOGORIO GUTIERREZ MORENO | OXN1: OSMAN GREOGORIO GUTIERREZ MORENO | OXV1: OSMAN GREOGORIO GUTIERREZ MORENO | OYD1: OSMAN GREOGORIO GUTIERREZ MORENO | OYL1: OSMAN GREOGORIO GUTIERREZ MORENO | OYT1: OSMAN GREOGORIO GUTIERREZ MORENO | OZB1: OSMAN GREOGORIO GUTIERREZ MORENO | OZJ1: OSMAN GREOGORIO GUTIERREZ MORENO | OZR1: OSMAN GREOGORIO GUTIERREZ MORENO | OZZ1: OSMAN GREOGORIO GUTIERREZ MORENO | PAH1: OSMAN GREOGORIO GUTIERREZ MORENO | PAP1: OSMAN GREOGORIO GUTIERREZ MORENO | PAX1: OSMAN GREOGORIO GUTIERREZ MORENO | PBF1: OSMAN GREOGORIO GUTIERREZ MORENO | PBN1: OSMAN GREOGORIO GUTIERREZ MORENO | PBV1: OSMAN GREOGORIO GUTIERREZ MORENO | PCD1: OSMAN GREOGORIO GUTIERREZ MORENO | PCL1: OSMAN GREOGORIO GUTIERREZ MORENO | PCT1: OSMAN GREOGORIO GUTIERREZ MORENO | PDB1: OSMAN GREOGORIO GUTIERREZ MORENO | PDJ1: OSMAN GREOGORIO GUTIERREZ MORENO | PDR1: OSMAN GREOGORIO GUTIERREZ MORENO | PDZ1: OSMAN GREOGORIO GUTIERREZ MORENO | PEH1: OSMAN GREOGORIO GUTIERREZ MORENO | PEP1: OSMAN GREOGORIO GUTIERREZ MORENO | PEX1: OSMAN GREOGORIO GUTIERREZ MORENO | PFF1: OSMAN GREOGORIO GUTIERREZ MORENO | PFN1: OSMAN GREOGORIO GUTIERREZ MORENO | PFV1: OSMAN GREOGORIO GUTIERREZ MORENO | PGD1: OSMAN GREOGORIO GUTIERREZ MORENO | PGL1: OSMAN GREOGORIO GUTIERREZ MORENO | PGT1: OSMAN GREOGORIO GUTIERREZ MORENO | PHB1: OSMAN GREOGORIO GUTIERREZ MORENO | PHJ1: OSMAN GREOGORIO GUTIERREZ MORENO | PHR1: OSMAN GREOGORIO GUTIERREZ MORENO | PHZ1: OSMAN GREOGORIO GUTIERREZ MORENO | PIH1: OSMAN GREOGORIO GUTIERREZ MORENO | PIP1: OSMAN GREOGORIO GUTIERREZ MORENO | PIX1: OSMAN GREOGORIO GUTIERREZ MORENO | PJF1: OSMAN GREOGORIO GUTIERREZ MORENO | PJN1: OSMAN GREOGORIO GUTIERREZ MORENO | PJV1: OSMAN GREOGORIO GUTIERREZ MORENO | PKD1: OSMAN GREOGORIO GUTIERREZ MORENO | PKL1: OSMAN GREOGORIO GUTIERREZ MORENO | PKT1: OSMAN GREOGORIO GUTIERREZ MORENO | PLB1: OSMAN GREOGORIO GUTIERREZ MORENO | PLJ1: OSMAN GREOGORIO GUTIERREZ MORENO | PLR1: OSMAN GREOGORIO GUTIERREZ MORENO | PLZ1: OSMAN GREOGORIO GUTIERREZ MORENO | PMH1: OSMAN GREOGORIO GUTIERREZ MORENO | PMP1: OSMAN GREOGORIO GUTIERREZ MORENO | PMX1: OSMAN GREOGORIO GUTIERREZ MORENO | PNF1: OSMAN GREOGORIO GUTIERREZ MORENO | PNN1: OSMAN GREOGORIO GUTIERREZ MORENO | PNV1: OSMAN GREOGORIO GUTIERREZ MORENO | POD1: OSMAN GREOGORIO GUTIERREZ MORENO | POL1: OSMAN GREOGORIO GUTIERREZ MORENO | POT1: OSMAN GREOGORIO GUTIERREZ MORENO | PPB1: OSMAN GREOGORIO GUTIERREZ MORENO | PPJ1: OSMAN GREOGORIO GUTIERREZ MORENO | PPR1: OSMAN GREOGORIO GUTIERREZ MORENO | PPZ1: OSMAN GREOGORIO GUTIERREZ MORENO | PQH1: OSMAN GREOGORIO GUTIERREZ MORENO | PQP1: OSMAN GREOGORIO GUTIERREZ MORENO | PQX1: OSMAN GREOGORIO GUTIERREZ MORENO | PRF1: OSMAN GREOGORIO GUTIERREZ MORENO | PRN1: OSMAN GREOGORIO GUTIERREZ MORENO | PRV1: OSMAN GREOGORIO GUTIERREZ MORENO | PSD1: OSMAN GREOGORIO GUTIERREZ MORENO | PSL1: OSMAN GREOGORIO GUTIERREZ MORENO | PST1: OSMAN GREOGORIO GUTIERREZ MORENO | PTB1: OSMAN GREOGORIO GUTIERREZ MORENO | PTJ1: OSMAN GREOGORIO GUTIERREZ MORENO | PTR1: OSMAN GREOGORIO GUTIERREZ MORENO | PTZ1: OSMAN GREOGORIO GUTIERREZ MORENO | PUH1: OSMAN GREOGORIO GUTIERREZ MORENO | PUP1: OSMAN GREOGORIO GUTIERREZ MORENO | PUX1: OSMAN GREOGORIO GUTIERREZ MORENO | PVF1: OSMAN GREOGORIO GUTIERREZ MORENO | PVN1: OSMAN GREOGORIO GUTIERREZ MORENO | PVV1: OSMAN GREOGORIO GUTIERREZ MORENO | PWD1: OSMAN GREOGORIO GUTIERREZ MORENO | PWL1: OSMAN GREOGORIO GUTIERREZ MORENO | PWT1: OSMAN GREOGORIO GUTIERREZ MORENO | PXB1: OSMAN GREOGORIO GUTIERREZ MORENO | PXJ1: OSMAN GREOGORIO GUTIERREZ MORENO | PXR1: OSMAN GREOGORIO GUTIERREZ MORENO | PXZ1: OSMAN GREOGORIO GUTIERREZ MORENO | PYH1: OSMAN GREOGORIO GUTIERREZ MORENO | PYP1: OSMAN GREOGORIO GUTIERREZ MORENO | PYX1: OSMAN GREOGORIO GUTIERREZ MORENO | PZF1: OSMAN GREOGORIO GUTIERREZ MORENO | PZN1: OSMAN GREOGORIO GUTIERREZ MORENO | PZV1: OSMAN GREOGORIO GUTIERREZ MORENO | QAD1: OSMAN GREOGORIO GUTIERREZ MORENO | QAL1: OSMAN GREOGORIO GUTIERREZ MORENO | QAT1: OSMAN GREOGORIO GUTIERREZ MORENO | QBB1: OSMAN GREOGORIO GUTIERREZ MORENO | QBJ1: OSMAN GREOGORIO GUTIERREZ MORENO | QBR1: OSMAN GREOGORIO GUTIERREZ MORENO | QBZ1: OSMAN GREOGORIO GUTIERREZ MORENO | QCH1: OSMAN GREOGORIO GUTIERREZ MORENO | QCP1: OSMAN GREOGORIO GUTIERREZ MORENO | QCX1: OSMAN GREOGORIO GUTIERREZ MORENO | QDF1: OSMAN GREOGORIO GUTIERREZ MORENO | QDN1: OSMAN GREOGORIO GUTIERREZ MORENO | QDV1: OSMAN GREOGORIO GUTIERREZ MORENO | QED1: OSMAN GREOGORIO GUTIERREZ MORENO | QEL1: OSMAN GREOGORIO GUTIERREZ MORENO | QET1: OSMAN GREOGORIO GUTIERREZ MORENO | QFB1: OSMAN GREOGORIO GUTIERREZ MORENO | QFJ1: OSMAN GREOGORIO GUTIERREZ MORENO | QFR1: OSMAN GREOGORIO GUTIERREZ MORENO | QFZ1: OSMAN GREOGORIO GUTIERREZ MORENO | QGH1: OSMAN GREOGORIO GUTIERREZ MORENO | QGP1: OSMAN GREOGORIO GUTIERREZ MORENO | QGX1: OSMAN GREOGORIO GUTIERREZ MORENO | QHF1: OSMAN GREOGORIO GUTIERREZ MORENO | QHN1: OSMAN GREOGORIO GUTIERREZ MORENO | QHV1: OSMAN GREOGORIO GUTIERREZ MORENO | QID1: OSMAN GREOGORIO GUTIERREZ MORENO | QIL1: OSMAN GREOGORIO GUTIERREZ MORENO | QIT1: OSMAN GREOGORIO GUTIERREZ MORENO | QJB1: OSMAN GREOGORIO GUTIERREZ MORENO | QJJ1: OSMAN GREOGORIO GUTIERREZ MORENO | QJR1: OSMAN GREOGORIO GUTIERREZ MORENO | QJZ1: OSMAN GREOGORIO GUTIERREZ MORENO | QKH1: OSMAN GREOGORIO GUTIERREZ MORENO | QKP1: OSMAN GREOGORIO GUTIERREZ MORENO | QKX1: OSMAN GREOGORIO GUTIERREZ MORENO | QLF1: OSMAN GREOGORIO GUTIERREZ MORENO | QLN1: OSMAN GREOGORIO GUTIERREZ MORENO | QLV1: OSMAN GREOGORIO GUTIERREZ MORENO | QMD1: OSMAN GREOGORIO GUTIERREZ MORENO | QML1: OSMAN GREOGORIO GUTIERREZ MORENO | QMT1: OSMAN GREOGORIO GUTIERREZ MORENO | QNB1: OSMAN GREOGORIO GUTIERREZ MORENO | QNJ1: OSMAN GREOGORIO GUTIERREZ MORENO | QNR1: OSMAN GREOGORIO GUTIERREZ MORENO | QNZ1: OSMAN GREOGORIO GUTIERREZ MORENO | QOH1: OSMAN GREOGORIO GUTIERREZ MORENO | QOP1: OSMAN GREOGORIO GUTIERREZ MORENO | QOX1: OSMAN GREOGORIO GUTIERREZ MORENO | QPF1: OSMAN GREOGORIO GUTIERREZ MORENO | QPN1: OSMAN GREOGORIO GUTIERREZ MORENO | QPV1: OSMAN GREOGORIO GUTIERREZ MORENO | QQD1: OSMAN GREOGORIO GUTIERREZ MORENO | QQL1: OSMAN GREOGORIO GUTIERREZ MORENO | QQT1: OSMAN GREOGORIO GUTIERREZ MORENO | QRB1: OSMAN GREOGORIO GUTIERREZ MORENO | QRJ1: OSMAN GREOGORIO GUTIERREZ MORENO | QRR1: OSMAN GREOGORIO GUTIERREZ MORENO | QRZ1: OSMAN GREOGORIO GUTIERREZ MORENO | QSH1: OSMAN GREOGORIO GUTIERREZ MORENO | QSP1: OSMAN GREOGORIO GUTIERREZ MORENO | QSX1: OSMAN GREOGORIO GUTIERREZ MORENO | QTF1: OSMAN GREOGORIO GUTIERREZ MORENO | QTN1: OSMAN GREOGORIO GUTIERREZ MORENO | QTV1: OSMAN GREOGORIO GUTIERREZ MORENO | QUD1: OSMAN GREOGORIO GUTIERREZ MORENO | QUL1: OSMAN GREOGORIO GUTIERREZ MORENO | QUT1: OSMAN GREOGORIO GUTIERREZ MORENO | QVB1: OSMAN GREOGORIO GUTIERREZ MORENO | QVJ1: OSMAN GREOGORIO GUTIERREZ MORENO | QVR1: OSMAN GREOGORIO GUTIERREZ MORENO | QVZ1: OSMAN GREOGORIO GUTIERREZ MORENO | QWH1: OSMAN GREOGORIO GUTIERREZ MORENO | QWP1: OSMAN GREOGORIO GUTIERREZ MORENO | QWX1: OSMAN GREOGORIO GUTIERREZ MORENO | QXF1: OSMAN GREOGORIO GUTIERREZ MORENO | QXN1: OSMAN GREOGORIO GUTIERREZ MORENO | QXV1: OSMAN GREOGORIO GUTIERREZ MORENO | QYD1: OSMAN GREOGORIO GUTIERREZ MORENO | QYL1: OSMAN GREOGORIO GUTIERREZ MORENO | QYT1: OSMAN GREOGORIO GUTIERREZ MORENO | QZB1: OSMAN GREOGORIO GUTIERREZ MORENO | QZJ1: OSMAN GREOGORIO GUTIERREZ MORENO | QZR1: OSMAN GREOGORIO GUTIERREZ MORENO | QZZ1: OSMAN GREOGORIO GUTIERREZ MORENO | RAH1: OSMAN GREOGORIO GUTIERREZ MORENO | RAP1: OSMAN GREOGORIO GUTIERREZ MORENO | RAX1: OSMAN GREOGORIO GUTIERREZ MORENO | RBF1: OSMAN GREOGORIO GUTIERREZ MORENO | RBN1: OSMAN GREOGORIO GUTIERREZ MORENO | RBV1: OSMAN GREOGORIO GUTIERREZ MORENO | RCD1: OSMAN GREOGORIO GUTIERREZ MORENO | RCL1: OSMAN GREOGORIO GUTIERREZ MORENO | RCT1: OSMAN GREOGORIO GUTIERREZ MORENO | RDB1: OSMAN GREOGORIO GUTIERREZ MORENO | RDJ1: OSMAN GREOGORIO GUTIERREZ MORENO | RDR1: OSMAN GREOGORIO GUTIERREZ MORENO | RDZ1: OSMAN GREOGORIO GUTIERREZ MORENO | REH1: OSMAN GREOGORIO GUTIERREZ MORENO | REP1: OSMAN GREOGORIO GUTIERREZ MORENO | REX1: OSMAN GREOGORIO GUTIERREZ MORENO | RFF1: OSMAN GREOGORIO GUTIERREZ MORENO | RFN1: OSMAN GREOGORIO GUTIERREZ MORENO | RFV1: OSMAN GREOGORIO GUTIERREZ MORENO | RGD1: OSMAN GREOGORIO GUTIERREZ MORENO | RGL1: OSMAN GREOGORIO GUTIERREZ MORENO | RGT1: OSMAN GREOGORIO GUTIERREZ MORENO | RHB1: OSMAN GREOGORIO GUTIERREZ MORENO | RHJ1: OSMAN GREOGORIO GUTIERREZ MORENO | RHR1: OSMAN GREOGORIO GUTIERREZ MORENO | RHZ1: OSMAN GREOGORIO GUTIERREZ MORENO | RIH1: OSMAN GREOGORIO GUTIERREZ MORENO | RIP1: OSMAN GREOGORIO GUTIERREZ MORENO | RIX1: OSMAN GREOGORIO GUTIERREZ MORENO | RJF1: OSMAN GREOGORIO GUTIERREZ MORENO | RJN1: OSMAN GREOGORIO GUTIERREZ MORENO | RJV1: OSMAN GREOGORIO GUTIERREZ MORENO | RKD1: OSMAN GREOGORIO GUTIERREZ MORENO | RKL1: OSMAN GREOGORIO GUTIERREZ MORENO | RKT1: OSMAN GREOGORIO GUTIERREZ MORENO | RLB1: OSMAN GREOGORIO GUTIERREZ MORENO | RLJ1: OSMAN GREOGORIO GUTIERREZ MORENO | RLR1: OSMAN GREOGORIO GUTIERREZ MORENO | RLZ1: OSMAN GREOGORIO GUTIERREZ MORENO | RMH1: OSMAN GREOGORIO GUTIERREZ MORENO | RMP1: OSMAN GREOGORIO GUTIERREZ MORENO | RMX1: OSMAN GREOGORIO GUTIERREZ MORENO | RNF1: OSMAN GREOGORIO GUTIERREZ MORENO | RNN1: OSMAN GREOGORIO GUTIERREZ MORENO | RNV1: OSMAN GREOGORIO GUTIERREZ MORENO | ROD1: OSMAN GREOGORIO GUTIERREZ MORENO | ROL1: OSMAN GREOGORIO GUTIERREZ MORENO | ROT1: OSMAN GREOGORIO GUTIERREZ MORENO | RPB1: OSMAN GREOGORIO GUTIERREZ MORENO | RPJ1: OSMAN GREOGORIO GUTIERREZ MORENO | RPR1: OSMAN GREOGORIO GUTIERREZ MORENO | RPZ1: OSMAN GREOGORIO GUTIERREZ MORENO | RQH1: OSMAN GREOGORIO GUTIERREZ MORENO | RQP1: OSMAN GREOGORIO GUTIERREZ MORENO | RQX1: OSMAN GREOGORIO GUTIERREZ MORENO | RRF1: OSMAN GREOGORIO GUTIERREZ MORENO | RRN1: OSMAN GREOGORIO GUTIERREZ MORENO | RRV1: OSMAN GREOGORIO GUTIERREZ MORENO | RSD1: OSMAN GREOGORIO GUTIERREZ MORENO | RSL1: OSMAN GREOGORIO GUTIERREZ MORENO | RST1: OSMAN GREOGORIO GUTIERREZ MORENO | RTB1: OSMAN GREOGORIO GUTIERREZ MORENO | RTJ1: OSMAN GREOGORIO GUTIERREZ MORENO | RTR1: OSMAN GREOGORIO GUTIERREZ MORENO | RTZ1: OSMAN GREOGORIO GUTIERREZ MORENO | RUH1: OSMAN GREOGORIO GUTIERREZ MORENO | RUP1: OSMAN GREOGORIO GUTIERREZ MORENO | RUX1: OSMAN GREOGORIO GUTIERREZ MORENO | RVF1: OSMAN GREOGORIO GUTIERREZ MORENO | RVN1: OSMAN GREOGORIO GUTIERREZ MORENO | RVV1: OSMAN GREOGORIO GUTIERREZ MORENO | RWD1: OSMAN GREOGORIO GUTIERREZ MORENO | RWL1: OSMAN GREOGORIO GUTIERREZ MORENO | RWT1: OSMAN GREOGORIO GUTIERREZ MORENO | RXB1: OSMAN GREOGORIO GUTIERREZ MORENO | RXJ1: OSMAN GREOGORIO GUTIERREZ MORENO | RXR1: OSMAN GREOGORIO GUTIERREZ MORENO | RXZ1: OSMAN GREOGORIO GUTIERREZ MORENO | RYH1: OSMAN GREOGORIO GUTIERREZ MORENO | RYP1: OSMAN GREOGORIO GUTIERREZ MORENO | RYX1: OSMAN GREOGORIO GUTIERREZ MORENO | RZF1: OSMAN GREOGORIO GUTIERREZ MORENO | RZN1: OSMAN GREOGORIO GUTIERREZ MORENO | RZV1: OSMAN GREOGORIO GUTIERREZ MORENO | SAD1: OSMAN GREOGORIO GUTIERREZ MORENO | SAL1: OSMAN GREOGORIO GUTIERREZ MORENO | SAT1: OSMAN GREOGORIO GUTIERREZ MORENO | SBB1: OSMAN GREOGORIO GUTIERREZ MORENO | SBJ1: OSMAN GREOGORIO GUTIERREZ MORENO | SBR1: OSMAN GREOGORIO GUTIERREZ MORENO | SBZ1: OSMAN GREOGORIO GUTIERREZ MORENO | SCH1: OSMAN GREOGORIO GUTIERREZ MORENO | SCP1: OSMAN GREOGORIO GUTIERREZ MORENO | SCX1: OSMAN GREOGORIO GUTIERREZ MORENO | SDF1: OSMAN GREOGORIO GUTIERREZ MORENO | SDN1: OSMAN GREOGORIO GUTIERREZ MORENO | SDV1: OSMAN GREOGORIO GUTIERREZ MORENO | SED1: OSMAN GREOGORIO GUTIERREZ MORENO | SEL1: OSMAN GREOGORIO GUTIERREZ MORENO | SET1: OSMAN GREOGORIO GUTIERREZ MORENO | SFB1: OSMAN GREOGORIO GUTIERREZ MORENO | SFJ1: OSMAN GREOGORIO GUTIERREZ MORENO | SFR1: OSMAN GREOGORIO GUTIERREZ MORENO | SFZ1: OSMAN GREOGORIO GUTIERREZ MORENO | SGH1: OSMAN GREOGORIO GUTIERREZ MORENO | SGP1: OSMAN GREOGORIO GUTIERREZ MORENO | SGX1: OSMAN GREOGORIO GUTIERREZ MORENO | SHF1: OSMAN GREOGORIO GUTIERREZ MORENO | SHN1: OSMAN GREOGORIO GUTIERREZ MORENO | SHV1: OSMAN GREOGORIO GUTIERREZ MORENO | SID1: OSMAN GREOGORIO GUTIERREZ MORENO | SIL1: OSMAN GREOGORIO GUTIERREZ MORENO | SIT1: OSMAN GREOGORIO GUTIERREZ MORENO | SJB1: OSMAN GREOGORIO GUTIERREZ MORENO | SJJ1: OSMAN GREOGORIO GUTIERREZ MORENO | SJR1: OSMAN GREOGORIO GUTIERREZ MORENO | SJZ1: OSMAN GREOGORIO GUTIERREZ MORENO | SKH1: OSMAN GREOGORIO GUTIERREZ MORENO | SKP1: OSMAN GREOGORIO GUTIERREZ MORENO | SKX1: OSMAN GREOGORIO GUTIERREZ MORENO | SLF1: OSMAN GREOGORIO GUTIERREZ MORENO | SLN1: OSMAN GREOGORIO GUTIERREZ MORENO | SLV1: OSMAN GREOGORIO GUTIERREZ MORENO | SMD1: OSMAN GREOGORIO GUTIERREZ MORENO | SML1: OSMAN GREOGORIO GUTIERREZ MORENO | SMT1: OSMAN GREOGORIO GUTIERREZ MORENO | SNB1: OSMAN GREOGORIO GUTIERREZ MORENO | SNJ1: OSMAN GREOGORIO GUTIERREZ MORENO | SNR1: OSMAN GREOGORIO GUTIERREZ MORENO | SNZ1: OSMAN GREOGORIO GUTIERREZ MORENO | SOH1: OSMAN GREOGORIO GUTIERREZ MORENO | SOP1: OSMAN GREOGORIO GUTIERREZ MORENO | SOX1: OSMAN GREOGORIO GUTIERREZ MORENO | SPF1: OSMAN GREOGORIO GUTIERREZ MORENO | SPN1: OSMAN GREOGORIO GUTIERREZ MORENO | SPV1: OSMAN GREOGORIO GUTIERREZ MORENO | SQD1: OSMAN GREOGORIO GUTIERREZ MORENO | SQL1: OSMAN GREOGORIO GUTIERREZ MORENO | SQT1: OSMAN GREOGORIO GUTIERREZ MORENO | SRB1: OSMAN GREOGORIO GUTIERREZ MORENO | SRJ1: OSMAN GREOGORIO GUTIERREZ MORENO | SRR1: OSMAN GREOGORIO GUTIERREZ MORENO | SRZ1: OSMAN GREOGORIO GUTIERREZ MORENO | SSH1: OSMAN GREOGORIO GUTIERREZ MORENO | SSP1: OSMAN GREOGORIO GUTIERREZ MORENO | SSX1: OSMAN GREOGORIO GUTIERREZ MORENO | STF1: OSMAN GREOGORIO GUTIERREZ MORENO | STN1: OSMAN GREOGORIO GUTIERREZ MORENO | STV1: OSMAN GREOGORIO GUTIERREZ MORENO | SUD1: OSMAN GREOGORIO GUTIERREZ MORENO | SUL1: OSMAN GREOGORIO GUTIERREZ MORENO | SUT1: OSMAN GREOGORIO GUTIERREZ MORENO | SVB1: OSMAN GREOGORIO GUTIERREZ MORENO | SVJ1: OSMAN GREOGORIO GUTIERREZ MORENO | SVR1: OSMAN GREOGORIO GUTIERREZ MORENO | SVZ1: OSMAN GREOGORIO GUTIERREZ MORENO | SWH1: OSMAN GREOGORIO GUTIERREZ MORENO | SWP1: OSMAN GREOGORIO GUTIERREZ MORENO | SWX1: OSMAN GREOGORIO GUTIERREZ MORENO | SXF1: OSMAN GREOGORIO GUTIERREZ MORENO | SXN1: OSMAN GREOGORIO GUTIERREZ MORENO | SXV1: OSMAN GREOGORIO GUTIERREZ MORENO | SYD1: OSMAN GREOGORIO GUTIERREZ MORENO | SYL1: OSMAN GREOGORIO GUTIERREZ MORENO | SYT1: OSMAN GREOGORIO GUTIERREZ MORENO | SZB1: OSMAN GREOGORIO GUTIERREZ MORENO | SZJ1: OSMAN GREOGORIO GUTIERREZ MORENO | SZR1: OSMAN GREOGORIO GUTIERREZ MORENO | SZZ1: OSMAN GREOGORIO GUTIERREZ MORENO | TAH1: OSMAN GREOGORIO GUTIERREZ MORENO | TAP1: OSMAN GREOGORIO GUTIERREZ MORENO | TAX1: OSMAN GREOGORIO GUTIERREZ MORENO | TBF1: OSMAN GREOGORIO GUTIERREZ MORENO | TBN1: OSMAN GREOGORIO GUTIERREZ MORENO | TBV1: OSMAN GREOGORIO GUTIERREZ MORENO | TCD1: OSMAN GREOGORIO GUTIERREZ MORENO | TCL1: OSMAN GREOGORIO GUTIERREZ MORENO | TCT1: OSMAN GREOGORIO GUTIERREZ MORENO | TDB1: OSMAN GREOGORIO GUTIERREZ MORENO | TDJ1: OSMAN GREOGORIO GUTIERREZ MORENO | TDR1: OSMAN GREOGORIO GUTIERREZ MORENO | TDZ1: OSMAN GREOGORIO GUTIERREZ MORENO | TEH1: OSMAN GREOGORIO GUTIERREZ MORENO | TEP1: OSMAN GREOGORIO GUTIERREZ MORENO | TEX1: OSMAN GREOGORIO GUTIERREZ MORENO | TFF1: OSMAN GREOGORIO GUTIERREZ MORENO | TFN1: OSMAN GREOGORIO GUTIERREZ MORENO | TFV1: OSMAN GREOGORIO GUTIERREZ MORENO | TGD1: OSMAN GREOGORIO GUTIERREZ MORENO | TGL1: OSMAN GREOGORIO GUTIERREZ MORENO | TGT1: OSMAN GREOGORIO GUTIERREZ MORENO | THB1: OSMAN GREOGORIO GUTIERREZ MORENO | THJ1: OSMAN GREOGORIO GUTIERREZ MORENO | THR1: OSMAN GREOGORIO GUTIERREZ MORENO | THZ1: OSMAN GREOGORIO GUTIERREZ MORENO | TIH1: OSMAN GREOGORIO GUTIERREZ MORENO | TIP1: OSMAN GREOGORIO GUTIERREZ MORENO | TIX1: OSMAN GREOGORIO GUTIERREZ MORENO | TJF1: OSMAN GREOGORIO GUTIERREZ MORENO | TJN1: OSMAN GREOGORIO GUTIERREZ MORENO | TJV1: OSMAN GREOGORIO GUTIERREZ MORENO | TKD1: OSMAN GREOGORIO GUTIERREZ MORENO | TKL1: OSMAN GREOGORIO GUTIERREZ MORENO | TKT1: OSMAN GREOGORIO GUTIERREZ MORENO | TLB1: OSMAN GREOGORIO GUTIERREZ MORENO | TLJ1: OSMAN GREOGORIO GUTIERREZ MORENO | TLR1: OSMAN GREOGORIO GUTIERREZ MORENO | TLZ1: OSMAN GREOGORIO GUTIERREZ MORENO | TMH1: OSMAN GREOGORIO GUTIERREZ MORENO | TMP1: OSMAN GREOGORIO GUTIERREZ MORENO | TMX1: OSMAN GREOGORIO GUTIERREZ MORENO | TNF1: OSMAN GREOGORIO GUTIERREZ MORENO | TNN1: OSMAN GREOGORIO GUTIERREZ MORENO | TNV1: OSMAN GREOGORIO GUTIERREZ MORENO | TOD1: OSMAN GREOGORIO GUTIERREZ MORENO | TOL1: OSMAN GREOGORIO GUTIERREZ MORENO | TOT1: OSMAN GREOGORIO GUTIERREZ MORENO | TPB1: OSMAN GREOGORIO GUTIERREZ MORENO | TPJ1: OSMAN GREOGORIO GUTIERREZ MORENO | TPR1: OSMAN GREOGORIO GUTIERREZ MORENO | TPZ1: OSMAN GREOGORIO GUTIERREZ MORENO | TQH1: OSMAN GREOGORIO GUTIERREZ MORENO | TQP1: OSMAN GREOGORIO GUTIERREZ MORENO | TQX1: OSMAN GREOGORIO GUTIERREZ MORENO | TRF1: OSMAN GREOGORIO GUTIERREZ MORENO | TRN1: OSMAN GREOGORIO GUTIERREZ MORENO | TRV1: OSMAN GREOGORIO GUTIERREZ MORENO | TSD1: OSMAN GREOGORIO GUTIERREZ MORENO | TSL1: OSMAN GREOGORIO GUTIERREZ MORENO | TST1: OSMAN GREOGORIO GUTIERREZ MORENO | TTB1: OSMAN GREOGORIO GUTIERREZ MORENO | TTJ1: OSMAN GREOGORIO GUTIERREZ MORENO | TTR1: OSMAN GREOGORIO GUTIERREZ MORENO | TTZ1: OSMAN GREOGORIO GUTIERREZ MORENO | TUH1: OSMAN GREOGORIO GUTIERREZ MORENO | TUP1: OSMAN GREOGORIO GUTIERREZ MORENO | TUX1: OSMAN GREOGORIO GUTIERREZ MORENO | TVF1: OSMAN GREOGORIO GUTIERREZ MORENO | TVN1: OSMAN GREOGORIO GUTIERREZ MORENO | TVV1: OSMAN GREOGORIO GUTIERREZ MORENO | TWD1: OSMAN GREOGORIO GUTIERREZ MORENO | TWL1: OSMAN GREOGORIO GUTIERREZ MORENO | TWT1: OSMAN GREOGORIO GUTIERREZ MORENO | TXB1: OSMAN GREOGORIO GUTIERREZ MORENO | TXJ1: OSMAN GREOGORIO GUTIERREZ MORENO | TXR1: OSMAN GREOGORIO GUTIERREZ MORENO | TXZ1: OSMAN GREOGORIO GUTIERREZ MORENO | TYH1: OSMAN GREOGORIO GUTIERREZ MORENO | TYP1: OSMAN GREOGORIO GUTIERREZ MORENO | TYX1: OSMAN GREOGORIO GUTIERREZ MORENO | TZF1: OSMAN GREOGORIO GUTIERREZ MORENO | TZN1: OSMAN GREOGORIO GUTIERREZ MORENO | TZV1: OSMAN GREOGORIO GUTIERREZ MORENO | UAD1: OSMAN GREOGORIO GUTIERREZ MORENO | UAL1: OSMAN GREOGORIO GUTIERREZ MORENO | UAT1: OSMAN GREOGORIO GUTIERREZ MORENO | UBB1: OSMAN GREOGORIO GUTIERREZ MORENO | UBJ1: OSMAN GREOGORIO GUTIERREZ MORENO | UBR1: OSMAN GREOGORIO GUTIERREZ MORENO | UBZ1: OSMAN GREOGORIO GUTIERREZ MORENO | UCH1: OSMAN GREOGORIO GUTIERREZ MORENO | UCP1: OSMAN GREOGORIO GUTIERREZ MORENO | UCX1: OSMAN GREOGORIO GUTIERREZ MORENO | UDF1: OSMAN GREOGORIO GUTIERREZ MORENO | UDN1: OSMAN GREOGORIO GUTIERREZ MORENO | UDV1: OSMAN GREOGORIO GUTIERREZ MORENO | UED1: OSMAN GREOGORIO GUTIERREZ MORENO | UEL1: OSMAN GREOGORIO GUTIERREZ MORENO | UET1: OSMAN GREOGORIO GUTIERREZ MORENO | UFB1: OSMAN GREOGORIO GUTIERREZ MORENO | UFJ1: OSMAN GREOGORIO GUTIERREZ MORENO | UFR1: OSMAN GREOGORIO GUTIERREZ MORENO | UFZ1: OSMAN GREOGORIO GUTIERREZ MORENO | UGH1: OSMAN GREOGORIO GUTIERREZ MORENO | UGP1: OSMAN GREOGORIO GUTIERREZ MORENO | UGX1: OSMAN GREOGORIO GUTIERREZ MORENO | UHF1: OSMAN GREOGORIO GUTIERREZ MORENO | UHN1: OSMAN GREOGORIO GUTIERREZ MORENO | UHV1: OSMAN GREOGORIO GUTIERREZ MORENO | UID1: OSMAN GREOGORIO GUTIERREZ MORENO | UIL1: OSMAN GREOGORIO GUTIERREZ MORENO | UIT1: OSMAN GREOGORIO GUTIERREZ MORENO | UJB1: OSMAN GREOGORIO GUTIERREZ MORENO | UJJ1: OSMAN GREOGORIO GUTIERREZ MORENO | UJR1: OSMAN GREOGORIO GUTIERREZ MORENO | UJZ1: OSMAN GREOGORIO GUTIERREZ MORENO | UKH1: OSMAN GREOGORIO GUTIERREZ MORENO | UKP1: OSMAN GREOGORIO GUTIERREZ MORENO | UKX1: OSMAN GREOGORIO GUTIERREZ MORENO | ULF1: OSMAN GREOGORIO GUTIERREZ MORENO | ULN1: OSMAN GREOGORIO GUTIERREZ MORENO | ULV1: OSMAN GREOGORIO GUTIERREZ MORENO | UMD1: OSMAN GREOGORIO GUTIERREZ MORENO | UML1: OSMAN GREOGORIO GUTIERREZ MORENO | UMT1: OSMAN GREOGORIO GUTIERREZ MORENO | UNB1: OSMAN GREOGORIO GUTIERREZ MORENO | UNJ1: OSMAN GREOGORIO GUTIERREZ MORENO | UNR1: OSMAN GREOGORIO GUTIERREZ MORENO | UNZ1: OSMAN GREOGORIO GUTIERREZ MORENO | UOH1: OSMAN GREOGORIO GUTIERREZ MORENO | UOP1: OSMAN GREOGORIO GUTIERREZ MORENO | UOX1: OSMAN GREOGORIO GUTIERREZ MORENO | UPF1: OSMAN GREOGORIO GUTIERREZ MORENO | UPN1: OSMAN GREOGORIO GUTIERREZ MORENO | UPV1: OSMAN GREOGORIO GUTIERREZ MORENO | UQD1: OSMAN GREOGORIO GUTIERREZ MORENO | UQL1: OSMAN GREOGORIO GUTIERREZ MORENO | UQT1: OSMAN GREOGORIO GUTIERREZ MORENO | URB1: OSMAN GREOGORIO GUTIERREZ MORENO | URJ1: OSMAN GREOGORIO GUTIERREZ MORENO | URR1: OSMAN GREOGORIO GUTIERREZ MORENO | URZ1: OSMAN GREOGORIO GUTIERREZ MORENO | USH1: OSMAN GREOGORIO GUTIERREZ MORENO | USP1: OSMAN GREOGORIO GUTIERREZ MORENO | USX1: OSMAN GREOGORIO GUTIERREZ MORENO | UTF1: OSMAN GREOGORIO GUTIERREZ MORENO | UTN1: OSMAN GREOGORIO GUTIERREZ MORENO | UTV1: OSMAN GREOGORIO GUTIERREZ MORENO | UUD1: OSMAN GREOGORIO GUTIERREZ MORENO | UUL1: OSMAN GREOGORIO GUTIERREZ MORENO | UUT1: OSMAN GREOGORIO GUTIERREZ MORENO | UVB1: OSMAN GREOGORIO GUTIERREZ MORENO | UVJ1: OSMAN GREOGORIO GUTIERREZ MORENO | UVR1: OSMAN GREOGORIO GUTIERREZ MORENO | UVZ1: OSMAN GREOGORIO GUTIERREZ MORENO | UWH1: OSMAN GREOGORIO GUTIERREZ MORENO | UWP1: OSMAN GREOGORIO GUTIERREZ MORENO | UWX1: OSMAN GREOGORIO GUTIERREZ MORENO | UXF1: OSMAN GREOGORIO GUTIERREZ MORENO | UXN1: OSMAN GREOGORIO GUTIERREZ MORENO | UXV1: OSMAN GREOGORIO GUTIERREZ MORENO | UYD1: OSMAN GREOGORIO GUTIERREZ MORENO | UYL1: OSMAN GREOGORIO GUTIERREZ MORENO | UYT1: OSMAN GREOGORIO GUTIERREZ MORENO | UZB1: OSMAN GREOGORIO GUTIERREZ MORENO | UZJ1: OSMAN GREOGORIO GUTIERREZ MORENO | UZR1: OSMAN GREOGORIO GUTIERREZ MORENO | UZZ1: OSMAN GREOGORIO GUTIERREZ MORENO | VAH1: OSMAN GREOGORIO GUTIERREZ MORENO | VAP1: OSMAN GREOGORIO GUTIERREZ MORENO | VAX1: OSMAN GREOGORIO GUTIERREZ MORENO | VBF1: OSMAN GREOGORIO GUTIERREZ MORENO | VBN1: OSMAN GREOGORIO GUTIERREZ MORENO | VBV1: OSMAN GREOGORIO GUTIERREZ MORENO | VCD1: OSMAN GREOGORIO GUTIERREZ MORENO | VCL1: OSMAN GREOGORIO GUTIERREZ MORENO | VCT1: OSMAN GREOGORIO GUTIERREZ MORENO | VDB1: OSMAN GREOGORIO GUTIERREZ MORENO | VDJ1: OSMAN GREOGORIO GUTIERREZ MORENO | VDR1: OSMAN GREOGORIO GUTIERREZ MORENO | VDZ1: OSMAN GREOGORIO GUTIERREZ MORENO | VEH1: OSMAN GREOGORIO GUTIERREZ MORENO | VEP1: OSMAN GREOGORIO GUTIERREZ MORENO | VEX1: OSMAN GREOGORIO GUTIERREZ MORENO | VFF1: OSMAN GREOGORIO GUTIERREZ MORENO | VFN1: OSMAN GREOGORIO GUTIERREZ MORENO | VFV1: OSMAN GREOGORIO GUTIERREZ MORENO | VGD1: OSMAN GREOGORIO GUTIERREZ MORENO | VGL1: OSMAN GREOGORIO GUTIERREZ MORENO | VGT1: OSMAN GREOGORIO GUTIERREZ MORENO | VHB1: OSMAN GREOGORIO GUTIERREZ MORENO | VHJ1: OSMAN GREOGORIO GUTIERREZ MORENO | VHR1: OSMAN GREOGORIO GUTIERREZ MORENO | VHZ1: OSMAN GREOGORIO GUTIERREZ MORENO | VIH1: OSMAN GREOGORIO GUTIERREZ MORENO | VIP1: OSMAN GREOGORIO GUTIERREZ MORENO | VIX1: OSMAN GREOGORIO GUTIERREZ MORENO | VJF1: OSMAN GREOGORIO GUTIERREZ MORENO | VJN1: OSMAN GREOGORIO GUTIERREZ MORENO | VJV1: OSMAN GREOGORIO GUTIERREZ MORENO | VKD1: OSMAN GREOGORIO GUTIERREZ MORENO | VKL1: OSMAN GREOGORIO GUTIERREZ MORENO | VKT1: OSMAN GREOGORIO GUTIERREZ MORENO | VLB1: OSMAN GREOGORIO GUTIERREZ MORENO | VLJ1: OSMAN GREOGORIO GUTIERREZ MORENO | VLR1: OSMAN GREOGORIO GUTIERREZ MORENO | VLZ1: OSMAN GREOGORIO GUTIERREZ MORENO | VMH1: OSMAN GREOGORIO GUTIERREZ MORENO | VMP1: OSMAN GREOGORIO GUTIERREZ MORENO | VMX1: OSMAN GREOGORIO GUTIERREZ MORENO | VNF1: OSMAN GREOGORIO GUTIERREZ MORENO | VNN1: OSMAN GREOGORIO GUTIERREZ MORENO | VNV1: OSMAN GREOGORIO GUTIERREZ MORENO | VOD1: OSMAN GREOGORIO GUTIERREZ MORENO | VOL1: OSMAN GREOGORIO GUTIERREZ MORENO | VOT1: OSMAN GREOGORIO GUTIERREZ MORENO | VPB1: OSMAN GREOGORIO GUTIERREZ MORENO | VPJ1: OSMAN GREOGORIO GUTIERREZ MORENO | VPR1: OSMAN GREOGORIO GUTIERREZ MORENO | VPZ1: OSMAN GREOGORIO GUTIERREZ MORENO | VQH1: OSMAN GREOGORIO GUTIERREZ MORENO | VQP1: OSMAN GREOGORIO GUTIERREZ MORENO | VQX1: OSMAN GREOGORIO GUTIERREZ MORENO | VRF1: OSMAN GREOGORIO GUTIERREZ MORENO | VRN1: OSMAN GREOGORIO GUTIERREZ MORENO | VRV1: OSMAN GREOGORIO GUTIERREZ MORENO | VSD1: OSMAN GREOGORIO GUTIERREZ MORENO | VSL1: OSMAN GREOGORIO GUTIERREZ MORENO | VST1: OSMAN GREOGORIO GUTIERREZ MORENO | VTB1: OSMAN GREOGORIO GUTIERREZ MORENO | VTJ1: OSMAN GREOGORIO GUTIERREZ MORENO | VTR1: OSMAN GREOGORIO GUTIERREZ MORENO | VTZ1: OSMAN GREOGORIO GUTIERREZ MORENO | VUH1: OSMAN GREOGORIO GUTIERREZ MORENO | VUP1: OSMAN GREOGORIO GUTIERREZ MORENO | VUX1: OSMAN GREOGORIO GUTIERREZ MORENO | VVF1: OSMAN GREOGORIO GUTIERREZ MORENO | VVN1: OSMAN GREOGORIO GUTIERREZ MORENO | VVV1: OSMAN GREOGORIO GUTIERREZ MORENO | VWD1: OSMAN GREOGORIO GUTIERREZ MORENO | VWL1: OSMAN GREOGORIO GUTIERREZ MORENO | VWT1: OSMAN GREOGORIO GUTIERREZ MORENO | VXB1: OSMAN GREOGORIO GUTIERREZ MORENO | VXJ1: OSMAN GREOGORIO GUTIERREZ MORENO | VXR1: OSMAN GREOGORIO GUTIERREZ MORENO | VXZ1: OSMAN GREOGORIO GUTIERREZ MORENO | VYH1: OSMAN GREOGORIO GUTIERREZ MORENO | VYP1: OSMAN GREOGORIO GUTIERREZ MORENO | VYX1: OSMAN GREOGORIO GUTIERREZ MORENO | VZF1: OSMAN GREOGORIO GUTIERREZ MORENO | VZN1: OSMAN GREOGORIO GUTIERREZ MORENO | VZV1: OSMAN GREOGORIO GUTIERREZ MORENO | WAD1: OSMAN GREOGORIO GUTIERREZ MORENO | WAL1: OSMAN GREOGORIO GUTIERREZ MORENO | WAT1: OSMAN GREOGORIO GUTIERREZ MORENO | WBB1: OSMAN GREOGORIO GUTIERREZ MORENO | WBJ1: OSMAN GREOGORIO GUTIERREZ MORENO | WBR1: OSMAN GREOGORIO GUTIERREZ MORENO | WBZ1: OSMAN GREOGORIO GUTIERREZ MORENO | WCH1: OSMAN GREOGORIO GUTIERREZ MORENO | WCP1: OSMAN GREOGORIO GUTIERREZ MORENO | WCX1: OSMAN GREOGORIO GUTIERREZ MORENO | WDF1: OSMAN GREOGORIO GUTIERREZ MORENO | WDN1: OSMAN GREOGORIO GUTIERREZ MORENO | WDV1: OSMAN GREOGORIO GUTIERREZ MORENO | WED1: OSMAN GREOGORIO GUTIERREZ MORENO | WEL1: OSMAN GREOGORIO GUTIERREZ MORENO | WET1: OSMAN GREOGORIO GUTIERREZ MORENO | WFB1: OSMAN GREOGORIO GUTIERREZ MORENO | WFJ1: OSMAN GREOGORIO GUTIERREZ MORENO | WFR1: OSMAN GREOGORIO GUTIERREZ MORENO | WFZ1: OSMAN GREOGORIO GUTIERREZ MORENO | WGH1: OSMAN GREOGORIO GUTIERREZ MORENO | WGP1: OSMAN GREOGORIO GUTIERREZ MORENO | WGX1: OSMAN GREOGORIO GUTIERREZ MORENO | WHF1: OSMAN GREOGORIO GUTIERREZ MORENO | WHN1: OSMAN GREOGORIO GUTIERREZ MORENO | WHV1: OSMAN GREOGORIO GUTIERREZ MORENO | WID1: OSMAN GREOGORIO GUTIERREZ MORENO | WIL1: OSMAN GREOGORIO GUTIERREZ MORENO | WIT1: OSMAN GREOGORIO GUTIERREZ MORENO | WJB1: OSMAN GREOGORIO GUTIERREZ MORENO | WJJ1: OSMAN GREOGORIO GUTIERREZ MORENO | WJR1: OSMAN GREOGORIO GUTIERREZ MORENO | WJZ1: OSMAN GREOGORIO GUTIERREZ MORENO | WKH1: OSMAN GREOGORIO GUTIERREZ MORENO | WKP1: OSMAN GREOGORIO GUTIERREZ MORENO | WKX1: OSMAN GREOGORIO GUTIERREZ MORENO | WLF1: OSMAN GREOGORIO GUTIERREZ MORENO | WLN1: OSMAN GREOGORIO GUTIERREZ MORENO | WLV1: OSMAN GREOGORIO GUTIERREZ MORENO | WMD1: OSMAN GREOGORIO GUTIERREZ MORENO | WML1: OSMAN GREOGORIO GUTIERREZ MORENO | WMT1: OSMAN GREOGORIO GUTIERREZ MORENO | WNB1: OSMAN GREOGORIO GUTIERREZ MORENO | WNJ1: OSMAN GREOGORIO GUTIERREZ MORENO | WNR1: OSMAN GREOGORIO GUTIERREZ MORENO | WNZ1: OSMAN GREOGORIO GUTIERREZ MORENO | WOH1: OSMAN GREOGORIO GUTIERREZ MORENO | WOP1: OSMAN GREOGORIO GUTIERREZ MORENO | WOX1: OSMAN GREOGORIO GUTIERREZ MORENO | WPF1: OSMAN GREOGORIO GUTIERREZ MORENO | WPN1: OSMAN GREOGORIO GUTIERREZ MORENO | WPV1: OSMAN GREOGORIO GUTIERREZ MORENO | WQD1: OSMAN GREOGORIO GUTIERREZ MORENO | WQL1: OSMAN GREOGORIO GUTIERREZ MORENO | WQT1: OSMAN GREOGORIO GUTIERREZ MORENO | WRB1: OSMAN GREOGORIO GUTIERREZ MORENO | WRJ1: OSMAN GREOGORIO GUTIERREZ MORENO | WRR1: OSMAN GREOGORIO GUTIERREZ MORENO | WRZ1: OSMAN GREOGORIO GUTIERREZ MORENO | WSH1: OSMAN GREOGORIO GUTIERREZ MORENO | WSP1: OSMAN GREOGORIO GUTIERREZ MORENO | WSX1: OSMAN GREOGORIO GUTIERREZ MORENO | WTF1: OSMAN GREOGORIO GUTIERREZ MORENO | WTN1: OSMAN GREOGORIO GUTIERREZ MORENO | WTV1: OSMAN GREOGORIO GUTIERREZ MORENO | WUD1: OSMAN GREOGORIO GUTIERREZ MORENO | WUL1: OSMAN GREOGORIO GUTIERREZ MORENO | WUT1: OSMAN GREOGORIO GUTIERREZ MORENO | WVB1: OSMAN GREOGORIO GUTIERREZ MORENO | WVJ1: OSMAN GREOGORIO GUTIERREZ MORENO | WVR1: OSMAN GREOGORIO GUTIERREZ MORENO | WVZ1: OSMAN GREOGORIO GUTIERREZ MORENO | WWH1: OSMAN GREOGORIO GUTIERREZ MORENO | WWP1: OSMAN GREOGORIO GUTIERREZ MORENO | WWX1: OSMAN GREOGORIO GUTIERREZ MORENO | WXF1: OSMAN GREOGORIO GUTIERREZ MORENO | WXN1: OSMAN GREOGORIO GUTIERREZ MORENO | WXV1: OSMAN GREOGORIO GUTIERREZ MORENO | WYD1: OSMAN GREOGORIO GUTIERREZ MORENO | WYL1: OSMAN GREOGORIO GUTIERREZ MORENO | WYT1: OSMAN GREOGORIO GUTIERREZ MORENO | WZB1: OSMAN GREOGORIO GUTIERREZ MORENO | WZJ1: OSMAN GREOGORIO GUTIERREZ MORENO | WZR1: OSMAN GREOGORIO GUTIERREZ MORENO | WZZ1: OSMAN GREOGORIO GUTIERREZ MORENO | XAH1: OSMAN GREOGORIO GUTIERREZ MORENO | XAP1: OSMAN GREOGORIO GUTIERREZ MORENO | XAX1: OSMAN GREOGORIO GUTIERREZ MORENO | XBF1: OSMAN GREOGORIO GUTIERREZ MORENO | XBN1: OSMAN GREOGORIO GUTIERREZ MORENO | XBV1: OSMAN GREOGORIO GUTIERREZ MORENO | XCD1: OSMAN GREOGORIO GUTIERREZ MORENO | XCL1: OSMAN GREOGORIO GUTIERREZ MORENO | XCT1: OSMAN GREOGORIO GUTIERREZ MORENO | XDB1: OSMAN GREOGORIO GUTIERREZ MORENO | XDJ1: OSMAN GREOGORIO GUTIERREZ MORENO | XDR1: OSMAN GREOGORIO GUTIERREZ MORENO | XDZ1: OSMAN GREOGORIO GUTIERREZ MORENO | XEH1: OSMAN GREOGORIO GUTIERREZ MORENO | XEP1: OSMAN GREOGORIO GUTIERREZ MORENO | XEX1: OSMAN GREOGORIO GUTIERREZ MORENO
A2: AGRICOLA SANTA ISABEL (EL CONSUELO)
A3: PLANILLA DE SALARIO QUINCENAL
B4: =+ADMON!A5 -> QUINCENA DEL 16 AL 30 DE ABRIL - 2026
L5: 6
A6: No | B6: INSS | C6: NUMERO DE CEDULA | D6: NOMBRES Y APELLIDOS | E6: GENERO | F6: CARGO | G6: cambio del dia | H6: SALARIO DIARIO | I6: SALARIO MENSUAL | J6: I N G R E S O S | R6: RETENCIONES | X6: TOTAL | Y6: FINCA | AA6: COMISARIATO | AB6: SALARIO DEVENGADO | AC6: FIRMAS | AD6: =+P7 -> VACACIONES | AE6: =+Q7 -> 13VO MES
J7: SALARIO QUINCENAL | K7: DIAS LABORADOS | L7: total subcidio | M7: subcidio por dia | N7: DIAS SUBSIDIO | O7: TOTAL BASICO | P7: VACACIONES | Q7: 13VO MES | R7: TOTAL | T7: INSS | U7: IR | V7: ABONO POR PRESTAMOS | W7: TOTAL RETENCION | Z7: TOTAL
A9: 1 | B9: 0 | C9: 241-310384-0005C | D9: RICARDO ALBERTO PORTILLO HERRERA | E9: M | F9: RESPONSABLE ACOPIO | G9: =+#REF! -> #REF! | H9: 350 | I9: =+H9*30 -> 10500 | J9: =(I9/30*K9) -> 0 | K9: 0 | L9: =+M9*N9 -> 0 | M9: =H9*60% -> 210 | N9: 0 | O9: =+J9-P9-Q9 -> 0 | P9: =+J9/12 -> 0 | Q9: =+P9 -> 0 | R9: =+Q9+O9+P9 -> 0 | S9: =O9+P9 -> 0 | W9: =T9 -> 0 | X9: =-W9+O9+P9+Q9 -> 0 | Y9: 0 | Z9: 0 | AA9: 0 | AB9: =X9-Y9-AA9 -> 0 | AD9: 0 | AE9: 0
A10: 2 | B10: 38675494 | C10: 214-300490-0008C | D10: EVELYN JUNNIETH PORTILLO HERRERA | E10: F | F10: CAJA | G10: =+#REF! -> #REF! | H10: 320 | I10: =+H10*30 -> 9600 | J10: =(I10/30*K10) -> 0 | K10: 0 | L10: =+M10*N10 -> 0 | M10: =H10*60% -> 192 | N10: 0 | O10: =+J10-P10-Q10 -> 0 | P10: =+J10/12 -> 0 | Q10: =+P10 -> 0 | R10: =+Q10+O10+P10 -> 0 | S10: =O10+P10 -> 0 | W10: =T10 -> 0 | X10: =-W10+O10+P10+Q10 -> 0 | Y10: 0 | Z10: 0 | AA10: 0 | AB10: =X10-Y10-AA10 -> 0 | AD10: 0 | AE10: 0
D11: DUSTIN PORTILLO | E11: M | F11: ESTIBADOR | H11: 320 | I11: =+H11*30 -> 9600 | J11: =(I11/30*K11) -> 0 | K11: 0 | N11: 0 | O11: =+J11-P11-Q11 -> 0 | P11: =+J11/12 -> 0 | Q11: =+P11 -> 0 | R11: =+Q11+O11+P11 -> 0 | X11: =-W11+O11+P11+Q11 -> 0 | Z11: 0 | AB11: =X11-Y11-AA11 -> 0
A12: TOTALES | G12: =SUM(#REF!) -> #REF! | H12: =SUM(H9:H11) -> 990 | I12: =SUM(I9:I11) -> 29700 | J12: =SUM(J9:J11) -> 0 | K12: =SUM(K9:K11) -> 0 | L12: =SUM(L9:L11) -> 0 | M12: =SUM(M9:M11) -> 402 | N12: =SUM(N9:N11) -> 0 | O12: =SUM(O9:O11) -> 0 | ... AB12: =SUM(AB9:AB11) -> 0 | AD12: =SUM(AD9:AD10) -> 0 | AE12: =SUM(AE9:AE10) -> 0
C26: ELABORADO POR: | K26: REVISADO POR: | AB26: AUTORIZADO POR:
C27: =+ADMON!C30 -> Jose Martin Conrrado | K27: Lic. Sandro Osmany Gutierrez Sanchez | AB27: Lic. Osman Gregorio Gutiérrez Moreno

Sheet ACOP LA UNION
A1: OSMAN DIEGO GUTIERREZ MONTIEL
A2: AGRÍCOLA SANTA ISABEL (LA UNION)
A3: PLANILLA DE SALARIO QUINCENAL
B4: =+ADMON!A5 -> QUINCENA DEL 16 AL 30 DE ABRIL - 2026
A6: No | B6: INSS | C6: NUMERO DE CEDULA | D6: NOMBRES Y APELLIDOS | E6: GENERO | F6: CARGO | G6: SALARIO DIARIO | H6: SALARIO MENSUAL | I6: I N G R E S O S | Q6: RETENCIONES | W6: TOTAL | X6: COMISARIATO | Y6: FINCA | Z6: SALARIO DEVENGADO | AA6: FIRMAS | AD6: INSS PATRONAL | AE6: VACACIONES | AF6: 13VO MES | AG6: INATEC 2% | AH6: TOTAL GASTOS NOMINAS
I7: SALARIO QUINCENAL | J7: DIAS LABORADOS | K7: total subcidio | L7: subcidio por dia | M7: DIAS SUBSIDIO | N7: TOTAL BASICO | O7: VACACIONES | P7: 13VO MES | Q7: TOTAL | S7: INSS | T7: IR | U7: ABONO POR PRESTAMOS | V7: TOTAL RETENCION
A9: 1 | B9: 7305067 | C9: 241-160179-0002F | D9: RAUL JOSE RUIZ PINEDA | E9: M | F9: RESPONSABLE ACOPIO | G9: 350 | H9: =+G9*30 -> 10500 | I9: =(H9/30)*J9 -> 0 | J9: 0 | K9: =+L9*M9 -> 0 | L9: =G9*60% -> 210 | M9: 0 | N9: =+I9-O9-P9 -> 0 | O9: =I9/12 -> 0 | P9: =+O9 -> 0 | Q9: =+P9+N9+O9 -> 0 | R9: =N9+O9 -> 0 | S9: 0 | V9: =S9 -> 0 | W9: =-V9+N9+O9+P9 -> 0 | X9: 0 | Y9: 0 | Z9: =W9-X9-Y9 -> 0 | AB9: 0.155 | AC9: =+Q9-P9 -> 0 | AD9: =AB9*Q9 -> 0 | AE9: =+I9/12 -> 0 | AF9: =+I9/12 -> 0 | AG9: =0.02*Z9 -> 0 | AH9: =Z9+AD9+AG9+AE9+AF9 -> 0
A10: TOTALES | G10: 0 | H10: =SUM(H9:H9) -> 10500 | I10: =SUM(I9:I9) -> 0 | J10: =SUM(J9:J9) -> 0 | K10: =SUM(K9:K9) -> 0 | L10: =SUM(L9:L9) -> 210 | M10: =SUM(M9:M9) -> 0 | N10: =SUM(N9:N9) -> 0 | O10: =SUM(O9:O9) -> 0 | ... Z10: =SUM(Z9:Z9) -> 0 | AA10: "EL SEÑOR ES MI PASTOR, NADA ME FALTARA" | AB10: =SUM(#REF!) -> #REF! | AC10: =SUM(#REF!) -> #REF! | AD10: =SUM(AD9:AD9) -> 0 | AE10: =SUM(AE9:AE9) -> 0 | AF10: =SUM(AF9:AF9) -> 0 | AG10: =SUM(AG9:AG9) -> 0 | AH10: =SUM(AH9:AH9) -> 0
C24: ELABORADO POR: | J24: REVISADO POR: | Z24: AUTORIZADO POR:
C25: =+ADMON!C30 -> Jose Martin Conrrado | J25: Lic. Sandro Osmany Gutierrez Sanchez | Z25: Lic. Osman Gregorio Gutiérrez Moreno

Sheet BODEG STA Isabel
M1: YEMIN ABEL GUTIERREZ PORRAS
A2: YEMIN ABEL GUTIERREZ PORRAS
A3: AGRÍCOLA SANTA ISABEL
A4: PLANILLA DE SALARIO QUINCENAL ( BODEGA DE ACOPIO)
A5: =+ADMON!A5 -> QUINCENA DEL 16 AL 30 DE ABRIL - 2026
A7: No | B7: INSS | C7: NUMERO DE CEDULA | D7: NOMBRES Y APELLIDOS | E7: GENERO | F7: CARGO | G7: SALARIO DIARIO | H7: SALARIO MENSUAL | I7: I N G R E S O S | Q7: RETENCIONES | W7: TOTAL | X7: COMISARIATO | Y7: FINCA | Z7: SALARIO DEVENGADO | AA7: FIRMAS | AD7: INSS PATRONAL | AE7: VACACIONES | AF7: 13VO MES | AG7: INATEC 2% | AH7: TOTAL GASTOS NOMINAS
I8: SALARIO QUINCENAL | J8: DIAS LABORADOS | K8: total subcidio | L8: subcidio por dia | M8: DIAS SUBSIDIO | N8: TOTAL BASICO | O8: VACACIONES | P8: 13VO MES | Q8: TOTAL | S8: INSS | T8: IR | U8: ABONO POR PRESTAMOS | V8: TOTAL RETENCION
A10: 1 | B10: 7305067 | D10: MARIA ULDA GARCIA RIVAS | E10: F | F10: ATENCION AL CLIENTE Y CAJA | G10: 240 | H10: 0 | I10: =(H10/30)*J10 -> 0 | J10: 15 | K10: =+L10*M10 -> 0 | L10: =G10*60% -> 144 | M10: 0 | N10: =+I10-O10-P10 -> 0 | O10: 0 | P10: =+O10 -> 0 | Q10: =+P10+N10+O10 -> 0 | R10: =N10+O10 -> 0 | S10: =+R10*5% -> 0 | V10: =S10 -> 0 | W10: =-V10+N10+O10+P10 -> 0 | X10: 0 | Y10: 0 | Z10: =W10-X10-Y10 -> 0 | AB10: 0.155 | AC10: =+Q10-P10 -> 0 | AD10: =AB10*Q10 -> 0 | AE10: =+I10/12 -> 0 | AF10: =+I10/12 -> 0 | AG10: =0.02*Z10 -> 0 | AH10: =Z10+AD10+AG10+AE10+AF10 -> 0
A11: 1 | B11: 001-060383-0004D | C11: 241-240392-0004S | D11: DANIEL ANTONIO RODRIGUEZ MORALES | E11: M | F11: RESPONSABLE DE BODEGA | G11: 300 | H11: 6171.6 | I11: =(H11/30)*J11 -> 3085.8 | J11: 15 | K11: =+L11*M11 -> 0 | L11: =G11*60% -> 180 | M11: 0 | N11: =G11*J11 -> 4500 | O11: 0 | P11: 0 | Q11: =+P11+N11+O11 -> 4500 | R11: =N11+O11 -> 4500 | S11: =+R11*5% -> 225 | V11: =S11 -> 225 | W11: =-V11+N11+O11+P11 -> 4275 | X11: 0 | Y11: 2000 | Z11: =W11-X11-Y11 -> 2275 | AB11: 0.155 | AC11: =+Q11-P11 -> 4500 | AD11: =AB11*Q11 -> 697.5 | AE11: 0 | AF11: 0 | AG11: =0.02*Z11 -> 45.5 | AH11: =Z11+AD11+AG11 -> 3018
A12: TOTALES | G12: 0 | H12: =SUM(H10:H11) -> 6171.6 | I12: =SUM(I10:I11) -> 3085.8 | J12: =SUM(J10:J11) -> 30 | K12: =SUM(K10:K11) -> 0 | L12: =SUM(L10:L11) -> 324 | M12: =SUM(M10:M11) -> 0 | N12: =SUM(N10:N11) -> 4500 | O12: =SUM(O10:O11) -> 0 | Q12: =SUM(Q10:Q11) -> 4500 | R12: =SUM(R10:R11) -> 4500 | S12: =SUM(S10:S11) -> 225 | U12: =SUM(U10:U11) -> 0 | V12: =SUM(V10:V11) -> 225 | W12: =SUM(W10:W11) -> 4275 | X12: =SUM(X10:X11) -> 0 | Y12: =SUM(Y10:Y11) -> 2000 | Z12: =SUM(Z10:Z11) -> 2275 | AA12: "EL SEÑOR ES MI PASTOR, NADA ME FALTARA" | AB12: =SUM(#REF!) -> #REF! | AC12: =SUM(#REF!) -> #REF! | AD12: =SUM(AD10:AD11) -> 697.5 | AE12: =SUM(AE10:AE11) -> 0 | AF12: =SUM(AF10:AF11) -> 0 | AG12: =SUM(AG10:AG11) -> 45.5 | AH12: =SUM(AH10:AH11) -> 3018
G14: 10
G15: 350 | H15: 35.6948 | I15: =+G15*H15 -> 12493.18
I16: =+G15/H15 -> 9.8053498 | J16: =9.81*30 -> 294.3
C28: ELABORADO POR: | J28: REVISADO POR: | Z28: AUTORIZADO POR:
C29: =+'ADMON COM. '!C50:F50 -> Jose Martin Conrrado | J29: IVAN OROZCO OSEJO | Z29: LIC:OSMAN G GREGORIO GUTIERREZ MORENO

Sheet COMISARIATO INSS
A2: AGRÍCOLA SANTA ISABEL
A3: PLANILLA DE SALARIO QUINCENAL ( COMISARIATO INSS )
A4: =+ADMON!A5 -> QUINCENA DEL 16 AL 30 DE ABRIL - 2026
P5: QUINCENA DEL 16 DE ABRIL AL 30 DE ABRIL 2026
A6: No | B6: INSS | C6: NUMERO DE CEDULA | D6: NOMBRES Y APELLIDOS | E6: GENERO | F6: CARGO | G6: salario en dolares | H6: cambio del dia | I6: SALARIO DIARIO | J6: SALARIO MENSUAL | K6: I N G R E S O S | S6: RETENCIONES | Y6: TOTAL | Z6: ALIMENTACION | AA6: FINCA | AB6: SALARIO DEVENGADO | AC6: FIRMAS | AF6: INSS PATRONAL | AG6: VACACIONES | AH6: 13VO MES | AI6: INATEC 2% | AJ6: TOTAL GASTOS NOMINAS
K7: SALARIO QUINCENAL | L7: DIAS LABORADOS | M7: total subcidio | N7: subcidio por dia | O7: DIAS SUBSIDIO | P7: TOTAL BASICO | Q7: VACACIONES | R7: 13VO MES | S7: TOTAL | U7: INSS | V7: IR | W7: ABONO POR PRESTAMOS | X7: TOTAL RETENCION
A9: 1 | B9: 15384256 | D9: ZOILA YESENIA BALTODANO PALACIOS | E9: F | F9: RESPONSABLE COMISARIATO | I9: 315 | J9: 9450 | K9: =(J9)/30*L9 -> 5040 | L9: 16 | M9: =+N9*O9 -> 0 | N9: =I9*60% -> 189 | O9: 0 | P9: =+K9-Q9-R9 -> 5040 | Q9: 0 | R9: =+Q9 -> 0 | S9: =+R9+P9+Q9 -> 5040 | T9: =P9+Q9 -> 5040 | U9: =+T9*7% -> 352.8 | X9: =U9 -> 352.8 | Y9: =-X9+P9+Q9+R9 -> 4687.2 | Z9: 0 | AA9: 0 | AB9: =Y9+Z9-AA9 -> 4687.2 | AD9: 0.155 | AE9: =+S9-R9 -> 5040 | AF9: =AD9*S9 -> 781.2 | AG9: =+K9/12 -> 420 | AH9: =+K9/12 -> 420 | AI9: =0.02*AB9 -> 93.744 | AJ9: =AB9+AF9+AI9 -> 5562.144
A10: 2 | B10: 23724864 | D10: MARVIN CRUZ TALAVERA | E10: M | F10: AYUDANTE COMISARIATO | I10: 300 | J10: =+I10*30 -> 9000 | K10: =(J10)/30*L10 -> 3300 | L10: 11 | M10: =+N10*O10 -> 0 | N10: =I10*60% -> 180 | O10: 0 | P10: =+K10-Q10-R10 -> 2750 | Q10: =+K10/12 -> 275 | R10: =+Q10 -> 275 | S10: =+R10+P10+Q10 -> 3300 | T10: =P10+Q10 -> 3025 | U10: =+T10*5% -> 151.25 | X10: =U10 -> 151.25 | Y10: =-X10+P10+Q10+R10 -> 3148.75 | Z10: 0 | AA10: 0 | AB10: =Y10+Z10-AA10 -> 3148.75 | AD10: 0.155 | AE10: =+S10-R10 -> 3025 | AF10: =AD10*S10 -> 511.5 | AG10: =+K10/12 -> 275 | AH10: =+K10/12 -> 275 | AI10: =0.02*AB10 -> 62.975 | AJ10: =AB10+AF10+AI10 -> 3723.225
A11: 3 | B11: 23724864 | D11: EDWIN DE JESUS MARTINEZ PICADO | E11: M | F11: RESPONSABLE DE COMISARIATOS | I11: 330 | J11: 9900 | K11: =(J11)/30*L11 -> 4950 | L11: 15 | M11: =+N11*O11 -> 0 | N11: =I11*60% -> 198 | O11: 0 | P11: =+K11-Q11-R11 -> 4125 | Q11: =+K11/12 -> 412.5 | R11: =+Q11 -> 412.5 | S11: =+R11+P11+Q11 -> 4950 | T11: =P11+Q11 -> 4537.5 | U11: =+T11*5% -> 226.875 | X11: =U11 -> 226.875 | Y11: =-X11+P11+Q11+R11 -> 4723.125 | Z11: 0 | AA11: 0 | AB11: =Y11+Z11-AA11 -> 4723.125 | AD11: 0.155 | AE11: =+S11-R11 -> 4537.5 | AF11: =AD11*S11 -> 767.25 | AG11: =+K11/12 -> 412.5 | AH11: =+K11/12 -> 412.5 | AI11: =0.02*AB11 -> 94.4625 | AJ11: =AB11+AF11+AI11 -> 5584.8375
A12: 4 | B12: 23724864 | D12: LESLIER ALEJANDRO PALACIOS | E12: M | F12: AYUDANTE COMISARIATO | I12: 0 | J12: 0 | K12: =(J12/30)*L12 -> 0 | L12: 0 | M12: =+N12*O12 -> 0 | N12: =I12*60% -> 0 | O12: 0 | P12: =+K12-Q12-R12 -> 0 | Q12: =+K12/12 -> 0 | R12: =+Q12 -> 0 | S12: =+R12+P12+Q12 -> 0 | T12: =P12+Q12 -> 0 | U12: =+T12*5% -> 0 | X12: =U12 -> 0 | Y12: =-X12+P12+Q12+R12 -> 0 | Z12: 0 | AA12: 0 | AB12: =Y12+Z12-AA12 -> 0 | AD12: 0.155 | AE12: =+S12-R12 -> 0 | AF12: =AD12*S12 -> 0 | AH12: 0 | AI12: =0.02*AB12 -> 0 | AJ12: =AB12+AF12+AI12 -> 0
A13: TOTALES | G13: =SUM(#REF!) -> #REF! | I13: 0 | J13: =SUM(J9:J12) -> 28350 | K13: =SUM(K9:K12) -> 13290 | L13: =SUM(L9:L12) -> 42 | M13: =SUM(M9:M12) -> 0 | N13: =SUM(N9:N12) -> 567 | O13: =SUM(O9:O12) -> 0 | P13: =SUM(P9:P12) -> 11915 | Q13: =SUM(Q9:Q12) -> 687.5 | ... AB13: =SUM(AB9:AB12) -> 12559.075 | AC13: "EL SEÑOR ES MI PASTOR, NADA ME FALTARA" | AD13: =SUM(#REF!) -> #REF! | AE13: =SUM(#REF!) -> #REF! | AF13: =SUM(AF9:AF12) -> 2059.95 | AG13: =SUM(AG9:AG12) -> 1107.5 | AH13: =SUM(AH9:AH12) -> 1107.5 | AI13: =SUM(AI9:AI12) -> 251.1815 | AJ13: =SUM(AJ9:AJ12) -> 14870.206
I15: 10
I16: 350 | J16: 35.6948 | K16: =+I16*J16 -> 12493.18
K17: =+I16/J16 -> 9.8053498 | L17: =9.81*30 -> 294.3
C28: ELABORADO POR: | L28: REVISADO POR: | AB28: AUTORIZADO POR:
C29: =+'ADMON COM. '!C50:F50 -> Jose Martin Conrrado | L29: IVAN ORZCO OSEJO | AB29: LIC:OSMAN G GUTIERREZ MORENO

Sheet COMISARIATO CON INSS
A2: AGRÍCOLA SANTA ISABEL
A3: PLANILLA DEL COMISARIATO SANTA ISABEL
A4: =+'ADMON COM. '!A5:AC5 -> QUINCENA DEL 16 AL 30 DE ABRIL - 2026
